Workbook

Sheet Sheet1
A1: Citation (APA 7th-Annotated) | B1: sequence | C1: DOI if different from article or doi Alt | D1: Item number | E1: 1st Author | F1: other author(s) | G1: year | H1: Publication name | I1: DOI (or Alt) | J1: Item name | K1: Item encoded | L1: Public TSV match from AUTO_Public_TSV_FileList (generated by _tools/file_list.R; do not edit manually) | M1: Item full original title | N1: Source format | O1: N.B. | P1: Progress stage | Q1: Snapshot name if unchanged | R1: Source URL link | S1: Flags pre-addressed | T1: Flags possible | U1: Flags active (skips) | V1: Topic | W1: Taxon | X1: Main Trait(s) | Y1: Other Trait(s) | Z1: Material type (e.g. histological, MRI) | AA1: Method | AB1: Measure type | AC1: Team | AD1: Collection | AE1: Data role (primary/secondary/both) | AF1: Source (if secondary) | AG1: recommendation
A2: Andelin, A. K., Olavarria, J. F., Fine, I., Taber, E. N., Schwartz, D., Kroenke, C. D., & Stevens, A. A. (2019). The Effect of Onset Age of Visual Deprivation on Visual Cortex Surface Area Across-Species. Cereb Cortex, 29(10), 4321-4333. https://doi.org/10.1093/cercor/bhy315 | D2: Table 4 | E2: =SUBSTITUTE(SUBSTITUTE(_xlfn.TEXTBEFORE(A2,","), "-", ""), " ", "") -> Andelin | F2: {=_xlfn.LET( _xlpm.authors,_xlfn.TEXTBEFORE(A2," ("&G2&")"), _xlpm.hasAmp,ISNUMBER(SEARCH("&",_xlpm.authors)), _xlpm.hasEllipsis,ISNUMBER(SEARCH(_xlfn.UNICHAR(8230),_xlpm.authors)), _xlpm.commasBeforeAmp,IF( _xlpm.hasAmp, LEN(_xlfn.TEXTBEFORE(_xlpm.authors,"&"))-LEN(SUBSTITUTE(_xlfn.TEXTBEFORE(_xlpm.authors,"&"),",","")), 0 ), IF( _xlpm.hasEllipsis, "etal", IF( NOT(_xlpm.hasAmp), "", IF( _xlpm.commasBeforeAmp>2, "etal", SUBSTITUTE(TRIM(_xlfn.TEXTBEFORE(_xlfn.TEXTAFTER(_xlpm.authors,"& "),",")),"-","") ) ) ) )} -> etal | G2: =_xlfn.TEXTBEFORE(_xlfn.TEXTAFTER(A2, "("), ")") -> 2019 | H2: =E2 & IF(F2<>"", "_" & F2, "_") & IF(G2<>"", "_" & G2, "_") & IF(B2<>"", "_" & B2, "") -> Andelin_etal_2019 | I2: =_xlfn.LET( _xlpm.doi,IF(C2<>"",C2,_xlfn.TEXTAFTER(A2,"https://doi.org/")), SUBSTITUTE( SUBSTITUTE( SUBSTITUTE( SUBSTITUTE( _xlpm.doi, "/","%2F"), ":","%3A"), "<","%3C"), ">","%3E") ) -> 10.1093%2Fcercor%2Fbhy315 | J2: =TRIM(_xlfn.TEXTJOIN("_",FALSE(),H2,(SUBSTITUTE(SUBSTITUTE(D2," ",""), "_", "")))) -> Andelin_etal_2019_Table4 | K2: =I2 & "_" & SUBSTITUTE(SUBSTITUTE(SUBSTITUTE(D2,CHAR(160),"")," ",""),"_","") -> 10.1093%2Fcercor%2Fbhy315_Table4 | L2: {=IFERROR(INDEX(AUTO_Public_TSV_FileList!$A$1:$A$1000,MATCH(TRUE(),EXACT(K2,IFERROR(_xlfn.TEXTBEFORE(AUTO_Public_TSV_FileList!$A$1:$A$1000,".tsv"),"")),0)),"notfound")} -> 10.1093%2Fcercor%2Fbhy315_Table4.tsv | N2: table | P2: FINISHED
A3: Armstrong, E. (1979). Quantitative comparison of the hominoid thalamus. I. Specific sensory relay nuclei. Am J Phys Anthropol, 51(3), 365-382. https://doi.org/10.1002/ajpa.1330510308 | D3: Tables 1-9 | E3: =SUBSTITUTE(SUBSTITUTE(_xlfn.TEXTBEFORE(A3,","), "-", ""), " ", "") -> Armstrong | F3: {=_xlfn.LET( _xlpm.authors,_xlfn.TEXTBEFORE(A3," ("&G3&")"), _xlpm.hasAmp,ISNUMBER(SEARCH("&",_xlpm.authors)), _xlpm.hasEllipsis,ISNUMBER(SEARCH(_xlfn.UNICHAR(8230),_xlpm.authors)), _xlpm.commasBeforeAmp,IF( _xlpm.hasAmp, LEN(_xlfn.TEXTBEFORE(_xlpm.authors,"&"))-LEN(SUBSTITUTE(_xlfn.TEXTBEFORE(_xlpm.authors,"&"),",","")), 0 ), IF( _xlpm.hasEllipsis, "etal", IF( NOT(_xlpm.hasAmp), "", IF( _xlpm.commasBeforeAmp>2, "etal", SUBSTITUTE(TRIM(_xlfn.TEXTBEFORE(_xlfn.TEXTAFTER(_xlpm.authors,"& "),",")),"-","") ) ) ) )} | G3: =_xlfn.TEXTBEFORE(_xlfn.TEXTAFTER(A3, "("), ")") -> 1979 | H3: =E3 & IF(F3<>"", "_" & F3, "_") & IF(G3<>"", "_" & G3, "_") & IF(B3<>"", "_" & B3, "") -> Armstrong__1979 | I3: =_xlfn.LET(_xlpm.doi,IF(C3<>"",C3,_xlfn.TEXTAFTER(A3,"https://doi.org/")),SUBSTITUTE(SUBSTITUTE(SUBSTITUTE(SUBSTITUTE(_xlpm.doi,"/","%2F"),":","%3A"),"<","%3C"),">","%3E")) -> 10.1002%2Fajpa.1330510308 | J3: =TRIM(_xlfn.TEXTJOIN("_",FALSE(),H3,(SUBSTITUTE(SUBSTITUTE(D3," ",""), "_", "")))) -> Armstrong__1979_Tables1-9 | K3: =I3 & "_" & SUBSTITUTE(SUBSTITUTE(SUBSTITUTE(D3,CHAR(160),"")," ",""),"_","") -> 10.1002%2Fajpa.1330510308_Tables1-9 | L3: {=IFERROR(INDEX(AUTO_Public_TSV_FileList!$A$1:$A$1000,MATCH(TRUE(),EXACT(K3,IFERROR(_xlfn.TEXTBEFORE(AUTO_Public_TSV_FileList!$A$1:$A$1000,".tsv"),"")),0)),"notfound")} -> 10.1002%2Fajpa.1330510308_Tables1-9.tsv | M3: Tables 1-9. Hominoid thalamic sensory-relay nucleus volumes, neuronal densities and numbers, and neuronal-volume distributions | N3: tables | O3: Primary mixed-datatype series. Table 1 provides LGB, MGBp and VB volumes plus percent of dorsal thalamus; Tables 2-4 density; Table 5 LGB subcomponent volumes; Table 6 neuron counts; Tables 7-9 neuronal perikaryal-volume distributions. Split during build. | P3: FINISHED | R3: https://doi.org/10.1002/ajpa.1330510308 | T3: mixed datatypes; specimen abbreviations require a specimen crosswalk; some literature-comparison rows are secondary | V3: thalamic sensory relay nuclei | W3: Hominoids | X3: regional volumes; neuronal density and number; neuronal size | Y3: LGB/LGBd; MGB parvocellular; ventrobasal complex; dorsal thalamus proportion; neuronal density; neuron number; neuronal perikaryal volume | AA3: histological volumetry; neuronal density/count estimation; neuronal perikaryal morphometry | AB3: volume + cell density/count + neuronal perikaryal volume | AC3: Armstrong | AE3: both | AG3: Keep specimen-level records and separate regional volume, cell density/count, and cell-size outputs.
A4: Ashwell, K. W. S. (2020). Quantitative analysis of cerebellar morphology in monotreme, metatherian and eutherian mammals. Zoology (Jena), 139, 125753. https://doi.org/10.1016/j.zool.2020.125753 | D4: Supplementary Table | E4: =SUBSTITUTE(SUBSTITUTE(_xlfn.TEXTBEFORE(A4,","), "-", ""), " ", "") -> Ashwell | F4: {=_xlfn.LET( _xlpm.authors,_xlfn.TEXTBEFORE(A4," ("&G4&")"), _xlpm.hasAmp,ISNUMBER(SEARCH("&",_xlpm.authors)), _xlpm.hasEllipsis,ISNUMBER(SEARCH(_xlfn.UNICHAR(8230),_xlpm.authors)), _xlpm.commasBeforeAmp,IF( _xlpm.hasAmp, LEN(_xlfn.TEXTBEFORE(_xlpm.authors,"&"))-LEN(SUBSTITUTE(_xlfn.TEXTBEFORE(_xlpm.authors,"&"),",","")), 0 ), IF( _xlpm.hasEllipsis, "etal", IF( NOT(_xlpm.hasAmp), "", IF( _xlpm.commasBeforeAmp>2, "etal", SUBSTITUTE(TRIM(_xlfn.TEXTBEFORE(_xlfn.TEXTAFTER(_xlpm.authors,"& "),",")),"-","") ) ) ) )} | G4: =_xlfn.TEXTBEFORE(_xlfn.TEXTAFTER(A4, "("), ")") -> 2020 | H4: =E4 & IF(F4<>"", "_" & F4, "_") & IF(G4<>"", "_" & G4, "_") & IF(B4<>"", "_" & B4, "") -> Ashwell__2020 | I4: =_xlfn.LET( _xlpm.doi,IF(C4<>"",C4,_xlfn.TEXTAFTER(A4,"https://doi.org/")), SUBSTITUTE( SUBSTITUTE( SUBSTITUTE( SUBSTITUTE( _xlpm.doi, "/","%2F"), ":","%3A"), "<","%3C"), ">","%3E") ) -> 10.1016%2Fj.zool.2020.125753 | J4: =TRIM(_xlfn.TEXTJOIN("_",FALSE(),H4,(SUBSTITUTE(SUBSTITUTE(D4," ",""), "_", "")))) -> Ashwell__2020_SupplementaryTable | K4: =I4 & "_" & SUBSTITUTE(SUBSTITUTE(SUBSTITUTE(D4,CHAR(160),"")," ",""),"_","") -> 10.1016%2Fj.zool.2020.125753_SupplementaryTable | L4: {=IFERROR(INDEX(AUTO_Public_TSV_FileList!$A$1:$A$1000,MATCH(TRUE(),EXACT(K4,IFERROR(_xlfn.TEXTBEFORE(AUTO_Public_TSV_FileList!$A$1:$A$1000,".tsv"),"")),0)),"notfound")} -> 10.1016%2Fj.zool.2020.125753_SupplementaryTable.tsv | M4: Supplementary Table. Cerebellar Morphology Data | P4: FINISHED | AC4: Ashwell
A5: Avelino-de-Souza, K., Patzke, N., Karlsson, K. A. E., Manger, P. R., & Herculano-Houzel, S. (2025). Cellular Composition of the Brain of a Northern Minke Whale. J Comp Neurol, 533(9), e70089. https://doi.org/10.1002/cne.70089 | D5: TABLE 1 | E5: =SUBSTITUTE(SUBSTITUTE(_xlfn.TEXTBEFORE(A5,","), "-", ""), " ", "") -> AvelinodeSouza | F5: {=_xlfn.LET( _xlpm.authors,_xlfn.TEXTBEFORE(A5," ("&G5&")"), _xlpm.hasAmp,ISNUMBER(SEARCH("&",_xlpm.authors)), _xlpm.hasEllipsis,ISNUMBER(SEARCH(_xlfn.UNICHAR(8230),_xlpm.authors)), _xlpm.commasBeforeAmp,IF( _xlpm.hasAmp, LEN(_xlfn.TEXTBEFORE(_xlpm.authors,"&"))-LEN(SUBSTITUTE(_xlfn.TEXTBEFORE(_xlpm.authors,"&"),",","")), 0 ), IF( _xlpm.hasEllipsis, "etal", IF( NOT(_xlpm.hasAmp), "", IF( _xlpm.commasBeforeAmp>2, "etal", SUBSTITUTE(TRIM(_xlfn.TEXTBEFORE(_xlfn.TEXTAFTER(_xlpm.authors,"& "),",")),"-","") ) ) ) )} -> etal | G5: =_xlfn.TEXTBEFORE(_xlfn.TEXTAFTER(A5, "("), ")") -> 2025 | H5: =E5 & IF(F5<>"", "_" & F5, "_") & IF(G5<>"", "_" & G5, "_") & IF(B5<>"", "_" & B5, "") -> AvelinodeSouza_etal_2025 | I5: =_xlfn.LET( _xlpm.doi,IF(C5<>"",C5,_xlfn.TEXTAFTER(A5,"https://doi.org/")), SUBSTITUTE( SUBSTITUTE( SUBSTITUTE( SUBSTITUTE( _xlpm.doi, "/","%2F"), ":","%3A"), "<","%3C"), ">","%3E") ) -> 10.1002%2Fcne.70089 | J5: =TRIM(_xlfn.TEXTJOIN("_",FALSE(),H5,(SUBSTITUTE(SUBSTITUTE(D5," ",""), "_", "")))) -> AvelinodeSouza_etal_2025_TABLE1 | K5: =I5 & "_" & SUBSTITUTE(SUBSTITUTE(SUBSTITUTE(D5,CHAR(160),"")," ",""),"_","") -> 10.1002%2Fcne.70089_TABLE1 | L5: {=IFERROR(INDEX(AUTO_Public_TSV_FileList!$A$1:$A$1000,MATCH(TRUE(),EXACT(K5,IFERROR(_xlfn.TEXTBEFORE(AUTO_Public_TSV_FileList!$A$1:$A$1000,".tsv"),"")),0)),"notfound")} -> 10.1002%2Fcne.70089_TABLE1.tsv | M5: Table 1. Cellular composition of the brain of a Northern minke whale (Balaenoptera acutorostrata) | N5: table | P5: FINISHED | R5: https://doi.org/10.1002/cne.70089 | W5: Cetaceans & others | X5: neuron number | AA5: isotropic fractionator | AB5: cell count | AC5: HH | AE5: primary
A6: Baker, J., Barton, R. A., & Venditti, C. (2025). Human dexterity and brains evolved hand in hand. Communications Biology, 8(1). https://doi.org/10.1038/s42003-025-08686-5 | D6: Supplementary Data 1 | E6: =SUBSTITUTE(SUBSTITUTE(_xlfn.TEXTBEFORE(A6,","), "-", ""), " ", "") -> Baker | F6: {=_xlfn.LET( _xlpm.authors,_xlfn.TEXTBEFORE(A6," ("&G6&")"), _xlpm.hasAmp,ISNUMBER(SEARCH("&",_xlpm.authors)), _xlpm.hasEllipsis,ISNUMBER(SEARCH(_xlfn.UNICHAR(8230),_xlpm.authors)), _xlpm.commasBeforeAmp,IF( _xlpm.hasAmp, LEN(_xlfn.TEXTBEFORE(_xlpm.authors,"&"))-LEN(SUBSTITUTE(_xlfn.TEXTBEFORE(_xlpm.authors,"&"),",","")), 0 ), IF( _xlpm.hasEllipsis, "etal", IF( NOT(_xlpm.hasAmp), "", IF( _xlpm.commasBeforeAmp>2, "etal", SUBSTITUTE(TRIM(_xlfn.TEXTBEFORE(_xlfn.TEXTAFTER(_xlpm.authors,"& "),",")),"-","") ) ) ) )} -> etal | G6: =_xlfn.TEXTBEFORE(_xlfn.TEXTAFTER(A6, "("), ")") -> 2025 | H6: =E6 & IF(F6<>"", "_" & F6, "_") & IF(G6<>"", "_" & G6, "_") & IF(B6<>"", "_" & B6, "") -> Baker_etal_2025 | I6: =_xlfn.LET( _xlpm.doi,IF(C6<>"",C6,_xlfn.TEXTAFTER(A6,"https://doi.org/")), SUBSTITUTE( SUBSTITUTE( SUBSTITUTE( SUBSTITUTE( _xlpm.doi, "/","%2F"), ":","%3A"), "<","%3C"), ">","%3E") ) -> 10.1038%2Fs42003-025-08686-5 | J6: =TRIM(_xlfn.TEXTJOIN("_",FALSE(),H6,(SUBSTITUTE(SUBSTITUTE(D6," ",""), "_", "")))) -> Baker_etal_2025_SupplementaryData1 | K6: =I6 & "_" & SUBSTITUTE(SUBSTITUTE(SUBSTITUTE(D6,CHAR(160),"")," ",""),"_","") -> 10.1038%2Fs42003-025-08686-5_SupplementaryData1 | L6: {=IFERROR(INDEX(AUTO_Public_TSV_FileList!$A$1:$A$1000,MATCH(TRUE(),EXACT(K6,IFERROR(_xlfn.TEXTBEFORE(AUTO_Public_TSV_FileList!$A$1:$A$1000,".tsv"),"")),0)),"notfound")} -> 10.1038%2Fs42003-025-08686-5_SupplementaryData1.tsv | P6: FINISHED
A7: Balzeau, A., Holloway, R. L., & Grimaud-Hervé, D. (2012). Variations and asymmetries in regional brain surface in the genus Homo. J Hum Evol, 62(6), 696-706. https://doi.org/10.1016/j.jhevol.2012.03.007 | D7: Table 2 | E7: =SUBSTITUTE(SUBSTITUTE(_xlfn.TEXTBEFORE(A7,","), "-", ""), " ", "") -> Balzeau | F7: {=_xlfn.LET( _xlpm.authors,_xlfn.TEXTBEFORE(A7," ("&G7&")"), _xlpm.hasAmp,ISNUMBER(SEARCH("&",_xlpm.authors)), _xlpm.hasEllipsis,ISNUMBER(SEARCH(_xlfn.UNICHAR(8230),_xlpm.authors)), _xlpm.commasBeforeAmp,IF( _xlpm.hasAmp, LEN(_xlfn.TEXTBEFORE(_xlpm.authors,"&"))-LEN(SUBSTITUTE(_xlfn.TEXTBEFORE(_xlpm.authors,"&"),",","")), 0 ), IF( _xlpm.hasEllipsis, "etal", IF( NOT(_xlpm.hasAmp), "", IF( _xlpm.commasBeforeAmp>2, "etal", SUBSTITUTE(TRIM(_xlfn.TEXTBEFORE(_xlfn.TEXTAFTER(_xlpm.authors,"& "),",")),"-","") ) ) ) )} -> etal | G7: =_xlfn.TEXTBEFORE(_xlfn.TEXTAFTER(A7, "("), ")") -> 2012 | H7: =E7 & IF(F7<>"", "_" & F7, "_") & IF(G7<>"", "_" & G7, "_") & IF(B7<>"", "_" & B7, "") -> Balzeau_etal_2012 | I7: =_xlfn.LET( _xlpm.doi,IF(C7<>"",C7,_xlfn.TEXTAFTER(A7,"https://doi.org/")), SUBSTITUTE( SUBSTITUTE( SUBSTITUTE( SUBSTITUTE( _xlpm.doi, "/","%2F"), ":","%3A"), "<","%3C"), ">","%3E") ) -> 10.1016%2Fj.jhevol.2012.03.007 | J7: =TRIM(_xlfn.TEXTJOIN("_",FALSE(),H7,(SUBSTITUTE(SUBSTITUTE(D7," ",""), "_", "")))) -> Balzeau_etal_2012_Table2 | K7: =I7 & "_" & SUBSTITUTE(SUBSTITUTE(SUBSTITUTE(D7,CHAR(160),"")," ",""),"_","") -> 10.1016%2Fj.jhevol.2012.03.007_Table2 | L7: {=IFERROR(INDEX(AUTO_Public_TSV_FileList!$A$1:$A$1000,MATCH(TRUE(),EXACT(K7,IFERROR(_xlfn.TEXTBEFORE(AUTO_Public_TSV_FileList!$A$1:$A$1000,".tsv"),"")),0)),"notfound")} -> 10.1016%2Fj.jhevol.2012.03.007_Table2.tsv | M7: Table 2. Regression results for the relationship between endocranial volume and the surface of the frontal, parieto-temporal and occipital lobes. | P7: FINISHED
A8: Balzeau, A., Holloway, R. L., & Grimaud-Hervé, D. (2012). Variations and asymmetries in regional brain surface in the genus Homo. J Hum Evol, 62(6), 696-706. https://doi.org/10.1016/j.jhevol.2012.03.007 | D8: Table 3 | E8: =SUBSTITUTE(SUBSTITUTE(_xlfn.TEXTBEFORE(A8,","), "-", ""), " ", "") -> Balzeau | F8: {=_xlfn.LET( _xlpm.authors,_xlfn.TEXTBEFORE(A8," ("&G8&")"), _xlpm.hasAmp,ISNUMBER(SEARCH("&",_xlpm.authors)), _xlpm.hasEllipsis,ISNUMBER(SEARCH(_xlfn.UNICHAR(8230),_xlpm.authors)), _xlpm.commasBeforeAmp,IF( _xlpm.hasAmp, LEN(_xlfn.TEXTBEFORE(_xlpm.authors,"&"))-LEN(SUBSTITUTE(_xlfn.TEXTBEFORE(_xlpm.authors,"&"),",","")), 0 ), IF( _xlpm.hasEllipsis, "etal", IF( NOT(_xlpm.hasAmp), "", IF( _xlpm.commasBeforeAmp>2, "etal", SUBSTITUTE(TRIM(_xlfn.TEXTBEFORE(_xlfn.TEXTAFTER(_xlpm.authors,"& "),",")),"-","") ) ) ) )} -> etal | G8: =_xlfn.TEXTBEFORE(_xlfn.TEXTAFTER(A8, "("), ")") -> 2012 | H8: =E8 & IF(F8<>"", "_" & F8, "_") & IF(G8<>"", "_" & G8, "_") & IF(B8<>"", "_" & B8, "") -> Balzeau_etal_2012 | I8: =_xlfn.LET( _xlpm.doi,IF(C8<>"",C8,_xlfn.TEXTAFTER(A8,"https://doi.org/")), SUBSTITUTE( SUBSTITUTE( SUBSTITUTE( SUBSTITUTE( _xlpm.doi, "/","%2F"), ":","%3A"), "<","%3C"), ">","%3E") ) -> 10.1016%2Fj.jhevol.2012.03.007 | J8: =TRIM(_xlfn.TEXTJOIN("_",FALSE(),H8,(SUBSTITUTE(SUBSTITUTE(D8," ",""), "_", "")))) -> Balzeau_etal_2012_Table3 | K8: =I8 & "_" & SUBSTITUTE(SUBSTITUTE(SUBSTITUTE(D8,CHAR(160),"")," ",""),"_","") -> 10.1016%2Fj.jhevol.2012.03.007_Table3 | L8: {=IFERROR(INDEX(AUTO_Public_TSV_FileList!$A$1:$A$1000,MATCH(TRUE(),EXACT(K8,IFERROR(_xlfn.TEXTBEFORE(AUTO_Public_TSV_FileList!$A$1:$A$1000,".tsv"),"")),0)),"notfound")} -> 10.1016%2Fj.jhevol.2012.03.007_Table3.tsv | M8: Table 3 Size-corrected dimensions for the surface of the frontal, parieto-temporal and occipital lobes in the different analysed samples. | P8: FINISHED
A9: Balzeau, A., Holloway, R. L., & Grimaud-Hervé, D. (2012). Variations and asymmetries in regional brain surface in the genus Homo. J Hum Evol, 62(6), 696-706. https://doi.org/10.1016/j.jhevol.2012.03.007 | D9: Table 5 | E9: =SUBSTITUTE(SUBSTITUTE(_xlfn.TEXTBEFORE(A9,","), "-", ""), " ", "") -> Balzeau | F9: {=_xlfn.LET( _xlpm.authors,_xlfn.TEXTBEFORE(A9," ("&G9&")"), _xlpm.hasAmp,ISNUMBER(SEARCH("&",_xlpm.authors)), _xlpm.hasEllipsis,ISNUMBER(SEARCH(_xlfn.UNICHAR(8230),_xlpm.authors)), _xlpm.commasBeforeAmp,IF( _xlpm.hasAmp, LEN(_xlfn.TEXTBEFORE(_xlpm.authors,"&"))-LEN(SUBSTITUTE(_xlfn.TEXTBEFORE(_xlpm.authors,"&"),",","")), 0 ), IF( _xlpm.hasEllipsis, "etal", IF( NOT(_xlpm.hasAmp), "", IF( _xlpm.commasBeforeAmp>2, "etal", SUBSTITUTE(TRIM(_xlfn.TEXTBEFORE(_xlfn.TEXTAFTER(_xlpm.authors,"& "),",")),"-","") ) ) ) )} -> etal | G9: =_xlfn.TEXTBEFORE(_xlfn.TEXTAFTER(A9, "("), ")") -> 2012 | H9: =E9 & IF(F9<>"", "_" & F9, "_") & IF(G9<>"", "_" & G9, "_") & IF(B9<>"", "_" & B9, "") -> Balzeau_etal_2012 | I9: =_xlfn.LET( _xlpm.doi,IF(C9<>"",C9,_xlfn.TEXTAFTER(A9,"https://doi.org/")), SUBSTITUTE( SUBSTITUTE( SUBSTITUTE( SUBSTITUTE( _xlpm.doi, "/","%2F"), ":","%3A"), "<","%3C"), ">","%3E") ) -> 10.1016%2Fj.jhevol.2012.03.007 | J9: =TRIM(_xlfn.TEXTJOIN("_",FALSE(),H9,(SUBSTITUTE(SUBSTITUTE(D9," ",""), "_", "")))) -> Balzeau_etal_2012_Table5 | K9: =I9 & "_" & SUBSTITUTE(SUBSTITUTE(SUBSTITUTE(D9,CHAR(160),"")," ",""),"_","") -> 10.1016%2Fj.jhevol.2012.03.007_Table5 | L9: {=IFERROR(INDEX(AUTO_Public_TSV_FileList!$A$1:$A$1000,MATCH(TRUE(),EXACT(K9,IFERROR(_xlfn.TEXTBEFORE(AUTO_Public_TSV_FileList!$A$1:$A$1000,".tsv"),"")),0)),"notfound")} -> 10.1016%2Fj.jhevol.2012.03.007_Table5.tsv | M9: Table 5 Percentage contribution of frontal, parieto-temporal and occipital lobes to the hemispheres. | P9: FINISHED
A10: Barbeito-Andrés, J., Castro-Fonseca, E., Qiu, L. R., Bernal, V., Lent, R., Henkelman, M., Lukowiak, K., Gleiser, P. M., Hallgrímsson, B., & González, P. N. (2019). Region-specific changes in Mus musculus brain size and cell composition under chronic nutrient restriction. J Exp Biol, 222(Pt 17). https://doi.org/10.1242/jeb.204651 | D10: cell density | E10: =SUBSTITUTE(SUBSTITUTE(_xlfn.TEXTBEFORE(A10,","), "-", ""), " ", "") -> BarbeitoAndrés | F10: {=_xlfn.LET( _xlpm.authors,_xlfn.TEXTBEFORE(A10," ("&G10&")"), _xlpm.hasAmp,ISNUMBER(SEARCH("&",_xlpm.authors)), _xlpm.hasEllipsis,ISNUMBER(SEARCH(_xlfn.UNICHAR(8230),_xlpm.authors)), _xlpm.commasBeforeAmp,IF( _xlpm.hasAmp, LEN(_xlfn.TEXTBEFORE(_xlpm.authors,"&"))-LEN(SUBSTITUTE(_xlfn.TEXTBEFORE(_xlpm.authors,"&"),",","")), 0 ), IF( _xlpm.hasEllipsis, "etal", IF( NOT(_xlpm.hasAmp), "", IF( _xlpm.commasBeforeAmp>2, "etal", SUBSTITUTE(TRIM(_xlfn.TEXTBEFORE(_xlfn.TEXTAFTER(_xlpm.authors,"& "),",")),"-","") ) ) ) )} -> etal | G10: =_xlfn.TEXTBEFORE(_xlfn.TEXTAFTER(A10, "("), ")") -> 2019 | H10: =E10 & IF(F10<>"", "_" & F10, "_") & IF(G10<>"", "_" & G10, "_") & IF(B10<>"", "_" & B10, "") -> BarbeitoAndrés_etal_2019 | I10: =_xlfn.LET( _xlpm.doi,IF(C10<>"",C10,_xlfn.TEXTAFTER(A10,"https://doi.org/")), SUBSTITUTE( SUBSTITUTE( SUBSTITUTE( SUBSTITUTE( _xlpm.doi, "/","%2F"), ":","%3A"), "<","%3C"), ">","%3E") ) -> 10.1242%2Fjeb.204651 | J10: =TRIM(_xlfn.TEXTJOIN("_",FALSE(),H10,(SUBSTITUTE(SUBSTITUTE(D10," ",""), "_", "")))) -> BarbeitoAndrés_etal_2019_celldensity | K10: =I10 & "_" & SUBSTITUTE(SUBSTITUTE(SUBSTITUTE(D10,CHAR(160),"")," ",""),"_","") -> 10.1242%2Fjeb.204651_celldensity | L10: {=IFERROR(INDEX(AUTO_Public_TSV_FileList!$A$1:$A$1000,MATCH(TRUE(),EXACT(K10,IFERROR(_xlfn.TEXTBEFORE(AUTO_Public_TSV_FileList!$A$1:$A$1000,".tsv"),"")),0)),"notfound")} -> 10.1242%2Fjeb.204651_celldensity.tsv | P10: FINISHED | AA10: isotropic fractionator | AB10: cell count
A11: Barbeito-Andrés, J., Castro-Fonseca, E., Qiu, L. R., Bernal, V., Lent, R., Henkelman, M., Lukowiak, K., Gleiser, P. M., Hallgrímsson, B., & González, P. N. (2019). Region-specific changes in Mus musculus brain size and cell composition under chronic nutrient restriction. J Exp Biol, 222(Pt 17). https://doi.org/10.1242/jeb.204651 | D11: cell number | E11: =SUBSTITUTE(SUBSTITUTE(_xlfn.TEXTBEFORE(A11,","), "-", ""), " ", "") -> BarbeitoAndrés | F11: {=_xlfn.LET( _xlpm.authors,_xlfn.TEXTBEFORE(A11," ("&G11&")"), _xlpm.hasAmp,ISNUMBER(SEARCH("&",_xlpm.authors)), _xlpm.hasEllipsis,ISNUMBER(SEARCH(_xlfn.UNICHAR(8230),_xlpm.authors)), _xlpm.commasBeforeAmp,IF( _xlpm.hasAmp, LEN(_xlfn.TEXTBEFORE(_xlpm.authors,"&"))-LEN(SUBSTITUTE(_xlfn.TEXTBEFORE(_xlpm.authors,"&"),",","")), 0 ), IF( _xlpm.hasEllipsis, "etal", IF( NOT(_xlpm.hasAmp), "", IF( _xlpm.commasBeforeAmp>2, "etal", SUBSTITUTE(TRIM(_xlfn.TEXTBEFORE(_xlfn.TEXTAFTER(_xlpm.authors,"& "),",")),"-","") ) ) ) )} -> etal | G11: =_xlfn.TEXTBEFORE(_xlfn.TEXTAFTER(A11, "("), ")") -> 2019 | H11: =E11 & IF(F11<>"", "_" & F11, "_") & IF(G11<>"", "_" & G11, "_") & IF(B11<>"", "_" & B11, "") -> BarbeitoAndrés_etal_2019 | I11: =_xlfn.LET( _xlpm.doi,IF(C11<>"",C11,_xlfn.TEXTAFTER(A11,"https://doi.org/")), SUBSTITUTE( SUBSTITUTE( SUBSTITUTE( SUBSTITUTE( _xlpm.doi, "/","%2F"), ":","%3A"), "<","%3C"), ">","%3E") ) -> 10.1242%2Fjeb.204651 | J11: =TRIM(_xlfn.TEXTJOIN("_",FALSE(),H11,(SUBSTITUTE(SUBSTITUTE(D11," ",""), "_", "")))) -> BarbeitoAndrés_etal_2019_cellnumber | K11: =I11 & "_" & SUBSTITUTE(SUBSTITUTE(SUBSTITUTE(D11,CHAR(160),"")," ",""),"_","") -> 10.1242%2Fjeb.204651_cellnumber | L11: {=IFERROR(INDEX(AUTO_Public_TSV_FileList!$A$1:$A$1000,MATCH(TRUE(),EXACT(K11,IFERROR(_xlfn.TEXTBEFORE(AUTO_Public_TSV_FileList!$A$1:$A$1000,".tsv"),"")),0)),"notfound")} -> 10.1242%2Fjeb.204651_cellnumber.tsv | P11: FINISHED | AA11: isotropic fractionator | AB11: cell count
A12: Barbeito-Andrés, J., Castro-Fonseca, E., Qiu, L. R., Bernal, V., Lent, R., Henkelman, M., Lukowiak, K., Gleiser, P. M., Hallgrímsson, B., & González, P. N. (2019). Region-specific changes in Mus musculus brain size and cell composition under chronic nutrient restriction. J Exp Biol, 222(Pt 17). https://doi.org/10.1242/jeb.204651 | D12: volumes | E12: =SUBSTITUTE(SUBSTITUTE(_xlfn.TEXTBEFORE(A12,","), "-", ""), " ", "") -> BarbeitoAndrés | F12: {=_xlfn.LET( _xlpm.authors,_xlfn.TEXTBEFORE(A12," ("&G12&")"), _xlpm.hasAmp,ISNUMBER(SEARCH("&",_xlpm.authors)), _xlpm.hasEllipsis,ISNUMBER(SEARCH(_xlfn.UNICHAR(8230),_xlpm.authors)), _xlpm.commasBeforeAmp,IF( _xlpm.hasAmp, LEN(_xlfn.TEXTBEFORE(_xlpm.authors,"&"))-LEN(SUBSTITUTE(_xlfn.TEXTBEFORE(_xlpm.authors,"&"),",","")), 0 ), IF( _xlpm.hasEllipsis, "etal", IF( NOT(_xlpm.hasAmp), "", IF( _xlpm.commasBeforeAmp>2, "etal", SUBSTITUTE(TRIM(_xlfn.TEXTBEFORE(_xlfn.TEXTAFTER(_xlpm.authors,"& "),",")),"-","") ) ) ) )} -> etal | G12: =_xlfn.TEXTBEFORE(_xlfn.TEXTAFTER(A12, "("), ")") -> 2019 | H12: =E12 & IF(F12<>"", "_" & F12, "_") & IF(G12<>"", "_" & G12, "_") & IF(B12<>"", "_" & B12, "") -> BarbeitoAndrés_etal_2019 | I12: =_xlfn.LET( _xlpm.doi,IF(C12<>"",C12,_xlfn.TEXTAFTER(A12,"https://doi.org/")), SUBSTITUTE( SUBSTITUTE( SUBSTITUTE( SUBSTITUTE( _xlpm.doi, "/","%2F"), ":","%3A"), "<","%3C"), ">","%3E") ) -> 10.1242%2Fjeb.204651 | J12: =TRIM(_xlfn.TEXTJOIN("_",FALSE(),H12,(SUBSTITUTE(SUBSTITUTE(D12," ",""), "_", "")))) -> BarbeitoAndrés_etal_2019_volumes | K12: =I12 & "_" & SUBSTITUTE(SUBSTITUTE(SUBSTITUTE(D12,CHAR(160),"")," ",""),"_","") -> 10.1242%2Fjeb.204651_volumes | L12: {=IFERROR(INDEX(AUTO_Public_TSV_FileList!$A$1:$A$1000,MATCH(TRUE(),EXACT(K12,IFERROR(_xlfn.TEXTBEFORE(AUTO_Public_TSV_FileList!$A$1:$A$1000,".tsv"),"")),0)),"notfound")} -> 10.1242%2Fjeb.204651_volumes.tsv | P12: FINISHED | AA12: isotropic fractionator | AB12: cell count
A13: Barger, N., Hanson, K. L., Teffer, K., Schenker-Ahmed, N. M., & Semendeferi, K. (2014). Evidence for evolutionary specialization in human limbic structures. Front Hum Neurosci, 8, 277. https://doi.org/10.3389/fnhum.2014.00277 | D13: Table 1 | E13: =SUBSTITUTE(SUBSTITUTE(_xlfn.TEXTBEFORE(A13,","), "-", ""), " ", "") -> Barger | F13: {=_xlfn.LET( _xlpm.authors,_xlfn.TEXTBEFORE(A13," ("&G13&")"), _xlpm.hasAmp,ISNUMBER(SEARCH("&",_xlpm.authors)), _xlpm.hasEllipsis,ISNUMBER(SEARCH(_xlfn.UNICHAR(8230),_xlpm.authors)), _xlpm.commasBeforeAmp,IF( _xlpm.hasAmp, LEN(_xlfn.TEXTBEFORE(_xlpm.authors,"&"))-LEN(SUBSTITUTE(_xlfn.TEXTBEFORE(_xlpm.authors,"&"),",","")), 0 ), IF( _xlpm.hasEllipsis, "etal", IF( NOT(_xlpm.hasAmp), "", IF( _xlpm.commasBeforeAmp>2, "etal", SUBSTITUTE(TRIM(_xlfn.TEXTBEFORE(_xlfn.TEXTAFTER(_xlpm.authors,"& "),",")),"-","") ) ) ) )} -> etal | G13: =_xlfn.TEXTBEFORE(_xlfn.TEXTAFTER(A13, "("), ")") -> 2014 | H13: =E13 & IF(F13<>"", "_" & F13, "_") & IF(G13<>"", "_" & G13, "_") & IF(B13<>"", "_" & B13, "") -> Barger_etal_2014 | I13: =_xlfn.LET( _xlpm.doi,IF(C13<>"",C13,_xlfn.TEXTAFTER(A13,"https://doi.org/")), SUBSTITUTE( SUBSTITUTE( SUBSTITUTE( SUBSTITUTE( _xlpm.doi, "/","%2F"), ":","%3A"), "<","%3C"), ">","%3E") ) -> 10.3389%2Ffnhum.2014.00277 | J13: =TRIM(_xlfn.TEXTJOIN("_",FALSE(),H13,(SUBSTITUTE(SUBSTITUTE(D13," ",""), "_", "")))) -> Barger_etal_2014_Table1 | K13: =I13 & "_" & SUBSTITUTE(SUBSTITUTE(SUBSTITUTE(D13,CHAR(160),"")," ",""),"_","") -> 10.3389%2Ffnhum.2014.00277_Table1 | L13: {=IFERROR(INDEX(AUTO_Public_TSV_FileList!$A$1:$A$1000,MATCH(TRUE(),EXACT(K13,IFERROR(_xlfn.TEXTBEFORE(AUTO_Public_TSV_FileList!$A$1:$A$1000,".tsv"),"")),0)),"notfound")} -> 10.3389%2Ffnhum.2014.00277_Table1.tsv | M13: Table 1 | Volume of amygdala, hippocampus, and striatum in hominoid species collected with stereological methods. | P13: FINISHED | Z13: histological sections | AC13: Zilles | AD13: Zilles
A14: Barger, N., Stefanacci, L., & Semendeferi, K. (2007). A comparative volumetric analysis of the amygdaloid complex and basolateral division in the human and ape brain. Am J Phys Anthropol, 134(3), 392-403. https://doi.org/10.1002/ajpa.20684 | D14: TABLE 1 | E14: =SUBSTITUTE(SUBSTITUTE(_xlfn.TEXTBEFORE(A14,","), "-", ""), " ", "") -> Barger | F14: {=_xlfn.LET( _xlpm.authors,_xlfn.TEXTBEFORE(A14," ("&G14&")"), _xlpm.hasAmp,ISNUMBER(SEARCH("&",_xlpm.authors)), _xlpm.hasEllipsis,ISNUMBER(SEARCH(_xlfn.UNICHAR(8230),_xlpm.authors)), _xlpm.commasBeforeAmp,IF( _xlpm.hasAmp, LEN(_xlfn.TEXTBEFORE(_xlpm.authors,"&"))-LEN(SUBSTITUTE(_xlfn.TEXTBEFORE(_xlpm.authors,"&"),",","")), 0 ), IF( _xlpm.hasEllipsis, "etal", IF( NOT(_xlpm.hasAmp), "", IF( _xlpm.commasBeforeAmp>2, "etal", SUBSTITUTE(TRIM(_xlfn.TEXTBEFORE(_xlfn.TEXTAFTER(_xlpm.authors,"& "),",")),"-","") ) ) ) )} -> etal | G14: =_xlfn.TEXTBEFORE(_xlfn.TEXTAFTER(A14, "("), ")") -> 2007 | H14: =E14 & IF(F14<>"", "_" & F14, "_") & IF(G14<>"", "_" & G14, "_") & IF(B14<>"", "_" & B14, "") -> Barger_etal_2007 | I14: =_xlfn.LET( _xlpm.doi,IF(C14<>"",C14,_xlfn.TEXTAFTER(A14,"https://doi.org/")), SUBSTITUTE( SUBSTITUTE( SUBSTITUTE( SUBSTITUTE( _xlpm.doi, "/","%2F"), ":","%3A"), "<","%3C"), ">","%3E") ) -> 10.1002%2Fajpa.20684 | J14: =TRIM(_xlfn.TEXTJOIN("_",FALSE(),H14,(SUBSTITUTE(SUBSTITUTE(D14," ",""), "_", "")))) -> Barger_etal_2007_TABLE1 | K14: =I14 & "_" & SUBSTITUTE(SUBSTITUTE(SUBSTITUTE(D14,CHAR(160),"")," ",""),"_","") -> 10.1002%2Fajpa.20684_TABLE1 | L14: {=IFERROR(INDEX(AUTO_Public_TSV_FileList!$A$1:$A$1000,MATCH(TRUE(),EXACT(K14,IFERROR(_xlfn.TEXTBEFORE(AUTO_Public_TSV_FileList!$A$1:$A$1000,".tsv"),"")),0)),"notfound")} -> 10.1002%2Fajpa.20684_TABLE1.tsv | M14: TABLE 1. Volumetric estimates of the amygdaloid complex and the basolateral division | P14: FINISHED | W14: Apes & humans | X14: amygdala subdivision volumes | AB14: volume | AC14: Zilles | AD14: Zilles | AE14: primary
A15: Barger, N., Stefanacci, L., Schumann, C. M., Sherwood, C. C., Annese, J., Allman, J. M., Buckwalter, J. A., Hof, P. R., & Semendeferi, K. (2012). Neuronal populations in the basolateral nuclei of the amygdala are differentially increased in humans compared with apes: A stereological study. J Comp Neurol, 520(13), 3035-3054. https://doi.org/10.1002/cne.23118 | D15: Table 1 | E15: =SUBSTITUTE(SUBSTITUTE(_xlfn.TEXTBEFORE(A15,","), "-", ""), " ", "") -> Barger | F15: {=_xlfn.LET( _xlpm.authors,_xlfn.TEXTBEFORE(A15," ("&G15&")"), _xlpm.hasAmp,ISNUMBER(SEARCH("&",_xlpm.authors)), _xlpm.hasEllipsis,ISNUMBER(SEARCH(_xlfn.UNICHAR(8230),_xlpm.authors)), _xlpm.commasBeforeAmp,IF( _xlpm.hasAmp, LEN(_xlfn.TEXTBEFORE(_xlpm.authors,"&"))-LEN(SUBSTITUTE(_xlfn.TEXTBEFORE(_xlpm.authors,"&"),",","")), 0 ), IF( _xlpm.hasEllipsis, "etal", IF( NOT(_xlpm.hasAmp), "", IF( _xlpm.commasBeforeAmp>2, "etal", SUBSTITUTE(TRIM(_xlfn.TEXTBEFORE(_xlfn.TEXTAFTER(_xlpm.authors,"& "),",")),"-","") ) ) ) )} -> etal | G15: =_xlfn.TEXTBEFORE(_xlfn.TEXTAFTER(A15, "("), ")") -> 2012 | H15: =E15 & IF(F15<>"", "_" & F15, "_") & IF(G15<>"", "_" & G15, "_") & IF(B15<>"", "_" & B15, "") -> Barger_etal_2012 | I15: =_xlfn.LET( _xlpm.doi,IF(C15<>"",C15,_xlfn.TEXTAFTER(A15,"https://doi.org/")), SUBSTITUTE( SUBSTITUTE( SUBSTITUTE( SUBSTITUTE( _xlpm.doi, "/","%2F"), ":","%3A"), "<","%3C"), ">","%3E") ) -> 10.1002%2Fcne.23118 | J15: =TRIM(_xlfn.TEXTJOIN("_",FALSE(),H15,(SUBSTITUTE(SUBSTITUTE(D15," ",""), "_", "")))) -> Barger_etal_2012_Table1 | K15: =I15 & "_" & SUBSTITUTE(SUBSTITUTE(SUBSTITUTE(D15,CHAR(160),"")," ",""),"_","") -> 10.1002%2Fcne.23118_Table1 | L15: {=IFERROR(INDEX(AUTO_Public_TSV_FileList!$A$1:$A$1000,MATCH(TRUE(),EXACT(K15,IFERROR(_xlfn.TEXTBEFORE(AUTO_Public_TSV_FileList!$A$1:$A$1000,".tsv"),"")),0)),"notfound")} -> 10.1002%2Fcne.23118_Table1.tsv | M15: Table 1. Specimens in Sample | N15: PDF (printed table) | P15: FINISHED | V15: Amygdala neuron number (specimen sample) | W15: Apes & humans; Old World monkey | X15: specimen sample: species, sex, age, hemisphere, collection provenance | Z15: histological sections | AB15: specimen metadata (not a volumetric/neuron measure) | AD15: Multiple (Semendeferi lab + contributed collections; see item note) | AE15: primary
A16: Barger, N., Stefanacci, L., Schumann, C. M., Sherwood, C. C., Annese, J., Allman, J. M., Buckwalter, J. A., Hof, P. R., & Semendeferi, K. (2012). Neuronal populations in the basolateral nuclei of the amygdala are differentially increased in humans compared with apes: A stereological study. J Comp Neurol, 520(13), 3035-3054. https://doi.org/10.1002/cne.23118 | D16: Table 3 | E16: =SUBSTITUTE(SUBSTITUTE(_xlfn.TEXTBEFORE(A16,","), "-", ""), " ", "") -> Barger | F16: {=_xlfn.LET( _xlpm.authors,_xlfn.TEXTBEFORE(A16," ("&G16&")"), _xlpm.hasAmp,ISNUMBER(SEARCH("&",_xlpm.authors)), _xlpm.hasEllipsis,ISNUMBER(SEARCH(_xlfn.UNICHAR(8230),_xlpm.authors)), _xlpm.commasBeforeAmp,IF( _xlpm.hasAmp, LEN(_xlfn.TEXTBEFORE(_xlpm.authors,"&"))-LEN(SUBSTITUTE(_xlfn.TEXTBEFORE(_xlpm.authors,"&"),",","")), 0 ), IF( _xlpm.hasEllipsis, "etal", IF( NOT(_xlpm.hasAmp), "", IF( _xlpm.commasBeforeAmp>2, "etal", SUBSTITUTE(TRIM(_xlfn.TEXTBEFORE(_xlfn.TEXTAFTER(_xlpm.authors,"& "),",")),"-","") ) ) ) )} -> etal | G16: =_xlfn.TEXTBEFORE(_xlfn.TEXTAFTER(A16, "("), ")") -> 2012 | H16: =E16 & IF(F16<>"", "_" & F16, "_") & IF(G16<>"", "_" & G16, "_") & IF(B16<>"", "_" & B16, "") -> Barger_etal_2012 | I16: =_xlfn.LET( _xlpm.doi,IF(C16<>"",C16,_xlfn.TEXTAFTER(A16,"https://doi.org/")), SUBSTITUTE( SUBSTITUTE( SUBSTITUTE( SUBSTITUTE( _xlpm.doi, "/","%2F"), ":","%3A"), "<","%3C"), ">","%3E") ) -> 10.1002%2Fcne.23118 | J16: =TRIM(_xlfn.TEXTJOIN("_",FALSE(),H16,(SUBSTITUTE(SUBSTITUTE(D16," ",""), "_", "")))) -> Barger_etal_2012_Table3 | K16: =I16 & "_" & SUBSTITUTE(SUBSTITUTE(SUBSTITUTE(D16,CHAR(160),"")," ",""),"_","") -> 10.1002%2Fcne.23118_Table3 | L16: {=IFERROR(INDEX(AUTO_Public_TSV_FileList!$A$1:$A$1000,MATCH(TRUE(),EXACT(K16,IFERROR(_xlfn.TEXTBEFORE(AUTO_Public_TSV_FileList!$A$1:$A$1000,".tsv"),"")),0)),"notfound")} -> 10.1002%2Fcne.23118_Table3.tsv | M16: Table 3. Average Neuron Number x10^6 (SD) for each nucleus in each species | P16: FINISHED | W16: Primates | X16: amygdala neuron numbers (basolateral + central nuclei) | AB16: neuron count (stereology) | AE16: primary
A17: Barks, S. K., Calhoun, M. E., Hopkins, W. D., Cranfield, M. R., Mudakikwa, A., Stoinski, T. S., Patterson, F. G., Erwin, J. M., Hecht, E. E., Hof, P. R., & Sherwood, C. C. (2014). Brain organization of gorillas reflects species differences in ecology. Am J Phys Anthropol. https://doi.org/10.1002/ajpa.22646 | D17: Fig 4 A | E17: =SUBSTITUTE(SUBSTITUTE(_xlfn.TEXTBEFORE(A17,","), "-", ""), " ", "") -> Barks | F17: {=_xlfn.LET( _xlpm.authors,_xlfn.TEXTBEFORE(A17," ("&G17&")"), _xlpm.hasAmp,ISNUMBER(SEARCH("&",_xlpm.authors)), _xlpm.hasEllipsis,ISNUMBER(SEARCH(_xlfn.UNICHAR(8230),_xlpm.authors)), _xlpm.commasBeforeAmp,IF( _xlpm.hasAmp, LEN(_xlfn.TEXTBEFORE(_xlpm.authors,"&"))-LEN(SUBSTITUTE(_xlfn.TEXTBEFORE(_xlpm.authors,"&"),",","")), 0 ), IF( _xlpm.hasEllipsis, "etal", IF( NOT(_xlpm.hasAmp), "", IF( _xlpm.commasBeforeAmp>2, "etal", SUBSTITUTE(TRIM(_xlfn.TEXTBEFORE(_xlfn.TEXTAFTER(_xlpm.authors,"& "),",")),"-","") ) ) ) )} -> etal | G17: =_xlfn.TEXTBEFORE(_xlfn.TEXTAFTER(A17, "("), ")") -> 2014 | H17: =E17 & IF(F17<>"", "_" & F17, "_") & IF(G17<>"", "_" & G17, "_") & IF(B17<>"", "_" & B17, "") -> Barks_etal_2014 | I17: =_xlfn.LET( _xlpm.doi,IF(C17<>"",C17,_xlfn.TEXTAFTER(A17,"https://doi.org/")), SUBSTITUTE( SUBSTITUTE( SUBSTITUTE( SUBSTITUTE( _xlpm.doi, "/","%2F"), ":","%3A"), "<","%3C"), ">","%3E") ) -> 10.1002%2Fajpa.22646 | J17: =TRIM(_xlfn.TEXTJOIN("_",FALSE(),H17,(SUBSTITUTE(SUBSTITUTE(D17," ",""), "_", "")))) -> Barks_etal_2014_Fig4A | K17: =I17 & "_" & SUBSTITUTE(SUBSTITUTE(SUBSTITUTE(D17,CHAR(160),"")," ",""),"_","") -> 10.1002%2Fajpa.22646_Fig4A | L17: {=IFERROR(INDEX(AUTO_Public_TSV_FileList!$A$1:$A$1000,MATCH(TRUE(),EXACT(K17,IFERROR(_xlfn.TEXTBEFORE(AUTO_Public_TSV_FileList!$A$1:$A$1000,".tsv"),"")),0)),"notfound")} -> 10.1002%2Fajpa.22646_Fig4A.tsv | M17: Fig4A_allsubjects_volumes | P17: FINISHED | AC17: Barks
A18: Barks, S. K., Calhoun, M. E., Hopkins, W. D., Cranfield, M. R., Mudakikwa, A., Stoinski, T. S., Patterson, F. G., Erwin, J. M., Hecht, E. E., Hof, P. R., & Sherwood, C. C. (2014). Brain organization of gorillas reflects species differences in ecology. Am J Phys Anthropol. https://doi.org/10.1002/ajpa.22646 | D18: Fig 5 A | E18: =SUBSTITUTE(SUBSTITUTE(_xlfn.TEXTBEFORE(A18,","), "-", ""), " ", "") -> Barks | F18: {=_xlfn.LET( _xlpm.authors,_xlfn.TEXTBEFORE(A18," ("&G18&")"), _xlpm.hasAmp,ISNUMBER(SEARCH("&",_xlpm.authors)), _xlpm.hasEllipsis,ISNUMBER(SEARCH(_xlfn.UNICHAR(8230),_xlpm.authors)), _xlpm.commasBeforeAmp,IF( _xlpm.hasAmp, LEN(_xlfn.TEXTBEFORE(_xlpm.authors,"&"))-LEN(SUBSTITUTE(_xlfn.TEXTBEFORE(_xlpm.authors,"&"),",","")), 0 ), IF( _xlpm.hasEllipsis, "etal", IF( NOT(_xlpm.hasAmp), "", IF( _xlpm.commasBeforeAmp>2, "etal", SUBSTITUTE(TRIM(_xlfn.TEXTBEFORE(_xlfn.TEXTAFTER(_xlpm.authors,"& "),",")),"-","") ) ) ) )} -> etal | G18: =_xlfn.TEXTBEFORE(_xlfn.TEXTAFTER(A18, "("), ")") -> 2014 | H18: =E18 & IF(F18<>"", "_" & F18, "_") & IF(G18<>"", "_" & G18, "_") & IF(B18<>"", "_" & B18, "") -> Barks_etal_2014 | I18: =_xlfn.LET( _xlpm.doi,IF(C18<>"",C18,_xlfn.TEXTAFTER(A18,"https://doi.org/")), SUBSTITUTE( SUBSTITUTE( SUBSTITUTE( SUBSTITUTE( _xlpm.doi, "/","%2F"), ":","%3A"), "<","%3C"), ">","%3E") ) -> 10.1002%2Fajpa.22646 | J18: =TRIM(_xlfn.TEXTJOIN("_",FALSE(),H18,(SUBSTITUTE(SUBSTITUTE(D18," ",""), "_", "")))) -> Barks_etal_2014_Fig5A | K18: =I18 & "_" & SUBSTITUTE(SUBSTITUTE(SUBSTITUTE(D18,CHAR(160),"")," ",""),"_","") -> 10.1002%2Fajpa.22646_Fig5A | L18: {=IFERROR(INDEX(AUTO_Public_TSV_FileList!$A$1:$A$1000,MATCH(TRUE(),EXACT(K18,IFERROR(_xlfn.TEXTBEFORE(AUTO_Public_TSV_FileList!$A$1:$A$1000,".tsv"),"")),0)),"notfound")} -> 10.1002%2Fajpa.22646_Fig5A.tsv | M18: Fig5A_adultsonly_volumes | P18: FINISHED
A19: Barks, S. K., Calhoun, M. E., Hopkins, W. D., Cranfield, M. R., Mudakikwa, A., Stoinski, T. S., Patterson, F. G., Erwin, J. M., Hecht, E. E., Hof, P. R., & Sherwood, C. C. (2014). Brain organization of gorillas reflects species differences in ecology. Am J Phys Anthropol. https://doi.org/10.1002/ajpa.22646 | D19: TABLE 1 | E19: =SUBSTITUTE(SUBSTITUTE(_xlfn.TEXTBEFORE(A19,","), "-", ""), " ", "") -> Barks | F19: {=_xlfn.LET( _xlpm.authors,_xlfn.TEXTBEFORE(A19," ("&G19&")"), _xlpm.hasAmp,ISNUMBER(SEARCH("&",_xlpm.authors)), _xlpm.hasEllipsis,ISNUMBER(SEARCH(_xlfn.UNICHAR(8230),_xlpm.authors)), _xlpm.commasBeforeAmp,IF( _xlpm.hasAmp, LEN(_xlfn.TEXTBEFORE(_xlpm.authors,"&"))-LEN(SUBSTITUTE(_xlfn.TEXTBEFORE(_xlpm.authors,"&"),",","")), 0 ), IF( _xlpm.hasEllipsis, "etal", IF( NOT(_xlpm.hasAmp), "", IF( _xlpm.commasBeforeAmp>2, "etal", SUBSTITUTE(TRIM(_xlfn.TEXTBEFORE(_xlfn.TEXTAFTER(_xlpm.authors,"& "),",")),"-","") ) ) ) )} -> etal | G19: =_xlfn.TEXTBEFORE(_xlfn.TEXTAFTER(A19, "("), ")") -> 2014 | H19: =E19 & IF(F19<>"", "_" & F19, "_") & IF(G19<>"", "_" & G19, "_") & IF(B19<>"", "_" & B19, "") -> Barks_etal_2014 | I19: =_xlfn.LET( _xlpm.doi,IF(C19<>"",C19,_xlfn.TEXTAFTER(A19,"https://doi.org/")), SUBSTITUTE( SUBSTITUTE( SUBSTITUTE( SUBSTITUTE( _xlpm.doi, "/","%2F"), ":","%3A"), "<","%3C"), ">","%3E") ) -> 10.1002%2Fajpa.22646 | J19: =TRIM(_xlfn.TEXTJOIN("_",FALSE(),H19,(SUBSTITUTE(SUBSTITUTE(D19," ",""), "_", "")))) -> Barks_etal_2014_TABLE1 | K19: =I19 & "_" & SUBSTITUTE(SUBSTITUTE(SUBSTITUTE(D19,CHAR(160),"")," ",""),"_","") -> 10.1002%2Fajpa.22646_TABLE1 | L19: {=IFERROR(INDEX(AUTO_Public_TSV_FileList!$A$1:$A$1000,MATCH(TRUE(),EXACT(K19,IFERROR(_xlfn.TEXTBEFORE(AUTO_Public_TSV_FileList!$A$1:$A$1000,".tsv"),"")),0)),"notfound")} -> 10.1002%2Fajpa.22646_TABLE1.tsv | M19: TABLE 1. Individual data | P19: FINISHED | AC19: Barks
A20: Barks, S. K., Calhoun, M. E., Hopkins, W. D., Cranfield, M. R., Mudakikwa, A., Stoinski, T. S., Patterson, F. G., Erwin, J. M., Hecht, E. E., Hof, P. R., & Sherwood, C. C. (2014). Brain organization of gorillas reflects species differences in ecology. Am J Phys Anthropol. https://doi.org/10.1002/ajpa.22646 | D20: TABLE 2 | E20: =SUBSTITUTE(SUBSTITUTE(_xlfn.TEXTBEFORE(A20,","), "-", ""), " ", "") -> Barks | F20: {=_xlfn.LET( _xlpm.authors,_xlfn.TEXTBEFORE(A20," ("&G20&")"), _xlpm.hasAmp,ISNUMBER(SEARCH("&",_xlpm.authors)), _xlpm.hasEllipsis,ISNUMBER(SEARCH(_xlfn.UNICHAR(8230),_xlpm.authors)), _xlpm.commasBeforeAmp,IF( _xlpm.hasAmp, LEN(_xlfn.TEXTBEFORE(_xlpm.authors,"&"))-LEN(SUBSTITUTE(_xlfn.TEXTBEFORE(_xlpm.authors,"&"),",","")), 0 ), IF( _xlpm.hasEllipsis, "etal", IF( NOT(_xlpm.hasAmp), "", IF( _xlpm.commasBeforeAmp>2, "etal", SUBSTITUTE(TRIM(_xlfn.TEXTBEFORE(_xlfn.TEXTAFTER(_xlpm.authors,"& "),",")),"-","") ) ) ) )} -> etal | G20: =_xlfn.TEXTBEFORE(_xlfn.TEXTAFTER(A20, "("), ")") -> 2014 | H20: =E20 & IF(F20<>"", "_" & F20, "_") & IF(G20<>"", "_" & G20, "_") & IF(B20<>"", "_" & B20, "") -> Barks_etal_2014 | I20: =_xlfn.LET( _xlpm.doi,IF(C20<>"",C20,_xlfn.TEXTAFTER(A20,"https://doi.org/")), SUBSTITUTE( SUBSTITUTE( SUBSTITUTE( SUBSTITUTE( _xlpm.doi, "/","%2F"), ":","%3A"), "<","%3C"), ">","%3E") ) -> 10.1002%2Fajpa.22646 | J20: =TRIM(_xlfn.TEXTJOIN("_",FALSE(),H20,(SUBSTITUTE(SUBSTITUTE(D20," ",""), "_", "")))) -> Barks_etal_2014_TABLE2 | K20: =I20 & "_" & SUBSTITUTE(SUBSTITUTE(SUBSTITUTE(D20,CHAR(160),"")," ",""),"_","") -> 10.1002%2Fajpa.22646_TABLE2 | L20: {=IFERROR(INDEX(AUTO_Public_TSV_FileList!$A$1:$A$1000,MATCH(TRUE(),EXACT(K20,IFERROR(_xlfn.TEXTBEFORE(AUTO_Public_TSV_FileList!$A$1:$A$1000,".tsv"),"")),0)),"notfound")} -> 10.1002%2Fajpa.22646_TABLE2.tsv | M20: TABLE 2. Stereological sampling of brains | P20: FINISHED
A21: Barks, S. K., Calhoun, M. E., Hopkins, W. D., Cranfield, M. R., Mudakikwa, A., Stoinski, T. S., Patterson, F. G., Erwin, J. M., Hecht, E. E., Hof, P. R., & Sherwood, C. C. (2014). Brain organization of gorillas reflects species differences in ecology. Am J Phys Anthropol. https://doi.org/10.1002/ajpa.22646 | D21: unpublishedviaDeCasien | E21: =SUBSTITUTE(SUBSTITUTE(_xlfn.TEXTBEFORE(A21,","), "-", ""), " ", "") -> Barks | F21: {=_xlfn.LET( _xlpm.authors,_xlfn.TEXTBEFORE(A21," ("&G21&")"), _xlpm.hasAmp,ISNUMBER(SEARCH("&",_xlpm.authors)), _xlpm.hasEllipsis,ISNUMBER(SEARCH(_xlfn.UNICHAR(8230),_xlpm.authors)), _xlpm.commasBeforeAmp,IF( _xlpm.hasAmp, LEN(_xlfn.TEXTBEFORE(_xlpm.authors,"&"))-LEN(SUBSTITUTE(_xlfn.TEXTBEFORE(_xlpm.authors,"&"),",","")), 0 ), IF( _xlpm.hasEllipsis, "etal", IF( NOT(_xlpm.hasAmp), "", IF( _xlpm.commasBeforeAmp>2, "etal", SUBSTITUTE(TRIM(_xlfn.TEXTBEFORE(_xlfn.TEXTAFTER(_xlpm.authors,"& "),",")),"-","") ) ) ) )} -> etal | G21: =_xlfn.TEXTBEFORE(_xlfn.TEXTAFTER(A21, "("), ")") -> 2014 | H21: =E21 & IF(F21<>"", "_" & F21, "_") & IF(G21<>"", "_" & G21, "_") & IF(B21<>"", "_" & B21, "") -> Barks_etal_2014 | I21: =_xlfn.LET( _xlpm.doi,IF(C21<>"",C21,_xlfn.TEXTAFTER(A21,"https://doi.org/")), SUBSTITUTE( SUBSTITUTE( SUBSTITUTE( SUBSTITUTE( _xlpm.doi, "/","%2F"), ":","%3A"), "<","%3C"), ">","%3E") ) -> 10.1002%2Fajpa.22646 | J21: =TRIM(_xlfn.TEXTJOIN("_",FALSE(),H21,(SUBSTITUTE(SUBSTITUTE(D21," ",""), "_", "")))) -> Barks_etal_2014_unpublishedviaDeCasien | K21: =I21 & "_" & SUBSTITUTE(SUBSTITUTE(SUBSTITUTE(D21,CHAR(160),"")," ",""),"_","") -> 10.1002%2Fajpa.22646_unpublishedviaDeCasien | L21: {=IFERROR(INDEX(AUTO_Public_TSV_FileList!$A$1:$A$1000,MATCH(TRUE(),EXACT(K21,IFERROR(_xlfn.TEXTBEFORE(AUTO_Public_TSV_FileList!$A$1:$A$1000,".tsv"),"")),0)),"notfound")} -> 10.1002%2Fajpa.22646_unpublishedviaDeCasien.tsv | O21: "Sherwood et al.64 and Barks et al.65 provided neocortex, hippocampus, striatum, thalamus, cerebellum, amygdala and insula measures for multiple gorilla species (Gorilla gorilla gorilla, G. g. graueri and G. beringei) from post-mortem MRI scans" (DeCasien and Higham 2019) | P21: FINISHED
A22: Baron, G., Frahm, H. D., & Stephan, H. (1988). Comparison of brain structure volumes in Insectivora and Primates. VIII. Vestibular complex. J Hirnforsch, 29(5), 509-523. http://www.ncbi.nlm.nih.gov/pubmed/3216099 | C22: PMID:3216099 | D22: Table 1 | E22: =SUBSTITUTE(SUBSTITUTE(_xlfn.TEXTBEFORE(A22,","), "-", ""), " ", "") -> Baron | F22: {=_xlfn.LET( _xlpm.authors,_xlfn.TEXTBEFORE(A22," ("&G22&")"), _xlpm.hasAmp,ISNUMBER(SEARCH("&",_xlpm.authors)), _xlpm.hasEllipsis,ISNUMBER(SEARCH(_xlfn.UNICHAR(8230),_xlpm.authors)), _xlpm.commasBeforeAmp,IF( _xlpm.hasAmp, LEN(_xlfn.TEXTBEFORE(_xlpm.authors,"&"))-LEN(SUBSTITUTE(_xlfn.TEXTBEFORE(_xlpm.authors,"&"),",","")), 0 ), IF( _xlpm.hasEllipsis, "etal", IF( NOT(_xlpm.hasAmp), "", IF( _xlpm.commasBeforeAmp>2, "etal", SUBSTITUTE(TRIM(_xlfn.TEXTBEFORE(_xlfn.TEXTAFTER(_xlpm.authors,"& "),",")),"-","") ) ) ) )} -> etal | G22: =_xlfn.TEXTBEFORE(_xlfn.TEXTAFTER(A22, "("), ")") -> 1988 | H22: =E22 & IF(F22<>"", "_" & F22, "_") & IF(G22<>"", "_" & G22, "_") & IF(B22<>"", "_" & B22, "") -> Baron_etal_1988 | I22: =_xlfn.LET( _xlpm.doi,IF(C22<>"",C22,_xlfn.TEXTAFTER(A22,"https://doi.org/")), SUBSTITUTE( SUBSTITUTE( SUBSTITUTE( SUBSTITUTE( _xlpm.doi, "/","%2F"), ":","%3A"), "<","%3C"), ">","%3E") ) -> PMID%3A3216099 | J22: =TRIM(_xlfn.TEXTJOIN("_",FALSE(),H22,(SUBSTITUTE(SUBSTITUTE(D22," ",""), "_", "")))) -> Baron_etal_1988_Table1 | K22: =I22 & "_" & SUBSTITUTE(SUBSTITUTE(SUBSTITUTE(D22,CHAR(160),"")," ",""),"_","") -> PMID%3A3216099_Table1 | L22: {=IFERROR(INDEX(AUTO_Public_TSV_FileList!$A$1:$A$1000,MATCH(TRUE(),EXACT(K22,IFERROR(_xlfn.TEXTBEFORE(AUTO_Public_TSV_FileList!$A$1:$A$1000,".tsv"),"")),0)),"notfound")} -> PMID%3A3216099_Table1.tsv | M22: Table 1. Volumes and indices of the vestibular complex (VC) and its main components (VM, V1, VL, VS) in Insectivora and Scadentia | P22: FINISHED | W22: Insectivora, Scandentia & Primates | X22: vestibular nuclear complex volume | Z22: histological sections | AB22: volume | AC22: Stephan | AD22: Stephan | AE22: primary
A23: Baron, G., Frahm, H. D., Bhatnagar, K. P., & Stephan, H. (1983). Comparison of brain structure volumes in Insectivora and Primates. III. Main olfactory bulb (MOB). J Hirnforsch, 24(5), 551-568. https://www.ncbi.nlm.nih.gov/pubmed/6663055 | C23: PMID:6663055 | D23: Table 1 | E23: =SUBSTITUTE(SUBSTITUTE(_xlfn.TEXTBEFORE(A23,","), "-", ""), " ", "") -> Baron | F23: {=_xlfn.LET( _xlpm.authors,_xlfn.TEXTBEFORE(A23," ("&G23&")"), _xlpm.hasAmp,ISNUMBER(SEARCH("&",_xlpm.authors)), _xlpm.hasEllipsis,ISNUMBER(SEARCH(_xlfn.UNICHAR(8230),_xlpm.authors)), _xlpm.commasBeforeAmp,IF( _xlpm.hasAmp, LEN(_xlfn.TEXTBEFORE(_xlpm.authors,"&"))-LEN(SUBSTITUTE(_xlfn.TEXTBEFORE(_xlpm.authors,"&"),",","")), 0 ), IF( _xlpm.hasEllipsis, "etal", IF( NOT(_xlpm.hasAmp), "", IF( _xlpm.commasBeforeAmp>2, "etal", SUBSTITUTE(TRIM(_xlfn.TEXTBEFORE(_xlfn.TEXTAFTER(_xlpm.authors,"& "),",")),"-","") ) ) ) )} -> etal | G23: =_xlfn.TEXTBEFORE(_xlfn.TEXTAFTER(A23, "("), ")") -> 1983 | H23: =E23 & IF(F23<>"", "_" & F23, "_") & IF(G23<>"", "_" & G23, "_") & IF(B23<>"", "_" & B23, "") -> Baron_etal_1983 | I23: =_xlfn.LET( _xlpm.doi,IF(C23<>"",C23,_xlfn.TEXTAFTER(A23,"https://doi.org/")), SUBSTITUTE( SUBSTITUTE( SUBSTITUTE( SUBSTITUTE( _xlpm.doi, "/","%2F"), ":","%3A"), "<","%3C"), ">","%3E") ) -> PMID%3A6663055 | J23: =TRIM(_xlfn.TEXTJOIN("_",FALSE(),H23,(SUBSTITUTE(SUBSTITUTE(D23," ",""), "_", "")))) -> Baron_etal_1983_Table1 | K23: =I23 & "_" & SUBSTITUTE(SUBSTITUTE(SUBSTITUTE(D23,CHAR(160),"")," ",""),"_","") -> PMID%3A6663055_Table1 | L23: {=IFERROR(INDEX(AUTO_Public_TSV_FileList!$A$1:$A$1000,MATCH(TRUE(),EXACT(K23,IFERROR(_xlfn.TEXTBEFORE(AUTO_Public_TSV_FileList!$A$1:$A$1000,".tsv"),"")),0)),"notfound")} -> PMID%3A6663055_Table1.tsv | N23: table | P23: FINISHED | W23: Insectivora, Scandentia & Primates | X23: main olfactory bulb (MOB) volume | Z23: histological sections | AB23: volume | AC23: Stephan | AD23: Stephan | AE23: primary
A24: Baron, G., Stephan, H., & Frahm, H. D. (1987). Comparison of brain structure volumes in Insectivora and Primates. VI. Paleocortical components. J Hirnforsch, 28(4), 463-477. http://www.ncbi.nlm.nih.gov/pubmed/3116076 | C24: PMID:3116076 | D24: Table 1 | E24: =SUBSTITUTE(SUBSTITUTE(_xlfn.TEXTBEFORE(A24,","), "-", ""), " ", "") -> Baron | F24: {=_xlfn.LET( _xlpm.authors,_xlfn.TEXTBEFORE(A24," ("&G24&")"), _xlpm.hasAmp,ISNUMBER(SEARCH("&",_xlpm.authors)), _xlpm.hasEllipsis,ISNUMBER(SEARCH(_xlfn.UNICHAR(8230),_xlpm.authors)), _xlpm.commasBeforeAmp,IF( _xlpm.hasAmp, LEN(_xlfn.TEXTBEFORE(_xlpm.authors,"&"))-LEN(SUBSTITUTE(_xlfn.TEXTBEFORE(_xlpm.authors,"&"),",","")), 0 ), IF( _xlpm.hasEllipsis, "etal", IF( NOT(_xlpm.hasAmp), "", IF( _xlpm.commasBeforeAmp>2, "etal", SUBSTITUTE(TRIM(_xlfn.TEXTBEFORE(_xlfn.TEXTAFTER(_xlpm.authors,"& "),",")),"-","") ) ) ) )} -> etal | G24: =_xlfn.TEXTBEFORE(_xlfn.TEXTAFTER(A24, "("), ")") -> 1987 | H24: =E24 & IF(F24<>"", "_" & F24, "_") & IF(G24<>"", "_" & G24, "_") & IF(B24<>"", "_" & B24, "") -> Baron_etal_1987 | I24: =_xlfn.LET( _xlpm.doi,IF(C24<>"",C24,_xlfn.TEXTAFTER(A24,"https://doi.org/")), SUBSTITUTE( SUBSTITUTE( SUBSTITUTE( SUBSTITUTE( _xlpm.doi, "/","%2F"), ":","%3A"), "<","%3C"), ">","%3E") ) -> PMID%3A3116076 | J24: =TRIM(_xlfn.TEXTJOIN("_",FALSE(),H24,(SUBSTITUTE(SUBSTITUTE(D24," ",""), "_", "")))) -> Baron_etal_1987_Table1 | K24: =I24 & "_" & SUBSTITUTE(SUBSTITUTE(SUBSTITUTE(D24,CHAR(160),"")," ",""),"_","") -> PMID%3A3116076_Table1 | L24: {=IFERROR(INDEX(AUTO_Public_TSV_FileList!$A$1:$A$1000,MATCH(TRUE(),EXACT(K24,IFERROR(_xlfn.TEXTBEFORE(AUTO_Public_TSV_FileList!$A$1:$A$1000,".tsv"),"")),0)),"notfound")} -> PMID%3A3116076_Table1.tsv | N24: table | P24: FINISHED | W24: Insectivora, Scandentia & Primates | X24: brain-structure volume (Comparison series, Part) | Z24: histological sections | AB24: volume | AC24: Stephan | AD24: Stephan | AE24: primary
A25: Baron, G., Stephan, H., & Frahm, H. D. (1990). Comparison of brain structure volumes in Insectivora and primates. IX. Trigeminal complex. J Hirnforsch, 31(2), 193-200. https://www.ncbi.nlm.nih.gov/pubmed/2358663 | C25: PMID:2358663 | D25: Table 1 | E25: =SUBSTITUTE(SUBSTITUTE(_xlfn.TEXTBEFORE(A25,","), "-", ""), " ", "") -> Baron | F25: {=_xlfn.LET( _xlpm.authors,_xlfn.TEXTBEFORE(A25," ("&G25&")"), _xlpm.hasAmp,ISNUMBER(SEARCH("&",_xlpm.authors)), _xlpm.hasEllipsis,ISNUMBER(SEARCH(_xlfn.UNICHAR(8230),_xlpm.authors)), _xlpm.commasBeforeAmp,IF( _xlpm.hasAmp, LEN(_xlfn.TEXTBEFORE(_xlpm.authors,"&"))-LEN(SUBSTITUTE(_xlfn.TEXTBEFORE(_xlpm.authors,"&"),",","")), 0 ), IF( _xlpm.hasEllipsis, "etal", IF( NOT(_xlpm.hasAmp), "", IF( _xlpm.commasBeforeAmp>2, "etal", SUBSTITUTE(TRIM(_xlfn.TEXTBEFORE(_xlfn.TEXTAFTER(_xlpm.authors,"& "),",")),"-","") ) ) ) )} -> etal | G25: =_xlfn.TEXTBEFORE(_xlfn.TEXTAFTER(A25, "("), ")") -> 1990 | H25: =E25 & IF(F25<>"", "_" & F25, "_") & IF(G25<>"", "_" & G25, "_") & IF(B25<>"", "_" & B25, "") -> Baron_etal_1990 | I25: =_xlfn.LET( _xlpm.doi,IF(C25<>"",C25,_xlfn.TEXTAFTER(A25,"https://doi.org/")), SUBSTITUTE( SUBSTITUTE( SUBSTITUTE( SUBSTITUTE( _xlpm.doi, "/","%2F"), ":","%3A"), "<","%3C"), ">","%3E") ) -> PMID%3A2358663 | J25: =TRIM(_xlfn.TEXTJOIN("_",FALSE(),H25,(SUBSTITUTE(SUBSTITUTE(D25," ",""), "_", "")))) -> Baron_etal_1990_Table1 | K25: =I25 & "_" & SUBSTITUTE(SUBSTITUTE(SUBSTITUTE(D25,CHAR(160),"")," ",""),"_","") -> PMID%3A2358663_Table1 | L25: {=IFERROR(INDEX(AUTO_Public_TSV_FileList!$A$1:$A$1000,MATCH(TRUE(),EXACT(K25,IFERROR(_xlfn.TEXTBEFORE(AUTO_Public_TSV_FileList!$A$1:$A$1000,".tsv"),"")),0)),"notfound")} -> PMID%3A2358663_Table1.tsv | M25: Table 1 .IX. Trigeminal complex | N25: table | P25: FINISHED | W25: Insectivora, Scandentia & Primates | X25: trigeminal complex volume | Z25: histological sections | AA25: volumetry | AB25: volume | AC25: Stephan | AD25: Stephan | AE25: primary
A26: Baron, G., Stephan, H., & Frahm, H. D. (1996). Comparative Neurobiology in Chiroptera: Macromorphology, Brain Structures, Tables, and Atlases. Birkhäuser. | C26: ISBN:9783764353704 | D26: Table 10 | E26: =SUBSTITUTE(SUBSTITUTE(_xlfn.TEXTBEFORE(A26,","), "-", ""), " ", "") -> Baron | F26: {=_xlfn.LET( _xlpm.authors,_xlfn.TEXTBEFORE(A26," ("&G26&")"), _xlpm.hasAmp,ISNUMBER(SEARCH("&",_xlpm.authors)), _xlpm.hasEllipsis,ISNUMBER(SEARCH(_xlfn.UNICHAR(8230),_xlpm.authors)), _xlpm.commasBeforeAmp,IF( _xlpm.hasAmp, LEN(_xlfn.TEXTBEFORE(_xlpm.authors,"&"))-LEN(SUBSTITUTE(_xlfn.TEXTBEFORE(_xlpm.authors,"&"),",","")), 0 ), IF( _xlpm.hasEllipsis, "etal", IF( NOT(_xlpm.hasAmp), "", IF( _xlpm.commasBeforeAmp>2, "etal", SUBSTITUTE(TRIM(_xlfn.TEXTBEFORE(_xlfn.TEXTAFTER(_xlpm.authors,"& "),",")),"-","") ) ) ) )} -> etal | G26: =_xlfn.TEXTBEFORE(_xlfn.TEXTAFTER(A26, "("), ")") -> 1996 | H26: =E26 & IF(F26<>"", "_" & F26, "_") & IF(G26<>"", "_" & G26, "_") & IF(B26<>"", "_" & B26, "") -> Baron_etal_1996 | I26: =_xlfn.LET( _xlpm.doi,IF(C26<>"",C26,_xlfn.TEXTAFTER(A26,"https://doi.org/")), SUBSTITUTE( SUBSTITUTE( SUBSTITUTE( SUBSTITUTE( _xlpm.doi, "/","%2F"), ":","%3A"), "<","%3C"), ">","%3E") ) -> ISBN%3A9783764353704 | J26: =TRIM(_xlfn.TEXTJOIN("_",FALSE(),H26,(SUBSTITUTE(SUBSTITUTE(D26," ",""), "_", "")))) -> Baron_etal_1996_Table10 | K26: =I26 & "_" & SUBSTITUTE(SUBSTITUTE(SUBSTITUTE(D26,CHAR(160),"")," ",""),"_","") -> ISBN%3A9783764353704_Table10 | L26: {=IFERROR(INDEX(AUTO_Public_TSV_FileList!$A$1:$A$1000,MATCH(TRUE(),EXACT(K26,IFERROR(_xlfn.TEXTBEFORE(AUTO_Public_TSV_FileList!$A$1:$A$1000,".tsv"),"")),0)),"notfound")} -> ISBN%3A9783764353704_Table10.tsv | P26: FINISHED | AE26: primary
A27: Baron, G., Stephan, H., & Frahm, H. D. (1996). Comparative Neurobiology in Chiroptera: Macromorphology, Brain Structures, Tables, and Atlases. Birkhäuser. | C27: ISBN:9783764353704 | D27: Table 13 | E27: =SUBSTITUTE(SUBSTITUTE(_xlfn.TEXTBEFORE(A27,","), "-", ""), " ", "") -> Baron | F27: {=_xlfn.LET( _xlpm.authors,_xlfn.TEXTBEFORE(A27," ("&G27&")"), _xlpm.hasAmp,ISNUMBER(SEARCH("&",_xlpm.authors)), _xlpm.hasEllipsis,ISNUMBER(SEARCH(_xlfn.UNICHAR(8230),_xlpm.authors)), _xlpm.commasBeforeAmp,IF( _xlpm.hasAmp, LEN(_xlfn.TEXTBEFORE(_xlpm.authors,"&"))-LEN(SUBSTITUTE(_xlfn.TEXTBEFORE(_xlpm.authors,"&"),",","")), 0 ), IF( _xlpm.hasEllipsis, "etal", IF( NOT(_xlpm.hasAmp), "", IF( _xlpm.commasBeforeAmp>2, "etal", SUBSTITUTE(TRIM(_xlfn.TEXTBEFORE(_xlfn.TEXTAFTER(_xlpm.authors,"& "),",")),"-","") ) ) ) )} -> etal | G27: =_xlfn.TEXTBEFORE(_xlfn.TEXTAFTER(A27, "("), ")") -> 1996 | H27: =E27 & IF(F27<>"", "_" & F27, "_") & IF(G27<>"", "_" & G27, "_") & IF(B27<>"", "_" & B27, "") -> Baron_etal_1996 | I27: =_xlfn.LET( _xlpm.doi,IF(C27<>"",C27,_xlfn.TEXTAFTER(A27,"https://doi.org/")), SUBSTITUTE( SUBSTITUTE( SUBSTITUTE( SUBSTITUTE( _xlpm.doi, "/","%2F"), ":","%3A"), "<","%3C"), ">","%3E") ) -> ISBN%3A9783764353704 | J27: =TRIM(_xlfn.TEXTJOIN("_",FALSE(),H27,(SUBSTITUTE(SUBSTITUTE(D27," ",""), "_", "")))) -> Baron_etal_1996_Table13 | K27: =I27 & "_" & SUBSTITUTE(SUBSTITUTE(SUBSTITUTE(D27,CHAR(160),"")," ",""),"_","") -> ISBN%3A9783764353704_Table13 | L27: {=IFERROR(INDEX(AUTO_Public_TSV_FileList!$A$1:$A$1000,MATCH(TRUE(),EXACT(K27,IFERROR(_xlfn.TEXTBEFORE(AUTO_Public_TSV_FileList!$A$1:$A$1000,".tsv"),"")),0)),"notfound")} -> ISBN%3A9783764353704_Table13.tsv | M27: Volumes (in mm3) of the sensory trigeminal complex and of the tractus solitarii and funicular nuclei of the medulla oblongata | N27: table | P27: FINISHED | S27: Structure list, species count and the table's size/index role confirmed against the book's own Table 1 key (PDF pp. 264-265) and the printed column header, 2026-08-31. | T27: Inherits the whole-source merge gate already recorded for Tables 10/32: seven historical taxon concepts in MANUAL_REVIEW, and source rows that collapse to the same species must be averaged within the item before Tier-1 recency resolution. Resolving that gate once unblocks every Baron item, so build order need not wait on it. | W27: Mammals | X27: trigeminal and somatosensory brainstem nucleus volumes | Y27: trigeminal and somatosensory brainstem nucleus volumes | Z27: histological sections | AB27: volume | AC27: Stephan | AD27: Stephan | AE27: primary | AG27: Not yet transcribed. PDF pages 74-78; N = 150 printed rows. Extend Baron_etal_1996_extract_snapshots.py, which already reads this PDF's text layer for Tables 10 and 32 with an explicit literal OCR-repair table.
A28: Baron, G., Stephan, H., & Frahm, H. D. (1996). Comparative Neurobiology in Chiroptera: Macromorphology, Brain Structures, Tables, and Atlases. Birkhäuser. | C28: ISBN:9783764353704 | D28: Table 16 | E28: =SUBSTITUTE(SUBSTITUTE(_xlfn.TEXTBEFORE(A28,","), "-", ""), " ", "") -> Baron | F28: {=_xlfn.LET( _xlpm.authors,_xlfn.TEXTBEFORE(A28," ("&G28&")"), _xlpm.hasAmp,ISNUMBER(SEARCH("&",_xlpm.authors)), _xlpm.hasEllipsis,ISNUMBER(SEARCH(_xlfn.UNICHAR(8230),_xlpm.authors)), _xlpm.commasBeforeAmp,IF( _xlpm.hasAmp, LEN(_xlfn.TEXTBEFORE(_xlpm.authors,"&"))-LEN(SUBSTITUTE(_xlfn.TEXTBEFORE(_xlpm.authors,"&"),",","")), 0 ), IF( _xlpm.hasEllipsis, "etal", IF( NOT(_xlpm.hasAmp), "", IF( _xlpm.commasBeforeAmp>2, "etal", SUBSTITUTE(TRIM(_xlfn.TEXTBEFORE(_xlfn.TEXTAFTER(_xlpm.authors,"& "),",")),"-","") ) ) ) )} -> etal | G28: =_xlfn.TEXTBEFORE(_xlfn.TEXTAFTER(A28, "("), ")") -> 1996 | H28: =E28 & IF(F28<>"", "_" & F28, "_") & IF(G28<>"", "_" & G28, "_") & IF(B28<>"", "_" & B28, "") -> Baron_etal_1996 | I28: =_xlfn.LET( _xlpm.doi,IF(C28<>"",C28,_xlfn.TEXTAFTER(A28,"https://doi.org/")), SUBSTITUTE( SUBSTITUTE( SUBSTITUTE( SUBSTITUTE( _xlpm.doi, "/","%2F"), ":","%3A"), "<","%3C"), ">","%3E") ) -> ISBN%3A9783764353704 | J28: =TRIM(_xlfn.TEXTJOIN("_",FALSE(),H28,(SUBSTITUTE(SUBSTITUTE(D28," ",""), "_", "")))) -> Baron_etal_1996_Table16 | K28: =I28 & "_" & SUBSTITUTE(SUBSTITUTE(SUBSTITUTE(D28,CHAR(160),"")," ",""),"_","") -> ISBN%3A9783764353704_Table16 | L28: {=IFERROR(INDEX(AUTO_Public_TSV_FileList!$A$1:$A$1000,MATCH(TRUE(),EXACT(K28,IFERROR(_xlfn.TEXTBEFORE(AUTO_Public_TSV_FileList!$A$1:$A$1000,".tsv"),"")),0)),"notfound")} -> ISBN%3A9783764353704_Table16.tsv | M28: Volumes of some motor and relay nuclei of the medulla oblongata | N28: table | P28: FINISHED | S28: Structure list, species count and the table's size/index role confirmed against the book's own Table 1 key (PDF pp. 264-265) and the printed column header, 2026-08-31. | T28: Inherits the whole-source merge gate already recorded for Tables 10/32: seven historical taxon concepts in MANUAL_REVIEW, and source rows that collapse to the same species must be averaged within the item before Tier-1 recency resolution. Resolving that gate once unblocks every Baron item, so build order need not wait on it. | W28: Mammals | X28: medullary motor and relay nucleus volumes | Y28: medullary motor and relay nucleus volumes | Z28: histological sections | AB28: volume | AC28: Stephan | AD28: Stephan | AE28: primary | AG28: Not yet transcribed. PDF pages 86-90; N = 150 printed rows. Extend Baron_etal_1996_extract_snapshots.py, which already reads this PDF's text layer for Tables 10 and 32 with an explicit literal OCR-repair table.
A29: Baron, G., Stephan, H., & Frahm, H. D. (1996). Comparative Neurobiology in Chiroptera: Macromorphology, Brain Structures, Tables, and Atlases. Birkhäuser. | C29: ISBN:9783764353704 | D29: Table 19 | E29: =SUBSTITUTE(SUBSTITUTE(_xlfn.TEXTBEFORE(A29,","), "-", ""), " ", "") -> Baron | F29: {=_xlfn.LET( _xlpm.authors,_xlfn.TEXTBEFORE(A29," ("&G29&")"), _xlpm.hasAmp,ISNUMBER(SEARCH("&",_xlpm.authors)), _xlpm.hasEllipsis,ISNUMBER(SEARCH(_xlfn.UNICHAR(8230),_xlpm.authors)), _xlpm.commasBeforeAmp,IF( _xlpm.hasAmp, LEN(_xlfn.TEXTBEFORE(_xlpm.authors,"&"))-LEN(SUBSTITUTE(_xlfn.TEXTBEFORE(_xlpm.authors,"&"),",","")), 0 ), IF( _xlpm.hasEllipsis, "etal", IF( NOT(_xlpm.hasAmp), "", IF( _xlpm.commasBeforeAmp>2, "etal", SUBSTITUTE(TRIM(_xlfn.TEXTBEFORE(_xlfn.TEXTAFTER(_xlpm.authors,"& "),",")),"-","") ) ) ) )} -> etal | G29: =_xlfn.TEXTBEFORE(_xlfn.TEXTAFTER(A29, "("), ")") -> 1996 | H29: =E29 & IF(F29<>"", "_" & F29, "_") & IF(G29<>"", "_" & G29, "_") & IF(B29<>"", "_" & B29, "") -> Baron_etal_1996 | I29: =_xlfn.LET( _xlpm.doi,IF(C29<>"",C29,_xlfn.TEXTAFTER(A29,"https://doi.org/")), SUBSTITUTE( SUBSTITUTE( SUBSTITUTE( SUBSTITUTE( _xlpm.doi, "/","%2F"), ":","%3A"), "<","%3C"), ">","%3E") ) -> ISBN%3A9783764353704 | J29: =TRIM(_xlfn.TEXTJOIN("_",FALSE(),H29,(SUBSTITUTE(SUBSTITUTE(D29," ",""), "_", "")))) -> Baron_etal_1996_Table19 | K29: =I29 & "_" & SUBSTITUTE(SUBSTITUTE(SUBSTITUTE(D29,CHAR(160),"")," ",""),"_","") -> ISBN%3A9783764353704_Table19 | L29: {=IFERROR(INDEX(AUTO_Public_TSV_FileList!$A$1:$A$1000,MATCH(TRUE(),EXACT(K29,IFERROR(_xlfn.TEXTBEFORE(AUTO_Public_TSV_FileList!$A$1:$A$1000,".tsv"),"")),0)),"notfound")} -> ISBN%3A9783764353704_Table19.tsv | M29: Volumes of the vestibular nuclei of the medulla oblongata | N29: table | P29: FINISHED | S29: Structure list, species count and the table's size/index role confirmed against the book's own Table 1 key (PDF pp. 264-265) and the printed column header, 2026-08-31. | T29: Inherits the whole-source merge gate already recorded for Tables 10/32: seven historical taxon concepts in MANUAL_REVIEW, and source rows that collapse to the same species must be averaged within the item before Tier-1 recency resolution. Resolving that gate once unblocks every Baron item, so build order need not wait on it. | W29: Mammals | X29: vestibular nucleus volumes | Y29: vestibular nucleus volumes | Z29: histological sections | AB29: volume | AC29: Stephan | AD29: Stephan | AE29: primary | AG29: Not yet transcribed. PDF pages 98-102; N = 150 printed rows. Extend Baron_etal_1996_extract_snapshots.py, which already reads this PDF's text layer for Tables 10 and 32 with an explicit literal OCR-repair table.
A30: Baron, G., Stephan, H., & Frahm, H. D. (1996). Comparative Neurobiology in Chiroptera: Macromorphology, Brain Structures, Tables, and Atlases. Birkhäuser. | C30: ISBN:9783764353704 | D30: Table 2 | E30: =SUBSTITUTE(SUBSTITUTE(_xlfn.TEXTBEFORE(A30,","), "-", ""), " ", "") -> Baron | F30: {=_xlfn.LET( _xlpm.authors,_xlfn.TEXTBEFORE(A30," ("&G30&")"), _xlpm.hasAmp,ISNUMBER(SEARCH("&",_xlpm.authors)), _xlpm.hasEllipsis,ISNUMBER(SEARCH(_xlfn.UNICHAR(8230),_xlpm.authors)), _xlpm.commasBeforeAmp,IF( _xlpm.hasAmp, LEN(_xlfn.TEXTBEFORE(_xlpm.authors,"&"))-LEN(SUBSTITUTE(_xlfn.TEXTBEFORE(_xlpm.authors,"&"),",","")), 0 ), IF( _xlpm.hasEllipsis, "etal", IF( NOT(_xlpm.hasAmp), "", IF( _xlpm.commasBeforeAmp>2, "etal", SUBSTITUTE(TRIM(_xlfn.TEXTBEFORE(_xlfn.TEXTAFTER(_xlpm.authors,"& "),",")),"-","") ) ) ) )} -> etal | G30: =_xlfn.TEXTBEFORE(_xlfn.TEXTAFTER(A30, "("), ")") -> 1996 | H30: =E30 & IF(F30<>"", "_" & F30, "_") & IF(G30<>"", "_" & G30, "_") & IF(B30<>"", "_" & B30, "") -> Baron_etal_1996 | I30: =_xlfn.LET( _xlpm.doi,IF(C30<>"",C30,_xlfn.TEXTAFTER(A30,"https://doi.org/")), SUBSTITUTE( SUBSTITUTE( SUBSTITUTE( SUBSTITUTE( _xlpm.doi, "/","%2F"), ":","%3A"), "<","%3C"), ">","%3E") ) -> ISBN%3A9783764353704 | J30: =TRIM(_xlfn.TEXTJOIN("_",FALSE(),H30,(SUBSTITUTE(SUBSTITUTE(D30," ",""), "_", "")))) -> Baron_etal_1996_Table2 | K30: =I30 & "_" & SUBSTITUTE(SUBSTITUTE(SUBSTITUTE(D30,CHAR(160),"")," ",""),"_","") -> ISBN%3A9783764353704_Table2 | L30: {=IFERROR(INDEX(AUTO_Public_TSV_FileList!$A$1:$A$1000,MATCH(TRUE(),EXACT(K30,IFERROR(_xlfn.TEXTBEFORE(AUTO_Public_TSV_FileList!$A$1:$A$1000,".tsv"),"")),0)),"notfound")} -> ISBN%3A9783764353704_Table2.tsv | M30: Linear measures of brains in mm | N30: table | P30: FINISHED | S30: Structure list, species count and the table's size/index role confirmed against the book's own Table 1 key (PDF pp. 264-265) and the printed column header, 2026-08-31. | T30: Inherits the whole-source merge gate already recorded for Tables 10/32: seven historical taxon concepts in MANUAL_REVIEW, and source rows that collapse to the same species must be averaged within the item before Tier-1 recency resolution. Resolving that gate once unblocks every Baron item, so build order need not wait on it. | W30: Mammals | X30: linear brain measures (mm); corpus callosum length | Y30: linear brain measures (mm); corpus callosum length | Z30: histological sections | AB30: linear measure (mm) | AC30: Stephan | AD30: Stephan | AE30: primary | AG30: Not yet transcribed. PDF pages 4-11; N = 303 printed rows. Extend Baron_etal_1996_extract_snapshots.py, which already reads this PDF's text layer for Tables 10 and 32 with an explicit literal OCR-repair table.
A31: Baron, G., Stephan, H., & Frahm, H. D. (1996). Comparative Neurobiology in Chiroptera: Macromorphology, Brain Structures, Tables, and Atlases. Birkhäuser. | C31: ISBN:9783764353704 | D31: Table 22 | E31: =SUBSTITUTE(SUBSTITUTE(_xlfn.TEXTBEFORE(A31,","), "-", ""), " ", "") -> Baron | F31: {=_xlfn.LET( _xlpm.authors,_xlfn.TEXTBEFORE(A31," ("&G31&")"), _xlpm.hasAmp,ISNUMBER(SEARCH("&",_xlpm.authors)), _xlpm.hasEllipsis,ISNUMBER(SEARCH(_xlfn.UNICHAR(8230),_xlpm.authors)), _xlpm.commasBeforeAmp,IF( _xlpm.hasAmp, LEN(_xlfn.TEXTBEFORE(_xlpm.authors,"&"))-LEN(SUBSTITUTE(_xlfn.TEXTBEFORE(_xlpm.authors,"&"),",","")), 0 ), IF( _xlpm.hasEllipsis, "etal", IF( NOT(_xlpm.hasAmp), "", IF( _xlpm.commasBeforeAmp>2, "etal", SUBSTITUTE(TRIM(_xlfn.TEXTBEFORE(_xlfn.TEXTAFTER(_xlpm.authors,"& "),",")),"-","") ) ) ) )} -> etal | G31: =_xlfn.TEXTBEFORE(_xlfn.TEXTAFTER(A31, "("), ")") -> 1996 | H31: =E31 & IF(F31<>"", "_" & F31, "_") & IF(G31<>"", "_" & G31, "_") & IF(B31<>"", "_" & B31, "") -> Baron_etal_1996 | I31: =_xlfn.LET( _xlpm.doi,IF(C31<>"",C31,_xlfn.TEXTAFTER(A31,"https://doi.org/")), SUBSTITUTE( SUBSTITUTE( SUBSTITUTE( SUBSTITUTE( _xlpm.doi, "/","%2F"), ":","%3A"), "<","%3C"), ">","%3E") ) -> ISBN%3A9783764353704 | J31: =TRIM(_xlfn.TEXTJOIN("_",FALSE(),H31,(SUBSTITUTE(SUBSTITUTE(D31," ",""), "_", "")))) -> Baron_etal_1996_Table22 | K31: =I31 & "_" & SUBSTITUTE(SUBSTITUTE(SUBSTITUTE(D31,CHAR(160),"")," ",""),"_","") -> ISBN%3A9783764353704_Table22 | L31: {=IFERROR(INDEX(AUTO_Public_TSV_FileList!$A$1:$A$1000,MATCH(TRUE(),EXACT(K31,IFERROR(_xlfn.TEXTBEFORE(AUTO_Public_TSV_FileList!$A$1:$A$1000,".tsv"),"")),0)),"notfound")} -> ISBN%3A9783764353704_Table22.tsv | M31: Volumes of the auditory nuclei of the medulla oblongata | N31: table | P31: FINISHED | S31: Structure list, species count and the table's size/index role confirmed against the book's own Table 1 key (PDF pp. 264-265) and the printed column header, 2026-08-31. | T31: Inherits the whole-source merge gate already recorded for Tables 10/32: seven historical taxon concepts in MANUAL_REVIEW, and source rows that collapse to the same species must be averaged within the item before Tier-1 recency resolution. Resolving that gate once unblocks every Baron item, so build order need not wait on it. | W31: Mammals | X31: auditory brainstem nucleus volumes | Y31: auditory brainstem nucleus volumes | Z31: histological sections | AB31: volume | AC31: Stephan | AD31: Stephan | AE31: primary | AG31: Not yet transcribed. PDF pages 110-114; N = 150 printed rows. Extend Baron_etal_1996_extract_snapshots.py, which already reads this PDF's text layer for Tables 10 and 32 with an explicit literal OCR-repair table.
A32: Baron, G., Stephan, H., & Frahm, H. D. (1996). Comparative Neurobiology in Chiroptera: Macromorphology, Brain Structures, Tables, and Atlases. Birkhäuser. | C32: ISBN:9783764353704 | D32: Table 25 | E32: =SUBSTITUTE(SUBSTITUTE(_xlfn.TEXTBEFORE(A32,","), "-", ""), " ", "") -> Baron | F32: {=_xlfn.LET( _xlpm.authors,_xlfn.TEXTBEFORE(A32," ("&G32&")"), _xlpm.hasAmp,ISNUMBER(SEARCH("&",_xlpm.authors)), _xlpm.hasEllipsis,ISNUMBER(SEARCH(_xlfn.UNICHAR(8230),_xlpm.authors)), _xlpm.commasBeforeAmp,IF( _xlpm.hasAmp, LEN(_xlfn.TEXTBEFORE(_xlpm.authors,"&"))-LEN(SUBSTITUTE(_xlfn.TEXTBEFORE(_xlpm.authors,"&"),",","")), 0 ), IF( _xlpm.hasEllipsis, "etal", IF( NOT(_xlpm.hasAmp), "", IF( _xlpm.commasBeforeAmp>2, "etal", SUBSTITUTE(TRIM(_xlfn.TEXTBEFORE(_xlfn.TEXTAFTER(_xlpm.authors,"& "),",")),"-","") ) ) ) )} -> etal | G32: =_xlfn.TEXTBEFORE(_xlfn.TEXTAFTER(A32, "("), ")") -> 1996 | H32: =E32 & IF(F32<>"", "_" & F32, "_") & IF(G32<>"", "_" & G32, "_") & IF(B32<>"", "_" & B32, "") -> Baron_etal_1996 | I32: =_xlfn.LET( _xlpm.doi,IF(C32<>"",C32,_xlfn.TEXTAFTER(A32,"https://doi.org/")), SUBSTITUTE( SUBSTITUTE( SUBSTITUTE( SUBSTITUTE( _xlpm.doi, "/","%2F"), ":","%3A"), "<","%3C"), ">","%3E") ) -> ISBN%3A9783764353704 | J32: =TRIM(_xlfn.TEXTJOIN("_",FALSE(),H32,(SUBSTITUTE(SUBSTITUTE(D32," ",""), "_", "")))) -> Baron_etal_1996_Table25 | K32: =I32 & "_" & SUBSTITUTE(SUBSTITUTE(SUBSTITUTE(D32,CHAR(160),"")," ",""),"_","") -> ISBN%3A9783764353704_Table25 | L32: {=IFERROR(INDEX(AUTO_Public_TSV_FileList!$A$1:$A$1000,MATCH(TRUE(),EXACT(K32,IFERROR(_xlfn.TEXTBEFORE(AUTO_Public_TSV_FileList!$A$1:$A$1000,".tsv"),"")),0)),"notfound")} -> ISBN%3A9783764353704_Table25.tsv | M32: Volumes of mesencephalic components | N32: table | P32: FINISHED | S32: Structure list, species count and the table's size/index role confirmed against the book's own Table 1 key (PDF pp. 264-265) and the printed column header, 2026-08-31. | T32: Inherits the whole-source merge gate already recorded for Tables 10/32: seven historical taxon concepts in MANUAL_REVIEW, and source rows that collapse to the same species must be averaged within the item before Tier-1 recency resolution. Resolving that gate once unblocks every Baron item, so build order need not wait on it. | W32: Mammals | X32: mesencephalic component volumes; inferior and superior colliculus | Y32: mesencephalic component volumes; inferior and superior colliculus | Z32: histological sections | AB32: volume | AC32: Stephan | AD32: Stephan | AE32: primary | AG32: Not yet transcribed. PDF pages 122-126; N = 150 printed rows. Extend Baron_etal_1996_extract_snapshots.py, which already reads this PDF's text layer for Tables 10 and 32 with an explicit literal OCR-repair table.
A33: Baron, G., Stephan, H., & Frahm, H. D. (1996). Comparative Neurobiology in Chiroptera: Macromorphology, Brain Structures, Tables, and Atlases. Birkhäuser. | C33: ISBN:9783764353704 | D33: Table 28 | E33: =SUBSTITUTE(SUBSTITUTE(_xlfn.TEXTBEFORE(A33,","), "-", ""), " ", "") -> Baron | F33: {=_xlfn.LET( _xlpm.authors,_xlfn.TEXTBEFORE(A33," ("&G33&")"), _xlpm.hasAmp,ISNUMBER(SEARCH("&",_xlpm.authors)), _xlpm.hasEllipsis,ISNUMBER(SEARCH(_xlfn.UNICHAR(8230),_xlpm.authors)), _xlpm.commasBeforeAmp,IF( _xlpm.hasAmp, LEN(_xlfn.TEXTBEFORE(_xlpm.authors,"&"))-LEN(SUBSTITUTE(_xlfn.TEXTBEFORE(_xlpm.authors,"&"),",","")), 0 ), IF( _xlpm.hasEllipsis, "etal", IF( NOT(_xlpm.hasAmp), "", IF( _xlpm.commasBeforeAmp>2, "etal", SUBSTITUTE(TRIM(_xlfn.TEXTBEFORE(_xlfn.TEXTAFTER(_xlpm.authors,"& "),",")),"-","") ) ) ) )} -> etal | G33: =_xlfn.TEXTBEFORE(_xlfn.TEXTAFTER(A33, "("), ")") -> 1996 | H33: =E33 & IF(F33<>"", "_" & F33, "_") & IF(G33<>"", "_" & G33, "_") & IF(B33<>"", "_" & B33, "") -> Baron_etal_1996 | I33: =_xlfn.LET( _xlpm.doi,IF(C33<>"",C33,_xlfn.TEXTAFTER(A33,"https://doi.org/")), SUBSTITUTE( SUBSTITUTE( SUBSTITUTE( SUBSTITUTE( _xlpm.doi, "/","%2F"), ":","%3A"), "<","%3C"), ">","%3E") ) -> ISBN%3A9783764353704 | J33: =TRIM(_xlfn.TEXTJOIN("_",FALSE(),H33,(SUBSTITUTE(SUBSTITUTE(D33," ",""), "_", "")))) -> Baron_etal_1996_Table28 | K33: =I33 & "_" & SUBSTITUTE(SUBSTITUTE(SUBSTITUTE(D33,CHAR(160),"")," ",""),"_","") -> ISBN%3A9783764353704_Table28 | L33: {=IFERROR(INDEX(AUTO_Public_TSV_FileList!$A$1:$A$1000,MATCH(TRUE(),EXACT(K33,IFERROR(_xlfn.TEXTBEFORE(AUTO_Public_TSV_FileList!$A$1:$A$1000,".tsv"),"")),0)),"notfound")} -> ISBN%3A9783764353704_Table28.tsv | M33: Volumes of cerebellar nuclei in mm3 | N33: table | P33: FINISHED | S33: Structure list, species count and the table's size/index role confirmed against the book's own Table 1 key (PDF pp. 264-265) and the printed column header, 2026-08-31. | T33: Inherits the whole-source merge gate already recorded for Tables 10/32: seven historical taxon concepts in MANUAL_REVIEW, and source rows that collapse to the same species must be averaged within the item before Tier-1 recency resolution. Resolving that gate once unblocks every Baron item, so build order need not wait on it. | W33: Mammals | X33: cerebellar nucleus volumes | Y33: cerebellar nucleus volumes | Z33: histological sections | AB33: volume | AC33: Stephan | AD33: Stephan | AE33: primary | AG33: Not yet transcribed. PDF pages 134; N = 18 printed rows. Extend Baron_etal_1996_extract_snapshots.py, which already reads this PDF's text layer for Tables 10 and 32 with an explicit literal OCR-repair table.
A34: Baron, G., Stephan, H., & Frahm, H. D. (1996). Comparative Neurobiology in Chiroptera: Macromorphology, Brain Structures, Tables, and Atlases. Birkhäuser. | C34: ISBN:9783764353704 | D34: Table 30 | E34: =SUBSTITUTE(SUBSTITUTE(_xlfn.TEXTBEFORE(A34,","), "-", ""), " ", "") -> Baron | F34: {=_xlfn.LET( _xlpm.authors,_xlfn.TEXTBEFORE(A34," ("&G34&")"), _xlpm.hasAmp,ISNUMBER(SEARCH("&",_xlpm.authors)), _xlpm.hasEllipsis,ISNUMBER(SEARCH(_xlfn.UNICHAR(8230),_xlpm.authors)), _xlpm.commasBeforeAmp,IF( _xlpm.hasAmp, LEN(_xlfn.TEXTBEFORE(_xlpm.authors,"&"))-LEN(SUBSTITUTE(_xlfn.TEXTBEFORE(_xlpm.authors,"&"),",","")), 0 ), IF( _xlpm.hasEllipsis, "etal", IF( NOT(_xlpm.hasAmp), "", IF( _xlpm.commasBeforeAmp>2, "etal", SUBSTITUTE(TRIM(_xlfn.TEXTBEFORE(_xlfn.TEXTAFTER(_xlpm.authors,"& "),",")),"-","") ) ) ) )} -> etal | G34: =_xlfn.TEXTBEFORE(_xlfn.TEXTAFTER(A34, "("), ")") -> 1996 | H34: =E34 & IF(F34<>"", "_" & F34, "_") & IF(G34<>"", "_" & G34, "_") & IF(B34<>"", "_" & B34, "") -> Baron_etal_1996 | I34: =_xlfn.LET( _xlpm.doi,IF(C34<>"",C34,_xlfn.TEXTAFTER(A34,"https://doi.org/")), SUBSTITUTE( SUBSTITUTE( SUBSTITUTE( SUBSTITUTE( _xlpm.doi, "/","%2F"), ":","%3A"), "<","%3C"), ">","%3E") ) -> ISBN%3A9783764353704 | J34: =TRIM(_xlfn.TEXTJOIN("_",FALSE(),H34,(SUBSTITUTE(SUBSTITUTE(D34," ",""), "_", "")))) -> Baron_etal_1996_Table30 | K34: =I34 & "_" & SUBSTITUTE(SUBSTITUTE(SUBSTITUTE(D34,CHAR(160),"")," ",""),"_","") -> ISBN%3A9783764353704_Table30 | L34: {=IFERROR(INDEX(AUTO_Public_TSV_FileList!$A$1:$A$1000,MATCH(TRUE(),EXACT(K34,IFERROR(_xlfn.TEXTBEFORE(AUTO_Public_TSV_FileList!$A$1:$A$1000,".tsv"),"")),0)),"notfound")} -> ISBN%3A9783764353704_Table30.tsv | M34: Volumes of some mesencephalic and diencephalic components in mm3 | N34: table | P34: FINISHED | S34: Structure list, species count and the table's size/index role confirmed against the book's own Table 1 key (PDF pp. 264-265) and the printed column header, 2026-08-31. | T34: Inherits the whole-source merge gate already recorded for Tables 10/32: seven historical taxon concepts in MANUAL_REVIEW, and source rows that collapse to the same species must be averaged within the item before Tier-1 recency resolution. Resolving that gate once unblocks every Baron item, so build order need not wait on it. | W34: Mammals | X34: lateral lemniscus and geniculate nucleus volumes | Y34: lateral lemniscus and geniculate nucleus volumes | Z34: histological sections | AB34: volume | AC34: Stephan | AD34: Stephan | AE34: primary | AG34: Build; small and cheap (19 species, one page) and disproportionately useful: medial geniculate (auditory) and lateral geniculate with its dorsal/ventral split (visual) in one table, which is the thalamic tier of the audiovisual comparison. Carry the corrected abbreviations, not the OCR forms. This table is also the only place Asellia tridens appears with component volumes.
A35: Baron, G., Stephan, H., & Frahm, H. D. (1996). Comparative Neurobiology in Chiroptera: Macromorphology, Brain Structures, Tables, and Atlases. Birkhäuser. | C35: ISBN:9783764353704 | D35: Table 32 | E35: =SUBSTITUTE(SUBSTITUTE(_xlfn.TEXTBEFORE(A35,","), "-", ""), " ", "") -> Baron | F35: {=_xlfn.LET( _xlpm.authors,_xlfn.TEXTBEFORE(A35," ("&G35&")"), _xlpm.hasAmp,ISNUMBER(SEARCH("&",_xlpm.authors)), _xlpm.hasEllipsis,ISNUMBER(SEARCH(_xlfn.UNICHAR(8230),_xlpm.authors)), _xlpm.commasBeforeAmp,IF( _xlpm.hasAmp, LEN(_xlfn.TEXTBEFORE(_xlpm.authors,"&"))-LEN(SUBSTITUTE(_xlfn.TEXTBEFORE(_xlpm.authors,"&"),",","")), 0 ), IF( _xlpm.hasEllipsis, "etal", IF( NOT(_xlpm.hasAmp), "", IF( _xlpm.commasBeforeAmp>2, "etal", SUBSTITUTE(TRIM(_xlfn.TEXTBEFORE(_xlfn.TEXTAFTER(_xlpm.authors,"& "),",")),"-","") ) ) ) )} -> etal | G35: =_xlfn.TEXTBEFORE(_xlfn.TEXTAFTER(A35, "("), ")") -> 1996 | H35: =E35 & IF(F35<>"", "_" & F35, "_") & IF(G35<>"", "_" & G35, "_") & IF(B35<>"", "_" & B35, "") -> Baron_etal_1996 | I35: =_xlfn.LET( _xlpm.doi,IF(C35<>"",C35,_xlfn.TEXTAFTER(A35,"https://doi.org/")), SUBSTITUTE( SUBSTITUTE( SUBSTITUTE( SUBSTITUTE( _xlpm.doi, "/","%2F"), ":","%3A"), "<","%3C"), ">","%3E") ) -> ISBN%3A9783764353704 | J35: =TRIM(_xlfn.TEXTJOIN("_",FALSE(),H35,(SUBSTITUTE(SUBSTITUTE(D35," ",""), "_", "")))) -> Baron_etal_1996_Table32 | K35: =I35 & "_" & SUBSTITUTE(SUBSTITUTE(SUBSTITUTE(D35,CHAR(160),"")," ",""),"_","") -> ISBN%3A9783764353704_Table32 | L35: {=IFERROR(INDEX(AUTO_Public_TSV_FileList!$A$1:$A$1000,MATCH(TRUE(),EXACT(K35,IFERROR(_xlfn.TEXTBEFORE(AUTO_Public_TSV_FileList!$A$1:$A$1000,".tsv"),"")),0)),"notfound")} -> ISBN%3A9783764353704_Table32.tsv | P35: FINISHED | AE35: primary
A36: Baron, G., Stephan, H., & Frahm, H. D. (1996). Comparative Neurobiology in Chiroptera: Macromorphology, Brain Structures, Tables, and Atlases. Birkhäuser. | C36: ISBN:9783764353704 | D36: Table 35 | E36: =SUBSTITUTE(SUBSTITUTE(_xlfn.TEXTBEFORE(A36,","), "-", ""), " ", "") -> Baron | F36: {=_xlfn.LET( _xlpm.authors,_xlfn.TEXTBEFORE(A36," ("&G36&")"), _xlpm.hasAmp,ISNUMBER(SEARCH("&",_xlpm.authors)), _xlpm.hasEllipsis,ISNUMBER(SEARCH(_xlfn.UNICHAR(8230),_xlpm.authors)), _xlpm.commasBeforeAmp,IF( _xlpm.hasAmp, LEN(_xlfn.TEXTBEFORE(_xlpm.authors,"&"))-LEN(SUBSTITUTE(_xlfn.TEXTBEFORE(_xlpm.authors,"&"),",","")), 0 ), IF( _xlpm.hasEllipsis, "etal", IF( NOT(_xlpm.hasAmp), "", IF( _xlpm.commasBeforeAmp>2, "etal", SUBSTITUTE(TRIM(_xlfn.TEXTBEFORE(_xlfn.TEXTAFTER(_xlpm.authors,"& "),",")),"-","") ) ) ) )} -> etal | G36: =_xlfn.TEXTBEFORE(_xlfn.TEXTAFTER(A36, "("), ")") -> 1996 | H36: =E36 & IF(F36<>"", "_" & F36, "_") & IF(G36<>"", "_" & G36, "_") & IF(B36<>"", "_" & B36, "") -> Baron_etal_1996 | I36: =_xlfn.LET( _xlpm.doi,IF(C36<>"",C36,_xlfn.TEXTAFTER(A36,"https://doi.org/")), SUBSTITUTE( SUBSTITUTE( SUBSTITUTE( SUBSTITUTE( _xlpm.doi, "/","%2F"), ":","%3A"), "<","%3C"), ">","%3E") ) -> ISBN%3A9783764353704 | J36: =TRIM(_xlfn.TEXTJOIN("_",FALSE(),H36,(SUBSTITUTE(SUBSTITUTE(D36," ",""), "_", "")))) -> Baron_etal_1996_Table35 | K36: =I36 & "_" & SUBSTITUTE(SUBSTITUTE(SUBSTITUTE(D36,CHAR(160),"")," ",""),"_","") -> ISBN%3A9783764353704_Table35 | L36: {=IFERROR(INDEX(AUTO_Public_TSV_FileList!$A$1:$A$1000,MATCH(TRUE(),EXACT(K36,IFERROR(_xlfn.TEXTBEFORE(AUTO_Public_TSV_FileList!$A$1:$A$1000,".tsv"),"")),0)),"notfound")} -> ISBN%3A9783764353704_Table35.tsv | M36: Volumes, size indices, average size indices of the accessory olfactory bulb, and percentage of AOB relative to the BOL complex | N36: table | P36: FINISHED | S36: Structure list, species count and the table's size/index role confirmed against the book's own Table 1 key (PDF pp. 264-265) and the printed column header, 2026-08-31. | T36: Inherits the whole-source merge gate already recorded for Tables 10/32: seven historical taxon concepts in MANUAL_REVIEW, and source rows that collapse to the same species must be averaged within the item before Tier-1 recency resolution. Resolving that gate once unblocks every Baron item, so build order need not wait on it. | W36: Mammals | X36: accessory olfactory bulb volume | Y36: accessory olfactory bulb volume | Z36: histological sections | AB36: volume | AC36: Stephan | AD36: Stephan | AE36: primary | AG36: Build the volume column only. AOB is not separated in Table 32, whose BOL is the whole olfactory bulb complex, so this is the only route to an MOB/AOB split for bats.
A37: Baron, G., Stephan, H., & Frahm, H. D. (1996). Comparative Neurobiology in Chiroptera: Macromorphology, Brain Structures, Tables, and Atlases. Birkhäuser. | C37: ISBN:9783764353704 | D37: Table 36 | E37: =SUBSTITUTE(SUBSTITUTE(_xlfn.TEXTBEFORE(A37,","), "-", ""), " ", "") -> Baron | F37: {=_xlfn.LET( _xlpm.authors,_xlfn.TEXTBEFORE(A37," ("&G37&")"), _xlpm.hasAmp,ISNUMBER(SEARCH("&",_xlpm.authors)), _xlpm.hasEllipsis,ISNUMBER(SEARCH(_xlfn.UNICHAR(8230),_xlpm.authors)), _xlpm.commasBeforeAmp,IF( _xlpm.hasAmp, LEN(_xlfn.TEXTBEFORE(_xlpm.authors,"&"))-LEN(SUBSTITUTE(_xlfn.TEXTBEFORE(_xlpm.authors,"&"),",","")), 0 ), IF( _xlpm.hasEllipsis, "etal", IF( NOT(_xlpm.hasAmp), "", IF( _xlpm.commasBeforeAmp>2, "etal", SUBSTITUTE(TRIM(_xlfn.TEXTBEFORE(_xlfn.TEXTAFTER(_xlpm.authors,"& "),",")),"-","") ) ) ) )} -> etal | G37: =_xlfn.TEXTBEFORE(_xlfn.TEXTAFTER(A37, "("), ")") -> 1996 | H37: =E37 & IF(F37<>"", "_" & F37, "_") & IF(G37<>"", "_" & G37, "_") & IF(B37<>"", "_" & B37, "") -> Baron_etal_1996 | I37: =_xlfn.LET( _xlpm.doi,IF(C37<>"",C37,_xlfn.TEXTAFTER(A37,"https://doi.org/")), SUBSTITUTE( SUBSTITUTE( SUBSTITUTE( SUBSTITUTE( _xlpm.doi, "/","%2F"), ":","%3A"), "<","%3C"), ">","%3E") ) -> ISBN%3A9783764353704 | J37: =TRIM(_xlfn.TEXTJOIN("_",FALSE(),H37,(SUBSTITUTE(SUBSTITUTE(D37," ",""), "_", "")))) -> Baron_etal_1996_Table36 | K37: =I37 & "_" & SUBSTITUTE(SUBSTITUTE(SUBSTITUTE(D37,CHAR(160),"")," ",""),"_","") -> ISBN%3A9783764353704_Table36 | L37: {=IFERROR(INDEX(AUTO_Public_TSV_FileList!$A$1:$A$1000,MATCH(TRUE(),EXACT(K37,IFERROR(_xlfn.TEXTBEFORE(AUTO_Public_TSV_FileList!$A$1:$A$1000,".tsv"),"")),0)),"notfound")} -> ISBN%3A9783764353704_Table36.tsv | M37: Schneider's area measurements of cortical regions (mm2) | N37: table | P37: FINISHED | S37: Structure list, species count and the table's size/index role confirmed against the book's own Table 1 key (PDF pp. 264-265) and the printed column header, 2026-08-31. | T37: Reprinted from another author's work, not a Frankfurt-collection measurement. Register as secondary and keep the original author attribution in the item note; check the upstream publication before treating any value as primary. Inherits the whole-source merge gate already recorded for Tables 10/32: seven historical taxon concepts in MANUAL_REVIEW, and source rows that collapse to the same species must be averaged within the item before Tier-1 recency resolution. Resolving that gate once unblocks every Baron item, so build order need not wait on it. | W37: Mammals | X37: cortical surface areas (mm2) | Y37: cortical surface areas (mm2) | Z37: histological sections | AB37: cortical surface area | AE37: secondary | AF37: Schneider (1957b) planimetry of cortical regions | AG37: Build only if bat cortical surface areas are wanted for __merging_cortical_areas. Secondary: the measurements are Schneider's (1957b), and Stephan & Pirlot 1970 cite Schneider's cortical surface work directly, so prefer the original if it can be obtained.
A38: Baron, G., Stephan, H., & Frahm, H. D. (1996). Comparative Neurobiology in Chiroptera: Macromorphology, Brain Structures, Tables, and Atlases. Birkhäuser. | C38: ISBN:9783764353704 | D38: Table 39 | E38: =SUBSTITUTE(SUBSTITUTE(_xlfn.TEXTBEFORE(A38,","), "-", ""), " ", "") -> Baron | F38: {=_xlfn.LET( _xlpm.authors,_xlfn.TEXTBEFORE(A38," ("&G38&")"), _xlpm.hasAmp,ISNUMBER(SEARCH("&",_xlpm.authors)), _xlpm.hasEllipsis,ISNUMBER(SEARCH(_xlfn.UNICHAR(8230),_xlpm.authors)), _xlpm.commasBeforeAmp,IF( _xlpm.hasAmp, LEN(_xlfn.TEXTBEFORE(_xlpm.authors,"&"))-LEN(SUBSTITUTE(_xlfn.TEXTBEFORE(_xlpm.authors,"&"),",","")), 0 ), IF( _xlpm.hasEllipsis, "etal", IF( NOT(_xlpm.hasAmp), "", IF( _xlpm.commasBeforeAmp>2, "etal", SUBSTITUTE(TRIM(_xlfn.TEXTBEFORE(_xlfn.TEXTAFTER(_xlpm.authors,"& "),",")),"-","") ) ) ) )} -> etal | G38: =_xlfn.TEXTBEFORE(_xlfn.TEXTAFTER(A38, "("), ")") -> 1996 | H38: =E38 & IF(F38<>"", "_" & F38, "_") & IF(G38<>"", "_" & G38, "_") & IF(B38<>"", "_" & B38, "") -> Baron_etal_1996 | I38: =_xlfn.LET( _xlpm.doi,IF(C38<>"",C38,_xlfn.TEXTAFTER(A38,"https://doi.org/")), SUBSTITUTE( SUBSTITUTE( SUBSTITUTE( SUBSTITUTE( _xlpm.doi, "/","%2F"), ":","%3A"), "<","%3C"), ">","%3E") ) -> ISBN%3A9783764353704 | J38: =TRIM(_xlfn.TEXTJOIN("_",FALSE(),H38,(SUBSTITUTE(SUBSTITUTE(D38," ",""), "_", "")))) -> Baron_etal_1996_Table39 | K38: =I38 & "_" & SUBSTITUTE(SUBSTITUTE(SUBSTITUTE(D38,CHAR(160),"")," ",""),"_","") -> ISBN%3A9783764353704_Table39 | L38: {=IFERROR(INDEX(AUTO_Public_TSV_FileList!$A$1:$A$1000,MATCH(TRUE(),EXACT(K38,IFERROR(_xlfn.TEXTBEFORE(AUTO_Public_TSV_FileList!$A$1:$A$1000,".tsv"),"")),0)),"notfound")} -> ISBN%3A9783764353704_Table39.tsv | M38: Lütgemeier's area measurements of cortical regions (in mm2) | N38: table | P38: FINISHED | S38: Structure list, species count and the table's size/index role confirmed against the book's own Table 1 key (PDF pp. 264-265) and the printed column header, 2026-08-31. | T38: Reprinted from another author's work, not a Frankfurt-collection measurement. Register as secondary and keep the original author attribution in the item note; check the upstream publication before treating any value as primary. Inherits the whole-source merge gate already recorded for Tables 10/32: seven historical taxon concepts in MANUAL_REVIEW, and source rows that collapse to the same species must be averaged within the item before Tier-1 recency resolution. Resolving that gate once unblocks every Baron item, so build order need not wait on it. | W38: Mammals | X38: cortical surface areas (mm2) | Z38: histological sections | AA38: Lütgemeier (1962) planimetry of cortical regions | AB38: cortical surface area | AE38: secondary
A39: Baron, G., Stephan, H., & Frahm, H. D. (1996). Comparative Neurobiology in Chiroptera: Macromorphology, Brain Structures, Tables, and Atlases. Birkhäuser. | C39: ISBN:9783764353704 | D39: Table 42 | E39: =SUBSTITUTE(SUBSTITUTE(_xlfn.TEXTBEFORE(A39,","), "-", ""), " ", "") -> Baron | F39: {=_xlfn.LET( _xlpm.authors,_xlfn.TEXTBEFORE(A39," ("&G39&")"), _xlpm.hasAmp,ISNUMBER(SEARCH("&",_xlpm.authors)), _xlpm.hasEllipsis,ISNUMBER(SEARCH(_xlfn.UNICHAR(8230),_xlpm.authors)), _xlpm.commasBeforeAmp,IF( _xlpm.hasAmp, LEN(_xlfn.TEXTBEFORE(_xlpm.authors,"&"))-LEN(SUBSTITUTE(_xlfn.TEXTBEFORE(_xlpm.authors,"&"),",","")), 0 ), IF( _xlpm.hasEllipsis, "etal", IF( NOT(_xlpm.hasAmp), "", IF( _xlpm.commasBeforeAmp>2, "etal", SUBSTITUTE(TRIM(_xlfn.TEXTBEFORE(_xlfn.TEXTAFTER(_xlpm.authors,"& "),",")),"-","") ) ) ) )} -> etal | G39: =_xlfn.TEXTBEFORE(_xlfn.TEXTAFTER(A39, "("), ")") -> 1996 | H39: =E39 & IF(F39<>"", "_" & F39, "_") & IF(G39<>"", "_" & G39, "_") & IF(B39<>"", "_" & B39, "") -> Baron_etal_1996 | I39: =_xlfn.LET( _xlpm.doi,IF(C39<>"",C39,_xlfn.TEXTAFTER(A39,"https://doi.org/")), SUBSTITUTE( SUBSTITUTE( SUBSTITUTE( SUBSTITUTE( _xlpm.doi, "/","%2F"), ":","%3A"), "<","%3C"), ">","%3E") ) -> ISBN%3A9783764353704 | J39: =TRIM(_xlfn.TEXTJOIN("_",FALSE(),H39,(SUBSTITUTE(SUBSTITUTE(D39," ",""), "_", "")))) -> Baron_etal_1996_Table42 | K39: =I39 & "_" & SUBSTITUTE(SUBSTITUTE(SUBSTITUTE(D39,CHAR(160),"")," ",""),"_","") -> ISBN%3A9783764353704_Table42 | L39: {=IFERROR(INDEX(AUTO_Public_TSV_FileList!$A$1:$A$1000,MATCH(TRUE(),EXACT(K39,IFERROR(_xlfn.TEXTBEFORE(AUTO_Public_TSV_FileList!$A$1:$A$1000,".tsv"),"")),0)),"notfound")} -> ISBN%3A9783764353704_Table42.tsv | M39: Lütgemeier's area measurements of the semicortex (in mm2) | N39: table | O39: Build only with Tables 39 and 45. Secondary (Lütgemeier 1962). | P39: FINISHED | S39: Structure list, species count and the table's size/index role confirmed against the book's own Table 1 key (PDF pp. 264-265) and the printed column header, 2026-08-31. | T39: Reprinted from another author's work, not a Frankfurt-collection measurement. Register as secondary and keep the original author attribution in the item note; check the upstream publication before treating any value as primary. Inherits the whole-source merge gate already recorded for Tables 10/32: seven historical taxon concepts in MANUAL_REVIEW, and source rows that collapse to the same species must be averaged within the item before Tier-1 recency resolution. Resolving that gate once unblocks every Baron item, so build order need not wait on it. | W39: Mammals | X39: semicortex surface areas (mm2) | Z39: histological sections | AA39: Lütgemeier (1962) planimetry of cortical regions | AB39: cortical surface area | AE39: secondary
A40: Baron, G., Stephan, H., & Frahm, H. D. (1996). Comparative Neurobiology in Chiroptera: Macromorphology, Brain Structures, Tables, and Atlases. Birkhäuser. | C40: ISBN:9783764353704 | D40: Table 45 | E40: =SUBSTITUTE(SUBSTITUTE(_xlfn.TEXTBEFORE(A40,","), "-", ""), " ", "") -> Baron | F40: {=_xlfn.LET( _xlpm.authors,_xlfn.TEXTBEFORE(A40," ("&G40&")"), _xlpm.hasAmp,ISNUMBER(SEARCH("&",_xlpm.authors)), _xlpm.hasEllipsis,ISNUMBER(SEARCH(_xlfn.UNICHAR(8230),_xlpm.authors)), _xlpm.commasBeforeAmp,IF( _xlpm.hasAmp, LEN(_xlfn.TEXTBEFORE(_xlpm.authors,"&"))-LEN(SUBSTITUTE(_xlfn.TEXTBEFORE(_xlpm.authors,"&"),",","")), 0 ), IF( _xlpm.hasEllipsis, "etal", IF( NOT(_xlpm.hasAmp), "", IF( _xlpm.commasBeforeAmp>2, "etal", SUBSTITUTE(TRIM(_xlfn.TEXTBEFORE(_xlfn.TEXTAFTER(_xlpm.authors,"& "),",")),"-","") ) ) ) )} -> etal | G40: =_xlfn.TEXTBEFORE(_xlfn.TEXTAFTER(A40, "("), ")") -> 1996 | H40: =E40 & IF(F40<>"", "_" & F40, "_") & IF(G40<>"", "_" & G40, "_") & IF(B40<>"", "_" & B40, "") -> Baron_etal_1996 | I40: =_xlfn.LET( _xlpm.doi,IF(C40<>"",C40,_xlfn.TEXTAFTER(A40,"https://doi.org/")), SUBSTITUTE( SUBSTITUTE( SUBSTITUTE( SUBSTITUTE( _xlpm.doi, "/","%2F"), ":","%3A"), "<","%3C"), ">","%3E") ) -> ISBN%3A9783764353704 | J40: =TRIM(_xlfn.TEXTJOIN("_",FALSE(),H40,(SUBSTITUTE(SUBSTITUTE(D40," ",""), "_", "")))) -> Baron_etal_1996_Table45 | K40: =I40 & "_" & SUBSTITUTE(SUBSTITUTE(SUBSTITUTE(D40,CHAR(160),"")," ",""),"_","") -> ISBN%3A9783764353704_Table45 | L40: {=IFERROR(INDEX(AUTO_Public_TSV_FileList!$A$1:$A$1000,MATCH(TRUE(),EXACT(K40,IFERROR(_xlfn.TEXTBEFORE(AUTO_Public_TSV_FileList!$A$1:$A$1000,".tsv"),"")),0)),"notfound")} -> ISBN%3A9783764353704_Table45.tsv | M40: Lütgemeier's area measurements of the "bicortex" (in mm2) | N40: table | O40: Build only with Tables 39 and 42. Secondary (Lütgemeier 1962). | P40: FINISHED | S40: Structure list, species count and the table's size/index role confirmed against the book's own Table 1 key (PDF pp. 264-265) and the printed column header, 2026-08-31. | T40: Reprinted from another author's work, not a Frankfurt-collection measurement. Register as secondary and keep the original author attribution in the item note; check the upstream publication before treating any value as primary. Inherits the whole-source merge gate already recorded for Tables 10/32: seven historical taxon concepts in MANUAL_REVIEW, and source rows that collapse to the same species must be averaged within the item before Tier-1 recency resolution. Resolving that gate once unblocks every Baron item, so build order need not wait on it. | W40: Mammals | X40: bicortex surface areas (mm2) | Z40: histological sections | AA40: Lütgemeier (1962) planimetry of cortical regions | AB40: cortical surface area | AE40: secondary
A41: Baron, G., Stephan, H., & Frahm, H. D. (1996). Comparative Neurobiology in Chiroptera: Macromorphology, Brain Structures, Tables, and Atlases. Birkhäuser. | C41: ISBN:9783764353704 | D41: Table 48 | E41: =SUBSTITUTE(SUBSTITUTE(_xlfn.TEXTBEFORE(A41,","), "-", ""), " ", "") -> Baron | F41: {=_xlfn.LET( _xlpm.authors,_xlfn.TEXTBEFORE(A41," ("&G41&")"), _xlpm.hasAmp,ISNUMBER(SEARCH("&",_xlpm.authors)), _xlpm.hasEllipsis,ISNUMBER(SEARCH(_xlfn.UNICHAR(8230),_xlpm.authors)), _xlpm.commasBeforeAmp,IF( _xlpm.hasAmp, LEN(_xlfn.TEXTBEFORE(_xlpm.authors,"&"))-LEN(SUBSTITUTE(_xlfn.TEXTBEFORE(_xlpm.authors,"&"),",","")), 0 ), IF( _xlpm.hasEllipsis, "etal", IF( NOT(_xlpm.hasAmp), "", IF( _xlpm.commasBeforeAmp>2, "etal", SUBSTITUTE(TRIM(_xlfn.TEXTBEFORE(_xlfn.TEXTAFTER(_xlpm.authors,"& "),",")),"-","") ) ) ) )} -> etal | G41: =_xlfn.TEXTBEFORE(_xlfn.TEXTAFTER(A41, "("), ")") -> 1996 | H41: =E41 & IF(F41<>"", "_" & F41, "_") & IF(G41<>"", "_" & G41, "_") & IF(B41<>"", "_" & B41, "") -> Baron_etal_1996 | I41: =_xlfn.LET( _xlpm.doi,IF(C41<>"",C41,_xlfn.TEXTAFTER(A41,"https://doi.org/")), SUBSTITUTE( SUBSTITUTE( SUBSTITUTE( SUBSTITUTE( _xlpm.doi, "/","%2F"), ":","%3A"), "<","%3C"), ">","%3E") ) -> ISBN%3A9783764353704 | J41: =TRIM(_xlfn.TEXTJOIN("_",FALSE(),H41,(SUBSTITUTE(SUBSTITUTE(D41," ",""), "_", "")))) -> Baron_etal_1996_Table48 | K41: =I41 & "_" & SUBSTITUTE(SUBSTITUTE(SUBSTITUTE(D41,CHAR(160),"")," ",""),"_","") -> ISBN%3A9783764353704_Table48 | L41: {=IFERROR(INDEX(AUTO_Public_TSV_FileList!$A$1:$A$1000,MATCH(TRUE(),EXACT(K41,IFERROR(_xlfn.TEXTBEFORE(AUTO_Public_TSV_FileList!$A$1:$A$1000,".tsv"),"")),0)),"notfound")} -> ISBN%3A9783764353704_Table48.tsv | M41: Brodmann's area measurements of cortical regions (in mm2) | N41: table | P41: FINISHED | S41: Structure list, species count and the table's size/index role confirmed against the book's own Table 1 key (PDF pp. 264-265) and the printed column header, 2026-08-31. | T41: Reprinted from another author's work, not a Frankfurt-collection measurement. Register as secondary and keep the original author attribution in the item note; check the upstream publication before treating any value as primary. Inherits the whole-source merge gate already recorded for Tables 10/32: seven historical taxon concepts in MANUAL_REVIEW, and source rows that collapse to the same species must be averaged within the item before Tier-1 recency resolution. Resolving that gate once unblocks every Baron item, so build order need not wait on it. | W41: Mammals | X41: cortical surface areas (mm2) | Y41: cortical surface areas (mm2) | Z41: histological sections | AB41: cortical surface area | AE41: secondary | AF41: Brodmann (1913) planimetry of cortical regions
A42: Baron, G., Stephan, H., & Frahm, H. D. (1996). Comparative Neurobiology in Chiroptera: Macromorphology, Brain Structures, Tables, and Atlases. Birkhäuser. | C42: ISBN:9783764353704 | D42: Table 5 | E42: =SUBSTITUTE(SUBSTITUTE(_xlfn.TEXTBEFORE(A42,","), "-", ""), " ", "") -> Baron | F42: {=_xlfn.LET( _xlpm.authors,_xlfn.TEXTBEFORE(A42," ("&G42&")"), _xlpm.hasAmp,ISNUMBER(SEARCH("&",_xlpm.authors)), _xlpm.hasEllipsis,ISNUMBER(SEARCH(_xlfn.UNICHAR(8230),_xlpm.authors)), _xlpm.commasBeforeAmp,IF( _xlpm.hasAmp, LEN(_xlfn.TEXTBEFORE(_xlpm.authors,"&"))-LEN(SUBSTITUTE(_xlfn.TEXTBEFORE(_xlpm.authors,"&"),",","")), 0 ), IF( _xlpm.hasEllipsis, "etal", IF( NOT(_xlpm.hasAmp), "", IF( _xlpm.commasBeforeAmp>2, "etal", SUBSTITUTE(TRIM(_xlfn.TEXTBEFORE(_xlfn.TEXTAFTER(_xlpm.authors,"& "),",")),"-","") ) ) ) )} -> etal | G42: =_xlfn.TEXTBEFORE(_xlfn.TEXTAFTER(A42, "("), ")") -> 1996 | H42: =E42 & IF(F42<>"", "_" & F42, "_") & IF(G42<>"", "_" & G42, "_") & IF(B42<>"", "_" & B42, "") -> Baron_etal_1996 | I42: =_xlfn.LET( _xlpm.doi,IF(C42<>"",C42,_xlfn.TEXTAFTER(A42,"https://doi.org/")), SUBSTITUTE( SUBSTITUTE( SUBSTITUTE( SUBSTITUTE( _xlpm.doi, "/","%2F"), ":","%3A"), "<","%3C"), ">","%3E") ) -> ISBN%3A9783764353704 | J42: =TRIM(_xlfn.TEXTJOIN("_",FALSE(),H42,(SUBSTITUTE(SUBSTITUTE(D42," ",""), "_", "")))) -> Baron_etal_1996_Table5 | K42: =I42 & "_" & SUBSTITUTE(SUBSTITUTE(SUBSTITUTE(D42,CHAR(160),"")," ",""),"_","") -> ISBN%3A9783764353704_Table5 | L42: {=IFERROR(INDEX(AUTO_Public_TSV_FileList!$A$1:$A$1000,MATCH(TRUE(),EXACT(K42,IFERROR(_xlfn.TEXTBEFORE(AUTO_Public_TSV_FileList!$A$1:$A$1000,".tsv"),"")),0)),"notfound")} -> ISBN%3A9783764353704_Table5.tsv | M42: Average body weights (BoW) and brain weights (BrW) of 342 species and/or subspecies of bats | N42: table | P42: FINISHED | S42: Structure list, species count and the table's size/index role confirmed against the book's own Table 1 key (PDF pp. 264-265) and the printed column header, 2026-08-31. | T42: Inherits the whole-source merge gate already recorded for Tables 10/32: seven historical taxon concepts in MANUAL_REVIEW, and source rows that collapse to the same species must be averaged within the item before Tier-1 recency resolution. Resolving that gate once unblocks every Baron item, so build order need not wait on it. | W42: Mammals | X42: body mass (g); brain mass (mg) | Y42: body mass (g); brain mass (mg) | AB42: body mass; brain mass | AC42: Stephan | AD42: Stephan | AE42: primary | AG42: Build, highest priority of the untranscribed set: 342 species/subspecies is the largest block in the book and larger than the 272 in Tables 10/32. Feeds __merging_brain_mass. Keep the source-of-data column — it separates Stephan-collection values from compiled literature values, so the item is part primary, part secondary at row level. Check the multi-line sex rows are not double-counted, and check overlap with Ashwell 2020 and the other held bat body/brain sources before wiring.
A43: Baron, G., Stephan, H., & Frahm, H. D. (1996). Comparative Neurobiology in Chiroptera: Macromorphology, Brain Structures, Tables, and Atlases. Birkhäuser. | C43: ISBN:9783764353704 | D43: Table 51 | E43: =SUBSTITUTE(SUBSTITUTE(_xlfn.TEXTBEFORE(A43,","), "-", ""), " ", "") -> Baron | F43: {=_xlfn.LET( _xlpm.authors,_xlfn.TEXTBEFORE(A43," ("&G43&")"), _xlpm.hasAmp,ISNUMBER(SEARCH("&",_xlpm.authors)), _xlpm.hasEllipsis,ISNUMBER(SEARCH(_xlfn.UNICHAR(8230),_xlpm.authors)), _xlpm.commasBeforeAmp,IF( _xlpm.hasAmp, LEN(_xlfn.TEXTBEFORE(_xlpm.authors,"&"))-LEN(SUBSTITUTE(_xlfn.TEXTBEFORE(_xlpm.authors,"&"),",","")), 0 ), IF( _xlpm.hasEllipsis, "etal", IF( NOT(_xlpm.hasAmp), "", IF( _xlpm.commasBeforeAmp>2, "etal", SUBSTITUTE(TRIM(_xlfn.TEXTBEFORE(_xlfn.TEXTAFTER(_xlpm.authors,"& "),",")),"-","") ) ) ) )} -> etal | G43: =_xlfn.TEXTBEFORE(_xlfn.TEXTAFTER(A43, "("), ")") -> 1996 | H43: =E43 & IF(F43<>"", "_" & F43, "_") & IF(G43<>"", "_" & G43, "_") & IF(B43<>"", "_" & B43, "") -> Baron_etal_1996 | I43: =_xlfn.LET( _xlpm.doi,IF(C43<>"",C43,_xlfn.TEXTAFTER(A43,"https://doi.org/")), SUBSTITUTE( SUBSTITUTE( SUBSTITUTE( SUBSTITUTE( _xlpm.doi, "/","%2F"), ":","%3A"), "<","%3C"), ">","%3E") ) -> ISBN%3A9783764353704 | J43: =TRIM(_xlfn.TEXTJOIN("_",FALSE(),H43,(SUBSTITUTE(SUBSTITUTE(D43," ",""), "_", "")))) -> Baron_etal_1996_Table51 | K43: =I43 & "_" & SUBSTITUTE(SUBSTITUTE(SUBSTITUTE(D43,CHAR(160),"")," ",""),"_","") -> ISBN%3A9783764353704_Table51 | L43: {=IFERROR(INDEX(AUTO_Public_TSV_FileList!$A$1:$A$1000,MATCH(TRUE(),EXACT(K43,IFERROR(_xlfn.TEXTBEFORE(AUTO_Public_TSV_FileList!$A$1:$A$1000,".tsv"),"")),0)),"notfound")} -> ISBN%3A9783764353704_Table51.tsv | M43: Pirlot's data of body and brain weights and of the volumes of the five fundamental brain parts and seven telencephalon components in mm3 | N43: table | P43: FINISHED | S43: Structure list, species count and the table's size/index role confirmed against the book's own Table 1 key (PDF pp. 264-265) and the printed column header, 2026-08-31. | T43: Reprinted from another author's work, not a Frankfurt-collection measurement. Register as secondary and keep the original author attribution in the item note; check the upstream publication before treating any value as primary. Inherits the whole-source merge gate already recorded for Tables 10/32: seven historical taxon concepts in MANUAL_REVIEW, and source rows that collapse to the same species must be averaged within the item before Tier-1 recency resolution. Resolving that gate once unblocks every Baron item, so build order need not wait on it. | W43: Mammals | X43: brain structure volumes (mm3); body and brain weight | Z43: histological sections | AA43: volumetry | AB43: volume | AE43: secondary | AG43: Build. Small but genuinely additive: six species that the 272-row tables do not cover, in the same structure scheme, so they extend rather than duplicate Tables 10/32. Note that paleocortex and amygdala are pooled here (PAL+AMY) whereas Table 32 separates them. Secondary within the book — the measurements are Pirlot's — and it is a different Pirlot dataset from Stephan & Pirlot (1970), which shares no species with it.
A44: Baron, G., Stephan, H., & Frahm, H. D. (1996). Comparative Neurobiology in Chiroptera: Macromorphology, Brain Structures, Tables, and Atlases. Birkhäuser. | C44: ISBN:9783764353704 | D44: Table 8 | E44: =SUBSTITUTE(SUBSTITUTE(_xlfn.TEXTBEFORE(A44,","), "-", ""), " ", "") -> Baron | F44: {=_xlfn.LET( _xlpm.authors,_xlfn.TEXTBEFORE(A44," ("&G44&")"), _xlpm.hasAmp,ISNUMBER(SEARCH("&",_xlpm.authors)), _xlpm.hasEllipsis,ISNUMBER(SEARCH(_xlfn.UNICHAR(8230),_xlpm.authors)), _xlpm.commasBeforeAmp,IF( _xlpm.hasAmp, LEN(_xlfn.TEXTBEFORE(_xlpm.authors,"&"))-LEN(SUBSTITUTE(_xlfn.TEXTBEFORE(_xlpm.authors,"&"),",","")), 0 ), IF( _xlpm.hasEllipsis, "etal", IF( NOT(_xlpm.hasAmp), "", IF( _xlpm.commasBeforeAmp>2, "etal", SUBSTITUTE(TRIM(_xlfn.TEXTBEFORE(_xlfn.TEXTAFTER(_xlpm.authors,"& "),",")),"-","") ) ) ) )} -> etal | G44: =_xlfn.TEXTBEFORE(_xlfn.TEXTAFTER(A44, "("), ")") -> 1996 | H44: =E44 & IF(F44<>"", "_" & F44, "_") & IF(G44<>"", "_" & G44, "_") & IF(B44<>"", "_" & B44, "") -> Baron_etal_1996 | I44: =_xlfn.LET( _xlpm.doi,IF(C44<>"",C44,_xlfn.TEXTAFTER(A44,"https://doi.org/")), SUBSTITUTE( SUBSTITUTE( SUBSTITUTE( SUBSTITUTE( _xlpm.doi, "/","%2F"), ":","%3A"), "<","%3C"), ">","%3E") ) -> ISBN%3A9783764353704 | J44: =TRIM(_xlfn.TEXTJOIN("_",FALSE(),H44,(SUBSTITUTE(SUBSTITUTE(D44," ",""), "_", "")))) -> Baron_etal_1996_Table8 | K44: =I44 & "_" & SUBSTITUTE(SUBSTITUTE(SUBSTITUTE(D44,CHAR(160),"")," ",""),"_","") -> ISBN%3A9783764353704_Table8 | L44: {=IFERROR(INDEX(AUTO_Public_TSV_FileList!$A$1:$A$1000,MATCH(TRUE(),EXACT(K44,IFERROR(_xlfn.TEXTBEFORE(AUTO_Public_TSV_FileList!$A$1:$A$1000,".tsv"),"")),0)),"notfound")} -> ISBN%3A9783764353704_Table8.tsv | M44: Volumes of net brain (NET), ventricles (VENT) and rests (REST) and their percentages relative to standard brain volumes | N44: table | O44: Printed columns: n, then mm3 and % for each of NET, VENT and REST. Only the three mm3 columns are raw; the three percentage columns are derived from them against the standard brain volume and should not be carried as measurements. Average percentages are Table 9 — do not transcribe. | P44: FINISHED | S44: Structure list, species count and the table's size/index role confirmed against the book's own Table 1 key (PDF pp. 264-265) and the printed column header, 2026-08-31. | T44: Inherits the whole-source merge gate already recorded for Tables 10/32: seven historical taxon concepts in MANUAL_REVIEW, and source rows that collapse to the same species must be averaged within the item before Tier-1 recency resolution. Resolving that gate once unblocks every Baron item, so build order need not wait on it. | W44: Mammals | X44: net brain volume; ventricle volume; rest volume | Y44: net brain volume; ventricle volume; rest volume | Z44: histological sections | AB44: volume | AC44: Stephan | AD44: Stephan | AE44: primary | AG44: Build. NET brain volume is the denominator the rest of the book's indices are built on, and the ventricle volumes are not available from any other held source. Transcribe the mm3 columns only.
A45: Bauernfeind, A. L., de Sousa, A. A., Avasthi, T., Dobson, S. D., Raghanti, M. A., Lewandowski, A. H., Zilles, K., Semendeferi, K., Allman, J. M., Craig, A. D., Hof, P. R., & Sherwood, C. C. (2013). A volumetric comparison of the insular cortex and its subregions in primates. J Hum Evol, 64(4), 263-279. https://doi.org/10.1016/j.jhevol.2012.12.003 | D45: Table 1 | E45: =SUBSTITUTE(SUBSTITUTE(_xlfn.TEXTBEFORE(A45,","), "-", ""), " ", "") -> Bauernfeind | F45: {=_xlfn.LET( _xlpm.authors,_xlfn.TEXTBEFORE(A45," ("&G45&")"), _xlpm.hasAmp,ISNUMBER(SEARCH("&",_xlpm.authors)), _xlpm.hasEllipsis,ISNUMBER(SEARCH(_xlfn.UNICHAR(8230),_xlpm.authors)), _xlpm.commasBeforeAmp,IF( _xlpm.hasAmp, LEN(_xlfn.TEXTBEFORE(_xlpm.authors,"&"))-LEN(SUBSTITUTE(_xlfn.TEXTBEFORE(_xlpm.authors,"&"),",","")), 0 ), IF( _xlpm.hasEllipsis, "etal", IF( NOT(_xlpm.hasAmp), "", IF( _xlpm.commasBeforeAmp>2, "etal", SUBSTITUTE(TRIM(_xlfn.TEXTBEFORE(_xlfn.TEXTAFTER(_xlpm.authors,"& "),",")),"-","") ) ) ) )} -> etal | G45: =_xlfn.TEXTBEFORE(_xlfn.TEXTAFTER(A45, "("), ")") -> 2013 | H45: =E45 & IF(F45<>"", "_" & F45, "_") & IF(G45<>"", "_" & G45, "_") & IF(B45<>"", "_" & B45, "") -> Bauernfeind_etal_2013 | I45: =_xlfn.LET( _xlpm.doi,IF(C45<>"",C45,_xlfn.TEXTAFTER(A45,"https://doi.org/")), SUBSTITUTE( SUBSTITUTE( SUBSTITUTE( SUBSTITUTE( _xlpm.doi, "/","%2F"), ":","%3A"), "<","%3C"), ">","%3E") ) -> 10.1016%2Fj.jhevol.2012.12.003 | J45: =TRIM(_xlfn.TEXTJOIN("_",FALSE(),H45,(SUBSTITUTE(SUBSTITUTE(D45," ",""), "_", "")))) -> Bauernfeind_etal_2013_Table1 | K45: =I45 & "_" & SUBSTITUTE(SUBSTITUTE(SUBSTITUTE(D45,CHAR(160),"")," ",""),"_","") -> 10.1016%2Fj.jhevol.2012.12.003_Table1 | L45: {=IFERROR(INDEX(AUTO_Public_TSV_FileList!$A$1:$A$1000,MATCH(TRUE(),EXACT(K45,IFERROR(_xlfn.TEXTBEFORE(AUTO_Public_TSV_FileList!$A$1:$A$1000,".tsv"),"")),0)),"notfound")} -> 10.1016%2Fj.jhevol.2012.12.003_Table1.tsv | M45: Volumetric comparison of the insular cortex (Table 1) | N45: table | P45: FINISHED | W45: Primates | X45: insular cortex volumes | Z45: histological sections | AA45: volumetry | AB45: volume | AC45: Stephan, Sherwood | AE45: primary
A46: Bauernfeind, A. L., de Sousa, A. A., Avasthi, T., Dobson, S. D., Raghanti, M. A., Lewandowski, A. H., Zilles, K., Semendeferi, K., Allman, J. M., Craig, A. D., Hof, P. R., & Sherwood, C. C. (2013). A volumetric comparison of the insular cortex and its subregions in primates. J Hum Evol, 64(4), 263-279. https://doi.org/10.1016/j.jhevol.2012.12.003 | D46: Table 2 | E46: =SUBSTITUTE(SUBSTITUTE(_xlfn.TEXTBEFORE(A46,","), "-", ""), " ", "") -> Bauernfeind | F46: {=_xlfn.LET( _xlpm.authors,_xlfn.TEXTBEFORE(A46," ("&G46&")"), _xlpm.hasAmp,ISNUMBER(SEARCH("&",_xlpm.authors)), _xlpm.hasEllipsis,ISNUMBER(SEARCH(_xlfn.UNICHAR(8230),_xlpm.authors)), _xlpm.commasBeforeAmp,IF( _xlpm.hasAmp, LEN(_xlfn.TEXTBEFORE(_xlpm.authors,"&"))-LEN(SUBSTITUTE(_xlfn.TEXTBEFORE(_xlpm.authors,"&"),",","")), 0 ), IF( _xlpm.hasEllipsis, "etal", IF( NOT(_xlpm.hasAmp), "", IF( _xlpm.commasBeforeAmp>2, "etal", SUBSTITUTE(TRIM(_xlfn.TEXTBEFORE(_xlfn.TEXTAFTER(_xlpm.authors,"& "),",")),"-","") ) ) ) )} -> etal | G46: =_xlfn.TEXTBEFORE(_xlfn.TEXTAFTER(A46, "("), ")") -> 2013 | H46: =E46 & IF(F46<>"", "_" & F46, "_") & IF(G46<>"", "_" & G46, "_") & IF(B46<>"", "_" & B46, "") -> Bauernfeind_etal_2013 | I46: =_xlfn.LET( _xlpm.doi,IF(C46<>"",C46,_xlfn.TEXTAFTER(A46,"https://doi.org/")), SUBSTITUTE( SUBSTITUTE( SUBSTITUTE( SUBSTITUTE( _xlpm.doi, "/","%2F"), ":","%3A"), "<","%3C"), ">","%3E") ) -> 10.1016%2Fj.jhevol.2012.12.003 | J46: =TRIM(_xlfn.TEXTJOIN("_",FALSE(),H46,(SUBSTITUTE(SUBSTITUTE(D46," ",""), "_", "")))) -> Bauernfeind_etal_2013_Table2 | K46: =I46 & "_" & SUBSTITUTE(SUBSTITUTE(SUBSTITUTE(D46,CHAR(160),"")," ",""),"_","") -> 10.1016%2Fj.jhevol.2012.12.003_Table2 | L46: {=IFERROR(INDEX(AUTO_Public_TSV_FileList!$A$1:$A$1000,MATCH(TRUE(),EXACT(K46,IFERROR(_xlfn.TEXTBEFORE(AUTO_Public_TSV_FileList!$A$1:$A$1000,".tsv"),"")),0)),"notfound")} -> 10.1016%2Fj.jhevol.2012.12.003_Table2.tsv | N46: table | P46: FINISHED | W46: Primates | X46: insular cortex volumes | Z46: histological sections | AA46: volumetry | AB46: volume | AC46: Stephan, Sherwood | AE46: primary
A47: Bauernfeind, A. L., de Sousa, A. A., Avasthi, T., Dobson, S. D., Raghanti, M. A., Lewandowski, A. H., Zilles, K., Semendeferi, K., Allman, J. M., Craig, A. D., Hof, P. R., & Sherwood, C. C. (2013). A volumetric comparison of the insular cortex and its subregions in primates. J Hum Evol, 64(4), 263-279. https://doi.org/10.1016/j.jhevol.2012.12.003 | D47: Table 3 | E47: =SUBSTITUTE(SUBSTITUTE(_xlfn.TEXTBEFORE(A47,","), "-", ""), " ", "") -> Bauernfeind | F47: {=_xlfn.LET( _xlpm.authors,_xlfn.TEXTBEFORE(A47," ("&G47&")"), _xlpm.hasAmp,ISNUMBER(SEARCH("&",_xlpm.authors)), _xlpm.hasEllipsis,ISNUMBER(SEARCH(_xlfn.UNICHAR(8230),_xlpm.authors)), _xlpm.commasBeforeAmp,IF( _xlpm.hasAmp, LEN(_xlfn.TEXTBEFORE(_xlpm.authors,"&"))-LEN(SUBSTITUTE(_xlfn.TEXTBEFORE(_xlpm.authors,"&"),",","")), 0 ), IF( _xlpm.hasEllipsis, "etal", IF( NOT(_xlpm.hasAmp), "", IF( _xlpm.commasBeforeAmp>2, "etal", SUBSTITUTE(TRIM(_xlfn.TEXTBEFORE(_xlfn.TEXTAFTER(_xlpm.authors,"& "),",")),"-","") ) ) ) )} -> etal | G47: =_xlfn.TEXTBEFORE(_xlfn.TEXTAFTER(A47, "("), ")") -> 2013 | H47: =E47 & IF(F47<>"", "_" & F47, "_") & IF(G47<>"", "_" & G47, "_") & IF(B47<>"", "_" & B47, "") -> Bauernfeind_etal_2013 | I47: =_xlfn.LET( _xlpm.doi,IF(C47<>"",C47,_xlfn.TEXTAFTER(A47,"https://doi.org/")), SUBSTITUTE( SUBSTITUTE( SUBSTITUTE( SUBSTITUTE( _xlpm.doi, "/","%2F"), ":","%3A"), "<","%3C"), ">","%3E") ) -> 10.1016%2Fj.jhevol.2012.12.003 | J47: =TRIM(_xlfn.TEXTJOIN("_",FALSE(),H47,(SUBSTITUTE(SUBSTITUTE(D47," ",""), "_", "")))) -> Bauernfeind_etal_2013_Table3 | K47: =I47 & "_" & SUBSTITUTE(SUBSTITUTE(SUBSTITUTE(D47,CHAR(160),"")," ",""),"_","") -> 10.1016%2Fj.jhevol.2012.12.003_Table3 | L47: {=IFERROR(INDEX(AUTO_Public_TSV_FileList!$A$1:$A$1000,MATCH(TRUE(),EXACT(K47,IFERROR(_xlfn.TEXTBEFORE(AUTO_Public_TSV_FileList!$A$1:$A$1000,".tsv"),"")),0)),"notfound")} -> 10.1016%2Fj.jhevol.2012.12.003_Table3.tsv | N47: table | P47: FINISHED | W47: Primates | X47: insular cortex volumes | Z47: histological sections | AA47: volumetry | AB47: volume | AC47: Stephan, Sherwood | AE47: primary
A48: Bianchi, S., Stimpson, C. D., Bauernfeind, A. L., Schapiro, S. J., Baze, W. B., McArthur, M. J., Bronson, E., Hopkins, W. D., Semendeferi, K., Jacobs, B., Hof, P. R., & Sherwood, C. C. (2012). Dendritic morphology of pyramidal neurons in the chimpanzee neocortex: regional specializations and comparison to humans. Cereb Cortex, 23(10), 2429-2436. https://doi.org/10.1093/cercor/bhs239 | D48: Table 1 | E48: =SUBSTITUTE(SUBSTITUTE(_xlfn.TEXTBEFORE(A48,","), "-", ""), " ", "") -> Bianchi | F48: {=_xlfn.LET( _xlpm.authors,_xlfn.TEXTBEFORE(A48," ("&G48&")"), _xlpm.hasAmp,ISNUMBER(SEARCH("&",_xlpm.authors)), _xlpm.hasEllipsis,ISNUMBER(SEARCH(_xlfn.UNICHAR(8230),_xlpm.authors)), _xlpm.commasBeforeAmp,IF( _xlpm.hasAmp, LEN(_xlfn.TEXTBEFORE(_xlpm.authors,"&"))-LEN(SUBSTITUTE(_xlfn.TEXTBEFORE(_xlpm.authors,"&"),",","")), 0 ), IF( _xlpm.hasEllipsis, "etal", IF( NOT(_xlpm.hasAmp), "", IF( _xlpm.commasBeforeAmp>2, "etal", SUBSTITUTE(TRIM(_xlfn.TEXTBEFORE(_xlfn.TEXTAFTER(_xlpm.authors,"& "),",")),"-","") ) ) ) )} -> etal | G48: =_xlfn.TEXTBEFORE(_xlfn.TEXTAFTER(A48, "("), ")") -> 2012 | H48: =E48 & IF(F48<>"", "_" & F48, "_") & IF(G48<>"", "_" & G48, "_") & IF(B48<>"", "_" & B48, "") -> Bianchi_etal_2012 | I48: =_xlfn.LET( _xlpm.doi,IF(C48<>"",C48,_xlfn.TEXTAFTER(A48,"https://doi.org/")), SUBSTITUTE( SUBSTITUTE( SUBSTITUTE( SUBSTITUTE( _xlpm.doi, "/","%2F"), ":","%3A"), "<","%3C"), ">","%3E") ) -> 10.1093%2Fcercor%2Fbhs239 | J48: =TRIM(_xlfn.TEXTJOIN("_",FALSE(),H48,(SUBSTITUTE(SUBSTITUTE(D48," ",""), "_", "")))) -> Bianchi_etal_2012_Table1 | K48: =I48 & "_" & SUBSTITUTE(SUBSTITUTE(SUBSTITUTE(D48,CHAR(160),"")," ",""),"_","") -> 10.1093%2Fcercor%2Fbhs239_Table1 | L48: {=IFERROR(INDEX(AUTO_Public_TSV_FileList!$A$1:$A$1000,MATCH(TRUE(),EXACT(K48,IFERROR(_xlfn.TEXTBEFORE(AUTO_Public_TSV_FileList!$A$1:$A$1000,".tsv"),"")),0)),"notfound")} -> 10.1093%2Fcercor%2Fbhs239_Table1.tsv | M48: Demographic information for chimpanzee (N=7) and human samples (N=8) | N48: PDF; table/figure | P48: FINISHED | R48: https://doi.org/10.1093/cercor/bhs239 | T48: overlapping publication lineage; retain specimen and source-level provenance | V48: cortical pyramidal-neuron morphology | W48: Primates | X48: dendritic morphology; spine measures; sample metadata | Y48: Sample metadata: age, sex, post-mortem interval, fixation length | AA48: Golgi or intracellular Lucifer Yellow morphology, as specified in source | AB48: cell morphology / metadata | AE48: primary | AG48: Add; essential specimen provenance.
A49: Bianchi, S., Stimpson, C. D., Bauernfeind, A. L., Schapiro, S. J., Baze, W. B., McArthur, M. J., Bronson, E., Hopkins, W. D., Semendeferi, K., Jacobs, B., Hof, P. R., & Sherwood, C. C. (2012). Dendritic morphology of pyramidal neurons in the chimpanzee neocortex: regional specializations and comparison to humans. Cereb Cortex, 23(10), 2429-2436. https://doi.org/10.1093/cercor/bhs239 | D49: Table 2 | E49: =SUBSTITUTE(SUBSTITUTE(_xlfn.TEXTBEFORE(A49,","), "-", ""), " ", "") -> Bianchi | F49: {=_xlfn.LET( _xlpm.authors,_xlfn.TEXTBEFORE(A49," ("&G49&")"), _xlpm.hasAmp,ISNUMBER(SEARCH("&",_xlpm.authors)), _xlpm.hasEllipsis,ISNUMBER(SEARCH(_xlfn.UNICHAR(8230),_xlpm.authors)), _xlpm.commasBeforeAmp,IF( _xlpm.hasAmp, LEN(_xlfn.TEXTBEFORE(_xlpm.authors,"&"))-LEN(SUBSTITUTE(_xlfn.TEXTBEFORE(_xlpm.authors,"&"),",","")), 0 ), IF( _xlpm.hasEllipsis, "etal", IF( NOT(_xlpm.hasAmp), "", IF( _xlpm.commasBeforeAmp>2, "etal", SUBSTITUTE(TRIM(_xlfn.TEXTBEFORE(_xlfn.TEXTAFTER(_xlpm.authors,"& "),",")),"-","") ) ) ) )} -> etal | G49: =_xlfn.TEXTBEFORE(_xlfn.TEXTAFTER(A49, "("), ")") -> 2012 | H49: =E49 & IF(F49<>"", "_" & F49, "_") & IF(G49<>"", "_" & G49, "_") & IF(B49<>"", "_" & B49, "") -> Bianchi_etal_2012 | I49: =_xlfn.LET( _xlpm.doi,IF(C49<>"",C49,_xlfn.TEXTAFTER(A49,"https://doi.org/")), SUBSTITUTE( SUBSTITUTE( SUBSTITUTE( SUBSTITUTE( _xlpm.doi, "/","%2F"), ":","%3A"), "<","%3C"), ">","%3E") ) -> 10.1093%2Fcercor%2Fbhs239 | J49: =TRIM(_xlfn.TEXTJOIN("_",FALSE(),H49,(SUBSTITUTE(SUBSTITUTE(D49," ",""), "_", "")))) -> Bianchi_etal_2012_Table2 | K49: =I49 & "_" & SUBSTITUTE(SUBSTITUTE(SUBSTITUTE(D49,CHAR(160),"")," ",""),"_","") -> 10.1093%2Fcercor%2Fbhs239_Table2 | L49: {=IFERROR(INDEX(AUTO_Public_TSV_FileList!$A$1:$A$1000,MATCH(TRUE(),EXACT(K49,IFERROR(_xlfn.TEXTBEFORE(AUTO_Public_TSV_FileList!$A$1:$A$1000,".tsv"),"")),0)),"notfound")} -> 10.1093%2Fcercor%2Fbhs239_Table2.tsv | M49: Dependent measures in areas 3b, 4, 18, and 10 in chimpanzees and humans | N49: PDF; table/figure | P49: FINISHED | R49: https://doi.org/10.1093/cercor/bhs239 | T49: overlapping publication lineage; retain specimen and source-level provenance | V49: cortical pyramidal-neuron morphology | W49: Primates | X49: dendritic morphology; spine measures; sample metadata | Y49: Cell soma area/depth, TDL, MSL, DSC, DSN, DSD, dendritic tree count by species and cortical area | AA49: Golgi or intracellular Lucifer Yellow morphology, as specified in source | AB49: cell morphology / metadata | AE49: primary quantitative table; human values reuse Jacobs 1997/2001 | AG49: Add; core trait table. Flag human values as reused source lineage.
A50: Boddy, A. M., McGowen, M. R., Sherwood, C. C., Grossman, L. I., Goodman, M., & Wildman, D. E. (2012). Comparative analysis of encephalization in mammals reveals relaxed constraints on anthropoid primate and cetacean brain scaling. J Evol Biol, 25(5), 981-994. https://doi.org/10.1111/j.1420-9101.2012.02491.x | D50: brain_body_database_v2.txt | E50: =SUBSTITUTE(SUBSTITUTE(_xlfn.TEXTBEFORE(A50,","), "-", ""), " ", "") -> Boddy | F50: {=_xlfn.LET( _xlpm.authors,_xlfn.TEXTBEFORE(A50," ("&G50&")"), _xlpm.hasAmp,ISNUMBER(SEARCH("&",_xlpm.authors)), _xlpm.hasEllipsis,ISNUMBER(SEARCH(_xlfn.UNICHAR(8230),_xlpm.authors)), _xlpm.commasBeforeAmp,IF( _xlpm.hasAmp, LEN(_xlfn.TEXTBEFORE(_xlpm.authors,"&"))-LEN(SUBSTITUTE(_xlfn.TEXTBEFORE(_xlpm.authors,"&"),",","")), 0 ), IF( _xlpm.hasEllipsis, "etal", IF( NOT(_xlpm.hasAmp), "", IF( _xlpm.commasBeforeAmp>2, "etal", SUBSTITUTE(TRIM(_xlfn.TEXTBEFORE(_xlfn.TEXTAFTER(_xlpm.authors,"& "),",")),"-","") ) ) ) )} -> etal | G50: =_xlfn.TEXTBEFORE(_xlfn.TEXTAFTER(A50, "("), ")") -> 2012 | H50: =E50 & IF(F50<>"", "_" & F50, "_") & IF(G50<>"", "_" & G50, "_") & IF(B50<>"", "_" & B50, "") -> Boddy_etal_2012 | I50: =_xlfn.LET( _xlpm.doi,IF(C50<>"",C50,_xlfn.TEXTAFTER(A50,"https://doi.org/")), SUBSTITUTE( SUBSTITUTE( SUBSTITUTE( SUBSTITUTE( _xlpm.doi, "/","%2F"), ":","%3A"), "<","%3C"), ">","%3E") ) -> 10.1111%2Fj.1420-9101.2012.02491.x | J50: =TRIM(_xlfn.TEXTJOIN("_",FALSE(),H50,(SUBSTITUTE(SUBSTITUTE(D50," ",""), "_", "")))) -> Boddy_etal_2012_brainbodydatabasev2.txt | K50: =I50 & "_" & SUBSTITUTE(SUBSTITUTE(SUBSTITUTE(D50,CHAR(160),"")," ",""),"_","") -> 10.1111%2Fj.1420-9101.2012.02491.x_brainbodydatabasev2.txt | L50: {=IFERROR(INDEX(AUTO_Public_TSV_FileList!$A$1:$A$1000,MATCH(TRUE(),EXACT(K50,IFERROR(_xlfn.TEXTBEFORE(AUTO_Public_TSV_FileList!$A$1:$A$1000,".tsv"),"")),0)),"notfound")} -> notfound | N50: the individuals values | P50: FINISHED
A51: Boddy, A. M., McGowen, M. R., Sherwood, C. C., Grossman, L. I., Goodman, M., & Wildman, D. E. (2012). Comparative analysis of encephalization in mammals reveals relaxed constraints on anthropoid primate and cetacean brain scaling. J Evol Biol, 25(5), 981-994. https://doi.org/10.1111/j.1420-9101.2012.02491.x | D51: Table S1 | E51: =SUBSTITUTE(SUBSTITUTE(_xlfn.TEXTBEFORE(A51,","), "-", ""), " ", "") -> Boddy | F51: {=_xlfn.LET( _xlpm.authors,_xlfn.TEXTBEFORE(A51," ("&G51&")"), _xlpm.hasAmp,ISNUMBER(SEARCH("&",_xlpm.authors)), _xlpm.hasEllipsis,ISNUMBER(SEARCH(_xlfn.UNICHAR(8230),_xlpm.authors)), _xlpm.commasBeforeAmp,IF( _xlpm.hasAmp, LEN(_xlfn.TEXTBEFORE(_xlpm.authors,"&"))-LEN(SUBSTITUTE(_xlfn.TEXTBEFORE(_xlpm.authors,"&"),",","")), 0 ), IF( _xlpm.hasEllipsis, "etal", IF( NOT(_xlpm.hasAmp), "", IF( _xlpm.commasBeforeAmp>2, "etal", SUBSTITUTE(TRIM(_xlfn.TEXTBEFORE(_xlfn.TEXTAFTER(_xlpm.authors,"& "),",")),"-","") ) ) ) )} -> etal | G51: =_xlfn.TEXTBEFORE(_xlfn.TEXTAFTER(A51, "("), ")") -> 2012 | H51: =E51 & IF(F51<>"", "_" & F51, "_") & IF(G51<>"", "_" & G51, "_") & IF(B51<>"", "_" & B51, "") -> Boddy_etal_2012 | I51: =_xlfn.LET( _xlpm.doi,IF(C51<>"",C51,_xlfn.TEXTAFTER(A51,"https://doi.org/")), SUBSTITUTE( SUBSTITUTE( SUBSTITUTE( SUBSTITUTE( _xlpm.doi, "/","%2F"), ":","%3A"), "<","%3C"), ">","%3E") ) -> 10.1111%2Fj.1420-9101.2012.02491.x | J51: =TRIM(_xlfn.TEXTJOIN("_",FALSE(),H51,(SUBSTITUTE(SUBSTITUTE(D51," ",""), "_", "")))) -> Boddy_etal_2012_TableS1 | K51: =I51 & "_" & SUBSTITUTE(SUBSTITUTE(SUBSTITUTE(D51,CHAR(160),"")," ",""),"_","") -> 10.1111%2Fj.1420-9101.2012.02491.x_TableS1 | L51: {=IFERROR(INDEX(AUTO_Public_TSV_FileList!$A$1:$A$1000,MATCH(TRUE(),EXACT(K51,IFERROR(_xlfn.TEXTBEFORE(AUTO_Public_TSV_FileList!$A$1:$A$1000,".tsv"),"")),0)),"notfound")} -> 10.1111%2Fj.1420-9101.2012.02491.x_TableS1.tsv | N51: means | P51: FINISHED
A52: Bortoff, G. A., & Strick, P. L. (1993). Corticospinal terminations in two New-World primates: Further evidence that corticomotoneuronal connections provide part of the neural substrate for manual dexterity. The Journal of Neuroscience, 13(12), 5105–5118. https://doi.org/10.1523/JNEUROSCI.13-12-05105.1993 | D52: Table 1 | E52: =SUBSTITUTE(SUBSTITUTE(_xlfn.TEXTBEFORE(A52,","), "-", ""), " ", "") -> Bortoff | F52: {=_xlfn.LET( _xlpm.authors,_xlfn.TEXTBEFORE(A52," ("&G52&")"), _xlpm.hasAmp,ISNUMBER(SEARCH("&",_xlpm.authors)), _xlpm.hasEllipsis,ISNUMBER(SEARCH(_xlfn.UNICHAR(8230),_xlpm.authors)), _xlpm.commasBeforeAmp,IF( _xlpm.hasAmp, LEN(_xlfn.TEXTBEFORE(_xlpm.authors,"&"))-LEN(SUBSTITUTE(_xlfn.TEXTBEFORE(_xlpm.authors,"&"),",","")), 0 ), IF( _xlpm.hasEllipsis, "etal", IF( NOT(_xlpm.hasAmp), "", IF( _xlpm.commasBeforeAmp>2, "etal", SUBSTITUTE(TRIM(_xlfn.TEXTBEFORE(_xlfn.TEXTAFTER(_xlpm.authors,"& "),",")),"-","") ) ) ) )} -> Strick | G52: =_xlfn.TEXTBEFORE(_xlfn.TEXTAFTER(A52, "("), ")") -> 1993 | H52: =E52 & IF(F52<>"", "_" & F52, "_") & IF(G52<>"", "_" & G52, "_") & IF(B52<>"", "_" & B52, "") -> Bortoff_Strick_1993 | I52: =_xlfn.LET( _xlpm.doi,IF(C52<>"",C52,_xlfn.TEXTAFTER(A52,"https://doi.org/")), SUBSTITUTE( SUBSTITUTE( SUBSTITUTE( SUBSTITUTE( _xlpm.doi, "/","%2F"), ":","%3A"), "<","%3C"), ">","%3E") ) -> 10.1523%2FJNEUROSCI.13-12-05105.1993 | J52: =TRIM(_xlfn.TEXTJOIN("_",FALSE(),H52,(SUBSTITUTE(SUBSTITUTE(D52," ",""), "_", "")))) -> Bortoff_Strick_1993_Table1 | K52: =I52 & "_" & SUBSTITUTE(SUBSTITUTE(SUBSTITUTE(D52,CHAR(160),"")," ",""),"_","") -> 10.1523%2FJNEUROSCI.13-12-05105.1993_Table1 | L52: {=IFERROR(INDEX(AUTO_Public_TSV_FileList!$A$1:$A$1000,MATCH(TRUE(),EXACT(K52,IFERROR(_xlfn.TEXTBEFORE(AUTO_Public_TSV_FileList!$A$1:$A$1000,".tsv"),"")),0)),"notfound")} -> 10.1523%2FJNEUROSCI.13-12-05105.1993_Table1.tsv | M52: Curated Table 1. Species-specific corticospinal termination extent and CM-connection inference | N52: table | P52: FINISHED | R52: https://doi.org/10.1523/JNEUROSCI.13-12-05105.1993 | V52: spinal cord / M1 output | W52: two New-World primate species | X52: corticospinal termination extent and corticomotoneuronal inference | Y52: CST ventral-horn / lamina IX termination extent; CM-connection inference | AA52: WGA-HRP anterograde tract tracing from primary motor cortex | AB52: ordinal anatomical grade + qualitative inference | AC52: Bortoff/Strick | AE52: primary | AG52: Grade 0–2 is coded only from explicit species-level terminal-field evidence. CM_monosynaptic remains blank because light microscopy cannot establish direct monosynaptic presence or absence; likely/against is retained separately as inference. Data role = PRIMARY: the WGA-HRP result is Bortoff & Strick’s own, only the 0–2 grading is curatorial (see reference_tables/..._definitions.csv, Method:coding). Keyed on the article DOI — the earlier COMPILATION:Corticospinal_terminations override was removed 2026-08-15; a second CST paper gets its own folder and is pooled in __merging_behaviour, not appended to this table.
A53: Boyer, D. M., & Harrington, A. R. (2018). Scaling of bony canals for encephalic vessels in euarchontans: Implications for the role of the vertebral artery and brain metabolism. J Hum Evol, 114, 85-101. https://doi.org/10.1016/j.jhevol.2017.09.003 | D53: Table 1 | E53: =SUBSTITUTE(SUBSTITUTE(_xlfn.TEXTBEFORE(A53,","), "-", ""), " ", "") -> Boyer | F53: {=_xlfn.LET( _xlpm.authors,_xlfn.TEXTBEFORE(A53," ("&G53&")"), _xlpm.hasAmp,ISNUMBER(SEARCH("&",_xlpm.authors)), _xlpm.hasEllipsis,ISNUMBER(SEARCH(_xlfn.UNICHAR(8230),_xlpm.authors)), _xlpm.commasBeforeAmp,IF( _xlpm.hasAmp, LEN(_xlfn.TEXTBEFORE(_xlpm.authors,"&"))-LEN(SUBSTITUTE(_xlfn.TEXTBEFORE(_xlpm.authors,"&"),",","")), 0 ), IF( _xlpm.hasEllipsis, "etal", IF( NOT(_xlpm.hasAmp), "", IF( _xlpm.commasBeforeAmp>2, "etal", SUBSTITUTE(TRIM(_xlfn.TEXTBEFORE(_xlfn.TEXTAFTER(_xlpm.authors,"& "),",")),"-","") ) ) ) )} -> Harrington | G53: =_xlfn.TEXTBEFORE(_xlfn.TEXTAFTER(A53, "("), ")") -> 2018 | H53: =E53 & IF(F53<>"", "_" & F53, "_") & IF(G53<>"", "_" & G53, "_") & IF(B53<>"", "_" & B53, "") -> Boyer_Harrington_2018 | I53: =_xlfn.LET( _xlpm.doi,IF(C53<>"",C53,_xlfn.TEXTAFTER(A53,"https://doi.org/")), SUBSTITUTE( SUBSTITUTE( SUBSTITUTE( SUBSTITUTE( _xlpm.doi, "/","%2F"), ":","%3A"), "<","%3C"), ">","%3E") ) -> 10.1016%2Fj.jhevol.2017.09.003 | J53: =TRIM(_xlfn.TEXTJOIN("_",FALSE(),H53,(SUBSTITUTE(SUBSTITUTE(D53," ",""), "_", "")))) -> Boyer_Harrington_2018_Table1 | K53: =I53 & "_" & SUBSTITUTE(SUBSTITUTE(SUBSTITUTE(D53,CHAR(160),"")," ",""),"_","") -> 10.1016%2Fj.jhevol.2017.09.003_Table1 | L53: {=IFERROR(INDEX(AUTO_Public_TSV_FileList!$A$1:$A$1000,MATCH(TRUE(),EXACT(K53,IFERROR(_xlfn.TEXTBEFORE(AUTO_Public_TSV_FileList!$A$1:$A$1000,".tsv"),"")),0)),"notfound")} -> 10.1016%2Fj.jhevol.2017.09.003_Table1.tsv | M53: Table 1 Taxon list and species mean values. | P53: FINISHED
A54: Boyer, D. M., & Harrington, A. R. (2019). New estimates of blood flow rates in the vertebral artery of euarchontans and their implications for encephalic blood flow scaling: A response to Seymour and Snelling (2018). J Hum Evol, 128, 93-98. https://doi.org/10.1016/j.jhevol.2018.10.002 | D54: SOM Table S6 | E54: =SUBSTITUTE(SUBSTITUTE(_xlfn.TEXTBEFORE(A54,","), "-", ""), " ", "") -> Boyer | F54: {=_xlfn.LET( _xlpm.authors,_xlfn.TEXTBEFORE(A54," ("&G54&")"), _xlpm.hasAmp,ISNUMBER(SEARCH("&",_xlpm.authors)), _xlpm.hasEllipsis,ISNUMBER(SEARCH(_xlfn.UNICHAR(8230),_xlpm.authors)), _xlpm.commasBeforeAmp,IF( _xlpm.hasAmp, LEN(_xlfn.TEXTBEFORE(_xlpm.authors,"&"))-LEN(SUBSTITUTE(_xlfn.TEXTBEFORE(_xlpm.authors,"&"),",","")), 0 ), IF( _xlpm.hasEllipsis, "etal", IF( NOT(_xlpm.hasAmp), "", IF( _xlpm.commasBeforeAmp>2, "etal", SUBSTITUTE(TRIM(_xlfn.TEXTBEFORE(_xlfn.TEXTAFTER(_xlpm.authors,"& "),",")),"-","") ) ) ) )} -> Harrington | G54: =_xlfn.TEXTBEFORE(_xlfn.TEXTAFTER(A54, "("), ")") -> 2019 | H54: =E54 & IF(F54<>"", "_" & F54, "_") & IF(G54<>"", "_" & G54, "_") & IF(B54<>"", "_" & B54, "") -> Boyer_Harrington_2019 | I54: =_xlfn.LET( _xlpm.doi,IF(C54<>"",C54,_xlfn.TEXTAFTER(A54,"https://doi.org/")), SUBSTITUTE( SUBSTITUTE( SUBSTITUTE( SUBSTITUTE( _xlpm.doi, "/","%2F"), ":","%3A"), "<","%3C"), ">","%3E") ) -> 10.1016%2Fj.jhevol.2018.10.002 | J54: =TRIM(_xlfn.TEXTJOIN("_",FALSE(),H54,(SUBSTITUTE(SUBSTITUTE(D54," ",""), "_", "")))) -> Boyer_Harrington_2019_SOMTableS6 | K54: =I54 & "_" & SUBSTITUTE(SUBSTITUTE(SUBSTITUTE(D54,CHAR(160),"")," ",""),"_","") -> 10.1016%2Fj.jhevol.2018.10.002_SOMTableS6 | L54: {=IFERROR(INDEX(AUTO_Public_TSV_FileList!$A$1:$A$1000,MATCH(TRUE(),EXACT(K54,IFERROR(_xlfn.TEXTBEFORE(AUTO_Public_TSV_FileList!$A$1:$A$1000,".tsv"),"")),0)),"notfound")} -> 10.1016%2Fj.jhevol.2018.10.002_SOMTableS6.tsv | P54: FINISHED
A55: Brodmann, K. (1913). Neue Ergebnisse über die vergleichende histologische Lokalisation der Großhirnrinde mit besonderer Berücksichtigung des Stirnhirns. Verhandlungen der Anatomischen Gesellschaft, 41, 157-216. | C55: OCLC:8777719 | D55: Table 1 | E55: =SUBSTITUTE(SUBSTITUTE(_xlfn.TEXTBEFORE(A55,","), "-", ""), " ", "") -> Brodmann | F55: {=_xlfn.LET( _xlpm.authors,_xlfn.TEXTBEFORE(A55," ("&G55&")"), _xlpm.hasAmp,ISNUMBER(SEARCH("&",_xlpm.authors)), _xlpm.hasEllipsis,ISNUMBER(SEARCH(_xlfn.UNICHAR(8230),_xlpm.authors)), _xlpm.commasBeforeAmp,IF( _xlpm.hasAmp, LEN(_xlfn.TEXTBEFORE(_xlpm.authors,"&"))-LEN(SUBSTITUTE(_xlfn.TEXTBEFORE(_xlpm.authors,"&"),",","")), 0 ), IF( _xlpm.hasEllipsis, "etal", IF( NOT(_xlpm.hasAmp), "", IF( _xlpm.commasBeforeAmp>2, "etal", SUBSTITUTE(TRIM(_xlfn.TEXTBEFORE(_xlfn.TEXTAFTER(_xlpm.authors,"& "),",")),"-","") ) ) ) )} | G55: =_xlfn.TEXTBEFORE(_xlfn.TEXTAFTER(A55, "("), ")") -> 1913 | H55: =E55 & IF(F55<>"", "_" & F55, "_") & IF(G55<>"", "_" & G55, "_") & IF(B55<>"", "_" & B55, "") -> Brodmann__1913 | I55: =_xlfn.LET( _xlpm.doi,IF(C55<>"",C55,_xlfn.TEXTAFTER(A55,"https://doi.org/")), SUBSTITUTE( SUBSTITUTE( SUBSTITUTE( SUBSTITUTE( _xlpm.doi, "/","%2F"), ":","%3A"), "<","%3C"), ">","%3E") ) -> OCLC%3A8777719 | J55: =TRIM(_xlfn.TEXTJOIN("_",FALSE(),H55,(SUBSTITUTE(SUBSTITUTE(D55," ",""), "_", "")))) -> Brodmann__1913_Table1 | K55: =I55 & "_" & SUBSTITUTE(SUBSTITUTE(SUBSTITUTE(D55,CHAR(160),"")," ",""),"_","") -> OCLC%3A8777719_Table1 | L55: {=IFERROR(INDEX(AUTO_Public_TSV_FileList!$A$1:$A$1000,MATCH(TRUE(),EXACT(K55,IFERROR(_xlfn.TEXTBEFORE(AUTO_Public_TSV_FileList!$A$1:$A$1000,".tsv"),"")),0)),"notfound")} -> OCLC%3A8777719_Table1.tsv | M55: Tabelle 1. Gesamtrindenfläche, Furchenrinde und Hirngewicht bei verschiedenen Säugetieren | P55: FINISHED | W55: Mammalia (all orders) | X55: total cortical surface area; sulcal cortex; brain weight | AB55: surface area (mm2) + mass (g) | AE55: primary
A56: Brodmann, K. (1913). Neue Forschungsergebnisse der Großhirnrindenanatomie mit besonderer Berücksichtigung anthropologischer Fragen. Verhandlungen der Gesellschaft Deutscher Naturforscher und Ärzte, 85(1), 200-240 | C56: 10.0000/placeholder | D56: Tabelle 1 | E56: =SUBSTITUTE(SUBSTITUTE(_xlfn.TEXTBEFORE(A56,","), "-", ""), " ", "") -> Brodmann | F56: {=_xlfn.LET( _xlpm.authors,_xlfn.TEXTBEFORE(A56," ("&G56&")"), _xlpm.hasAmp,ISNUMBER(SEARCH("&",_xlpm.authors)), _xlpm.hasEllipsis,ISNUMBER(SEARCH(_xlfn.UNICHAR(8230),_xlpm.authors)), _xlpm.commasBeforeAmp,IF( _xlpm.hasAmp, LEN(_xlfn.TEXTBEFORE(_xlpm.authors,"&"))-LEN(SUBSTITUTE(_xlfn.TEXTBEFORE(_xlpm.authors,"&"),",","")), 0 ), IF( _xlpm.hasEllipsis, "etal", IF( NOT(_xlpm.hasAmp), "", IF( _xlpm.commasBeforeAmp>2, "etal", SUBSTITUTE(TRIM(_xlfn.TEXTBEFORE(_xlfn.TEXTAFTER(_xlpm.authors,"& "),",")),"-","") ) ) ) )} | G56: =_xlfn.TEXTBEFORE(_xlfn.TEXTAFTER(A56, "("), ")") -> 1913 | H56: =E56 & IF(F56<>"", "_" & F56, "_") & IF(G56<>"", "_" & G56, "_") & IF(B56<>"", "_" & B56, "") -> Brodmann__1913 | I56: =_xlfn.LET( _xlpm.doi,IF(C56<>"",C56,_xlfn.TEXTAFTER(A56,"https://doi.org/")), SUBSTITUTE( SUBSTITUTE( SUBSTITUTE( SUBSTITUTE( _xlpm.doi, "/","%2F"), ":","%3A"), "<","%3C"), ">","%3E") ) -> 10.0000%2Fplaceholder | J56: =TRIM(_xlfn.TEXTJOIN("_",FALSE(),H56,(SUBSTITUTE(SUBSTITUTE(D56," ",""), "_", "")))) -> Brodmann__1913_Tabelle1 | K56: =I56 & "_" & SUBSTITUTE(SUBSTITUTE(SUBSTITUTE(D56,CHAR(160),"")," ",""),"_","") -> 10.0000%2Fplaceholder_Tabelle1 | L56: {=IFERROR(INDEX(AUTO_Public_TSV_FileList!$A$1:$A$1000,MATCH(TRUE(),EXACT(K56,IFERROR(_xlfn.TEXTBEFORE(AUTO_Public_TSV_FileList!$A$1:$A$1000,".tsv"),"")),0)),"notfound")} -> notfound | O56: Documented non-build: this row's "Tabelle 1: Gesamtrindenfläche, Furchenrinde und Hirngewicht bei verschiedenen Säugetieren" is the identical table (same title, same data) already captured in Brodmann__1913_Table1, built from Brodmann_1913_Verhandlungen.pdf p.206 (the only Brodmann source PDF present in this folder besides the unrelated English 1909 localisation-doctrine book, Brodmann.pdf). This row's own citation (Verhandlungen der Gesellschaft Deutscher Naturforscher und Ärzte, 85(1), 200-240) matches this PDF's actual title page exactly, while Brodmann__1913_Table1's citation (Verhandlungen der Anatomischen Gesellschaft, 41, 157-216) is a different nominal source not present as a separate file here. Whether these are two genuinely separate 1913 Brodmann publications that happen to repeat the same table verbatim, or a mislabeled citation on one row, could not be resolved from the materials in this repo -- flagged for owner review -- but no distinct additional data exists to build here without duplicating the already-delivered 38-row dataset. Marked FINISHED rather than left blank, per the same documented-non-build precedent as Halley_Krubitzer_2019_Figure1. | P56: FINISHED | W56: Mammals (various) | X56: cortical surface area | AB56: cortical surface area | AE56: primary
A57: Burger, J. R., George, M. A., Leadbetter, C., & Shaikh, F. (2019). The allometry of brain size in mammals. J Mammal, 100(2), 276-283. https://doi.org/10.1093/jmammal/gyz043 | D57: Supplementary Data SD1 | E57: =SUBSTITUTE(SUBSTITUTE(_xlfn.TEXTBEFORE(A57,","), "-", ""), " ", "") -> Burger | F57: {=_xlfn.LET( _xlpm.authors,_xlfn.TEXTBEFORE(A57," ("&G57&")"), _xlpm.hasAmp,ISNUMBER(SEARCH("&",_xlpm.authors)), _xlpm.hasEllipsis,ISNUMBER(SEARCH(_xlfn.UNICHAR(8230),_xlpm.authors)), _xlpm.commasBeforeAmp,IF( _xlpm.hasAmp, LEN(_xlfn.TEXTBEFORE(_xlpm.authors,"&"))-LEN(SUBSTITUTE(_xlfn.TEXTBEFORE(_xlpm.authors,"&"),",","")), 0 ), IF( _xlpm.hasEllipsis, "etal", IF( NOT(_xlpm.hasAmp), "", IF( _xlpm.commasBeforeAmp>2, "etal", SUBSTITUTE(TRIM(_xlfn.TEXTBEFORE(_xlfn.TEXTAFTER(_xlpm.authors,"& "),",")),"-","") ) ) ) )} -> etal | G57: =_xlfn.TEXTBEFORE(_xlfn.TEXTAFTER(A57, "("), ")") -> 2019 | H57: =E57 & IF(F57<>"", "_" & F57, "_") & IF(G57<>"", "_" & G57, "_") & IF(B57<>"", "_" & B57, "") -> Burger_etal_2019 | I57: =_xlfn.LET( _xlpm.doi,IF(C57<>"",C57,_xlfn.TEXTAFTER(A57,"https://doi.org/")), SUBSTITUTE( SUBSTITUTE( SUBSTITUTE( SUBSTITUTE( _xlpm.doi, "/","%2F"), ":","%3A"), "<","%3C"), ">","%3E") ) -> 10.1093%2Fjmammal%2Fgyz043 | J57: =TRIM(_xlfn.TEXTJOIN("_",FALSE(),H57,(SUBSTITUTE(SUBSTITUTE(D57," ",""), "_", "")))) -> Burger_etal_2019_SupplementaryDataSD1 | K57: =I57 & "_" & SUBSTITUTE(SUBSTITUTE(SUBSTITUTE(D57,CHAR(160),"")," ",""),"_","") -> 10.1093%2Fjmammal%2Fgyz043_SupplementaryDataSD1 | L57: {=IFERROR(INDEX(AUTO_Public_TSV_FileList!$A$1:$A$1000,MATCH(TRUE(),EXACT(K57,IFERROR(_xlfn.TEXTBEFORE(AUTO_Public_TSV_FileList!$A$1:$A$1000,".tsv"),"")),0)),"notfound")} -> 10.1093%2Fjmammal%2Fgyz043_SupplementaryDataSD1.tsv | M57: Supplementary Data SD2 | N57: table | P57: FINISHED | Q57: gyz043_suppl_Supplement_Data.csv | W57: Mammals | X57: brain and body size | AB57: brain & body mass | AE57: secondary | AG57: derived relative brain size data are problematic
A58: Burish, M. J., Peebles, J. K., Baldwin, M. K., Tavares, L., Kaas, J. H., & Herculano-Houzel, S. (2010). Cellular scaling rules for primate spinal cords. Brain Behav Evol, 76(1), 45-59. https://doi.org/10.1159/000319019 | D58: Supplementary Table 1 | E58: =SUBSTITUTE(SUBSTITUTE(_xlfn.TEXTBEFORE(A58,","), "-", ""), " ", "") -> Burish | F58: {=_xlfn.LET( _xlpm.authors,_xlfn.TEXTBEFORE(A58," ("&G58&")"), _xlpm.hasAmp,ISNUMBER(SEARCH("&",_xlpm.authors)), _xlpm.hasEllipsis,ISNUMBER(SEARCH(_xlfn.UNICHAR(8230),_xlpm.authors)), _xlpm.commasBeforeAmp,IF( _xlpm.hasAmp, LEN(_xlfn.TEXTBEFORE(_xlpm.authors,"&"))-LEN(SUBSTITUTE(_xlfn.TEXTBEFORE(_xlpm.authors,"&"),",","")), 0 ), IF( _xlpm.hasEllipsis, "etal", IF( NOT(_xlpm.hasAmp), "", IF( _xlpm.commasBeforeAmp>2, "etal", SUBSTITUTE(TRIM(_xlfn.TEXTBEFORE(_xlfn.TEXTAFTER(_xlpm.authors,"& "),",")),"-","") ) ) ) )} -> etal | G58: =_xlfn.TEXTBEFORE(_xlfn.TEXTAFTER(A58, "("), ")") -> 2010 | H58: =E58 & IF(F58<>"", "_" & F58, "_") & IF(G58<>"", "_" & G58, "_") & IF(B58<>"", "_" & B58, "") -> Burish_etal_2010 | I58: =_xlfn.LET( _xlpm.doi,IF(C58<>"",C58,_xlfn.TEXTAFTER(A58,"https://doi.org/")), SUBSTITUTE( SUBSTITUTE( SUBSTITUTE( SUBSTITUTE( _xlpm.doi, "/","%2F"), ":","%3A"), "<","%3C"), ">","%3E") ) -> 10.1159%2F000319019 | J58: =TRIM(_xlfn.TEXTJOIN("_",FALSE(),H58,(SUBSTITUTE(SUBSTITUTE(D58," ",""), "_", "")))) -> Burish_etal_2010_SupplementaryTable1 | K58: =I58 & "_" & SUBSTITUTE(SUBSTITUTE(SUBSTITUTE(D58,CHAR(160),"")," ",""),"_","") -> 10.1159%2F000319019_SupplementaryTable1 | L58: {=IFERROR(INDEX(AUTO_Public_TSV_FileList!$A$1:$A$1000,MATCH(TRUE(),EXACT(K58,IFERROR(_xlfn.TEXTBEFORE(AUTO_Public_TSV_FileList!$A$1:$A$1000,".tsv"),"")),0)),"notfound")} -> 10.1159%2F000319019_SupplementaryTable1.tsv | M58: Supplementary Table 1: Dataset of individual spinal cord measurements | P58: FINISHED | W58: primates and tree shrew | X58: number spinal cord neurons | AA58: isotropic fractionator | AC58: HH | AD58: HH
A59: Burish, M. J., Peebles, J. K., Baldwin, M. K., Tavares, L., Kaas, J. H., & Herculano-Houzel, S. (2010). Cellular scaling rules for primate spinal cords. Brain Behav Evol, 76(1), 45-59. https://doi.org/10.1159/000319019 | D59: Table 1 | E59: =SUBSTITUTE(SUBSTITUTE(_xlfn.TEXTBEFORE(A59,","), "-", ""), " ", "") -> Burish | F59: {=_xlfn.LET( _xlpm.authors,_xlfn.TEXTBEFORE(A59," ("&G59&")"), _xlpm.hasAmp,ISNUMBER(SEARCH("&",_xlpm.authors)), _xlpm.hasEllipsis,ISNUMBER(SEARCH(_xlfn.UNICHAR(8230),_xlpm.authors)), _xlpm.commasBeforeAmp,IF( _xlpm.hasAmp, LEN(_xlfn.TEXTBEFORE(_xlpm.authors,"&"))-LEN(SUBSTITUTE(_xlfn.TEXTBEFORE(_xlpm.authors,"&"),",","")), 0 ), IF( _xlpm.hasEllipsis, "etal", IF( NOT(_xlpm.hasAmp), "", IF( _xlpm.commasBeforeAmp>2, "etal", SUBSTITUTE(TRIM(_xlfn.TEXTBEFORE(_xlfn.TEXTAFTER(_xlpm.authors,"& "),",")),"-","") ) ) ) )} -> etal | G59: =_xlfn.TEXTBEFORE(_xlfn.TEXTAFTER(A59, "("), ")") -> 2010 | H59: =E59 & IF(F59<>"", "_" & F59, "_") & IF(G59<>"", "_" & G59, "_") & IF(B59<>"", "_" & B59, "") -> Burish_etal_2010 | I59: =_xlfn.LET( _xlpm.doi,IF(C59<>"",C59,_xlfn.TEXTAFTER(A59,"https://doi.org/")), SUBSTITUTE( SUBSTITUTE( SUBSTITUTE( SUBSTITUTE( _xlpm.doi, "/","%2F"), ":","%3A"), "<","%3C"), ">","%3E") ) -> 10.1159%2F000319019 | J59: =TRIM(_xlfn.TEXTJOIN("_",FALSE(),H59,(SUBSTITUTE(SUBSTITUTE(D59," ",""), "_", "")))) -> Burish_etal_2010_Table1 | K59: =I59 & "_" & SUBSTITUTE(SUBSTITUTE(SUBSTITUTE(D59,CHAR(160),"")," ",""),"_","") -> 10.1159%2F000319019_Table1 | L59: {=IFERROR(INDEX(AUTO_Public_TSV_FileList!$A$1:$A$1000,MATCH(TRUE(),EXACT(K59,IFERROR(_xlfn.TEXTBEFORE(AUTO_Public_TSV_FileList!$A$1:$A$1000,".tsv"),"")),0)),"notfound")} -> 10.1159%2F000319019_Table1.tsv | M59: Table 1. Cellular composition of the spinal cord | N59: table | P59: FINISHED | R59: https://doi.org/10.1159/000319019 | S59: species-name-error: species-name typo corrected from paper text (in .R script). | W59: primates and tree shrew | X59: number spinal cord neurons | AA59: isotropic fractionator | AC59: HH | AD59: HH
A60: Bush, E. C., & Allman, J. M. (2003). The scaling of white matter to gray matter in cerebellum and neocortex. Brain Behav Evol, 61(1), 1-5. https://doi.org/10.1159/000068880 | D60: Table 1 | E60: =SUBSTITUTE(SUBSTITUTE(_xlfn.TEXTBEFORE(A60,","), "-", ""), " ", "") -> Bush | F60: {=_xlfn.LET( _xlpm.authors,_xlfn.TEXTBEFORE(A60," ("&G60&")"), _xlpm.hasAmp,ISNUMBER(SEARCH("&",_xlpm.authors)), _xlpm.hasEllipsis,ISNUMBER(SEARCH(_xlfn.UNICHAR(8230),_xlpm.authors)), _xlpm.commasBeforeAmp,IF( _xlpm.hasAmp, LEN(_xlfn.TEXTBEFORE(_xlpm.authors,"&"))-LEN(SUBSTITUTE(_xlfn.TEXTBEFORE(_xlpm.authors,"&"),",","")), 0 ), IF( _xlpm.hasEllipsis, "etal", IF( NOT(_xlpm.hasAmp), "", IF( _xlpm.commasBeforeAmp>2, "etal", SUBSTITUTE(TRIM(_xlfn.TEXTBEFORE(_xlfn.TEXTAFTER(_xlpm.authors,"& "),",")),"-","") ) ) ) )} -> Allman | G60: =_xlfn.TEXTBEFORE(_xlfn.TEXTAFTER(A60, "("), ")") -> 2003 | H60: =E60 & IF(F60<>"", "_" & F60, "_") & IF(G60<>"", "_" & G60, "_") & IF(B60<>"", "_" & B60, "") -> Bush_Allman_2003 | I60: =_xlfn.LET( _xlpm.doi,IF(C60<>"",C60,_xlfn.TEXTAFTER(A60,"https://doi.org/")), SUBSTITUTE( SUBSTITUTE( SUBSTITUTE( SUBSTITUTE( _xlpm.doi, "/","%2F"), ":","%3A"), "<","%3C"), ">","%3E") ) -> 10.1159%2F000068880 | J60: =TRIM(_xlfn.TEXTJOIN("_",FALSE(),H60,(SUBSTITUTE(SUBSTITUTE(D60," ",""), "_", "")))) -> Bush_Allman_2003_Table1 | K60: =I60 & "_" & SUBSTITUTE(SUBSTITUTE(SUBSTITUTE(D60,CHAR(160),"")," ",""),"_","") -> 10.1159%2F000068880_Table1 | L60: {=IFERROR(INDEX(AUTO_Public_TSV_FileList!$A$1:$A$1000,MATCH(TRUE(),EXACT(K60,IFERROR(_xlfn.TEXTBEFORE(AUTO_Public_TSV_FileList!$A$1:$A$1000,".tsv"),"")),0)),"notfound")} -> 10.1159%2F000068880_Table1.tsv | P60: FINISHED | AC60: Allman | AD60: AFIP
A61: Bush, E. C., & Allman, J. M. (2004). The scaling of frontal cortex in primates and carnivores. Proc Natl Acad Sci U S A, 101(11), 3962-3966. https://doi.org/10.1073/pnas.0305760101 | B61: a | D61: Table 2 | E61: =SUBSTITUTE(SUBSTITUTE(_xlfn.TEXTBEFORE(A61,","), "-", ""), " ", "") -> Bush | F61: {=_xlfn.LET( _xlpm.authors,_xlfn.TEXTBEFORE(A61," ("&G61&")"), _xlpm.hasAmp,ISNUMBER(SEARCH("&",_xlpm.authors)), _xlpm.hasEllipsis,ISNUMBER(SEARCH(_xlfn.UNICHAR(8230),_xlpm.authors)), _xlpm.commasBeforeAmp,IF( _xlpm.hasAmp, LEN(_xlfn.TEXTBEFORE(_xlpm.authors,"&"))-LEN(SUBSTITUTE(_xlfn.TEXTBEFORE(_xlpm.authors,"&"),",","")), 0 ), IF( _xlpm.hasEllipsis, "etal", IF( NOT(_xlpm.hasAmp), "", IF( _xlpm.commasBeforeAmp>2, "etal", SUBSTITUTE(TRIM(_xlfn.TEXTBEFORE(_xlfn.TEXTAFTER(_xlpm.authors,"& "),",")),"-","") ) ) ) )} -> Allman | G61: =_xlfn.TEXTBEFORE(_xlfn.TEXTAFTER(A61, "("), ")") -> 2004 | H61: =E61 & IF(F61<>"", "_" & F61, "_") & IF(G61<>"", "_" & G61, "_") & IF(B61<>"", "_" & B61, "") -> Bush_Allman_2004_a | I61: =_xlfn.LET( _xlpm.doi,IF(C61<>"",C61,_xlfn.TEXTAFTER(A61,"https://doi.org/")), SUBSTITUTE( SUBSTITUTE( SUBSTITUTE( SUBSTITUTE( _xlpm.doi, "/","%2F"), ":","%3A"), "<","%3C"), ">","%3E") ) -> 10.1073%2Fpnas.0305760101 | J61: =TRIM(_xlfn.TEXTJOIN("_",FALSE(),H61,(SUBSTITUTE(SUBSTITUTE(D61," ",""), "_", "")))) -> Bush_Allman_2004_a_Table2 | K61: =I61 & "_" & SUBSTITUTE(SUBSTITUTE(SUBSTITUTE(D61,CHAR(160),"")," ",""),"_","") -> 10.1073%2Fpnas.0305760101_Table2 | L61: {=IFERROR(INDEX(AUTO_Public_TSV_FileList!$A$1:$A$1000,MATCH(TRUE(),EXACT(K61,IFERROR(_xlfn.TEXTBEFORE(AUTO_Public_TSV_FileList!$A$1:$A$1000,".tsv"),"")),0)),"notfound")} -> 10.1073%2Fpnas.0305760101_Table2.tsv | M61: Table 1. White matter and gray matter volumes (cm3) for neocortex and cerebellum for 45 mammals | N61: table | P61: FINISHED | W61: Mammals (incl. primates) | X61: neocortex & cerebellum grey/white volumes | Z61: histological sections | AA61: volumetry | AC61: Allman | AD61: AFIP
A62: Bush, E. C., & Allman, J. M. (2004). Three-dimensional structure and evolution of primate primary visual cortex. Anat Rec (Hoboken), 281(1), 1088-1094. https://doi.org/10.1002/ar.a.20114 | B62: b | D62: TABLE 1 | E62: =SUBSTITUTE(SUBSTITUTE(_xlfn.TEXTBEFORE(A62,","), "-", ""), " ", "") -> Bush | F62: {=_xlfn.LET( _xlpm.authors,_xlfn.TEXTBEFORE(A62," ("&G62&")"), _xlpm.hasAmp,ISNUMBER(SEARCH("&",_xlpm.authors)), _xlpm.hasEllipsis,ISNUMBER(SEARCH(_xlfn.UNICHAR(8230),_xlpm.authors)), _xlpm.commasBeforeAmp,IF( _xlpm.hasAmp, LEN(_xlfn.TEXTBEFORE(_xlpm.authors,"&"))-LEN(SUBSTITUTE(_xlfn.TEXTBEFORE(_xlpm.authors,"&"),",","")), 0 ), IF( _xlpm.hasEllipsis, "etal", IF( NOT(_xlpm.hasAmp), "", IF( _xlpm.commasBeforeAmp>2, "etal", SUBSTITUTE(TRIM(_xlfn.TEXTBEFORE(_xlfn.TEXTAFTER(_xlpm.authors,"& "),",")),"-","") ) ) ) )} -> Allman | G62: =_xlfn.TEXTBEFORE(_xlfn.TEXTAFTER(A62, "("), ")") -> 2004 | H62: =E62 & IF(F62<>"", "_" & F62, "_") & IF(G62<>"", "_" & G62, "_") & IF(B62<>"", "_" & B62, "") -> Bush_Allman_2004_b | I62: =_xlfn.LET( _xlpm.doi,IF(C62<>"",C62,_xlfn.TEXTAFTER(A62,"https://doi.org/")), SUBSTITUTE( SUBSTITUTE( SUBSTITUTE( SUBSTITUTE( _xlpm.doi, "/","%2F"), ":","%3A"), "<","%3C"), ">","%3E") ) -> 10.1002%2Far.a.20114 | J62: =TRIM(_xlfn.TEXTJOIN("_",FALSE(),H62,(SUBSTITUTE(SUBSTITUTE(D62," ",""), "_", "")))) -> Bush_Allman_2004_b_TABLE1 | K62: =I62 & "_" & SUBSTITUTE(SUBSTITUTE(SUBSTITUTE(D62,CHAR(160),"")," ",""),"_","") -> 10.1002%2Far.a.20114_TABLE1 | L62: {=IFERROR(INDEX(AUTO_Public_TSV_FileList!$A$1:$A$1000,MATCH(TRUE(),EXACT(K62,IFERROR(_xlfn.TEXTBEFORE(AUTO_Public_TSV_FileList!$A$1:$A$1000,".tsv"),"")),0)),"notfound")} -> 10.1002%2Far.a.20114_TABLE1.tsv | M62: Table 1. Measurements in V1 and the rest of the brain for a sample of primates | N62: table | P62: FINISHED | W62: Primates | X62: V1 grey, LGN, V1 surface, neocortex GM/WM | Z62: histological sections | AA62: volumetry/stereology | AC62: Allman | AD62: AFIP
A63: Bush, E. C., & Allman, J. M. (2004). Three-dimensional structure and evolution of primate primary visual cortex. Anat Rec (Hoboken), 281(1), 1088-1094. https://doi.org/10.1002/ar.a.20114 | B63: b | D63: TABLE 2 | E63: =SUBSTITUTE(SUBSTITUTE(_xlfn.TEXTBEFORE(A63,","), "-", ""), " ", "") -> Bush | F63: {=_xlfn.LET( _xlpm.authors,_xlfn.TEXTBEFORE(A63," ("&G63&")"), _xlpm.hasAmp,ISNUMBER(SEARCH("&",_xlpm.authors)), _xlpm.hasEllipsis,ISNUMBER(SEARCH(_xlfn.UNICHAR(8230),_xlpm.authors)), _xlpm.commasBeforeAmp,IF( _xlpm.hasAmp, LEN(_xlfn.TEXTBEFORE(_xlpm.authors,"&"))-LEN(SUBSTITUTE(_xlfn.TEXTBEFORE(_xlpm.authors,"&"),",","")), 0 ), IF( _xlpm.hasEllipsis, "etal", IF( NOT(_xlpm.hasAmp), "", IF( _xlpm.commasBeforeAmp>2, "etal", SUBSTITUTE(TRIM(_xlfn.TEXTBEFORE(_xlfn.TEXTAFTER(_xlpm.authors,"& "),",")),"-","") ) ) ) )} -> Allman | G63: =_xlfn.TEXTBEFORE(_xlfn.TEXTAFTER(A63, "("), ")") -> 2004 | H63: =E63 & IF(F63<>"", "_" & F63, "_") & IF(G63<>"", "_" & G63, "_") & IF(B63<>"", "_" & B63, "") -> Bush_Allman_2004_b | I63: =_xlfn.LET( _xlpm.doi,IF(C63<>"",C63,_xlfn.TEXTAFTER(A63,"https://doi.org/")), SUBSTITUTE( SUBSTITUTE( SUBSTITUTE( SUBSTITUTE( _xlpm.doi, "/","%2F"), ":","%3A"), "<","%3C"), ">","%3E") ) -> 10.1002%2Far.a.20114 | J63: =TRIM(_xlfn.TEXTJOIN("_",FALSE(),H63,(SUBSTITUTE(SUBSTITUTE(D63," ",""), "_", "")))) -> Bush_Allman_2004_b_TABLE2 | K63: =I63 & "_" & SUBSTITUTE(SUBSTITUTE(SUBSTITUTE(D63,CHAR(160),"")," ",""),"_","") -> 10.1002%2Far.a.20114_TABLE2 | L63: {=IFERROR(INDEX(AUTO_Public_TSV_FileList!$A$1:$A$1000,MATCH(TRUE(),EXACT(K63,IFERROR(_xlfn.TEXTBEFORE(AUTO_Public_TSV_FileList!$A$1:$A$1000,".tsv"),"")),0)),"notfound")} -> 10.1002%2Far.a.20114_TABLE2.tsv | P63: FINISHED
A64: Bush, E. C., & Allman, J. M. (2004). Three-dimensional structure and evolution of primate primary visual cortex. Anat Rec (Hoboken), 281(1), 1088-1094. https://doi.org/10.1002/ar.a.20114 | B64: b | D64: TABLE 3 | E64: =SUBSTITUTE(SUBSTITUTE(_xlfn.TEXTBEFORE(A64,","), "-", ""), " ", "") -> Bush | F64: {=_xlfn.LET( _xlpm.authors,_xlfn.TEXTBEFORE(A64," ("&G64&")"), _xlpm.hasAmp,ISNUMBER(SEARCH("&",_xlpm.authors)), _xlpm.hasEllipsis,ISNUMBER(SEARCH(_xlfn.UNICHAR(8230),_xlpm.authors)), _xlpm.commasBeforeAmp,IF( _xlpm.hasAmp, LEN(_xlfn.TEXTBEFORE(_xlpm.authors,"&"))-LEN(SUBSTITUTE(_xlfn.TEXTBEFORE(_xlpm.authors,"&"),",","")), 0 ), IF( _xlpm.hasEllipsis, "etal", IF( NOT(_xlpm.hasAmp), "", IF( _xlpm.commasBeforeAmp>2, "etal", SUBSTITUTE(TRIM(_xlfn.TEXTBEFORE(_xlfn.TEXTAFTER(_xlpm.authors,"& "),",")),"-","") ) ) ) )} -> Allman | G64: =_xlfn.TEXTBEFORE(_xlfn.TEXTAFTER(A64, "("), ")") -> 2004 | H64: =E64 & IF(F64<>"", "_" & F64, "_") & IF(G64<>"", "_" & G64, "_") & IF(B64<>"", "_" & B64, "") -> Bush_Allman_2004_b | I64: =_xlfn.LET( _xlpm.doi,IF(C64<>"",C64,_xlfn.TEXTAFTER(A64,"https://doi.org/")), SUBSTITUTE( SUBSTITUTE( SUBSTITUTE( SUBSTITUTE( _xlpm.doi, "/","%2F"), ":","%3A"), "<","%3C"), ">","%3E") ) -> 10.1002%2Far.a.20114 | J64: =TRIM(_xlfn.TEXTJOIN("_",FALSE(),H64,(SUBSTITUTE(SUBSTITUTE(D64," ",""), "_", "")))) -> Bush_Allman_2004_b_TABLE3 | K64: =I64 & "_" & SUBSTITUTE(SUBSTITUTE(SUBSTITUTE(D64,CHAR(160),"")," ",""),"_","") -> 10.1002%2Far.a.20114_TABLE3 | L64: {=IFERROR(INDEX(AUTO_Public_TSV_FileList!$A$1:$A$1000,MATCH(TRUE(),EXACT(K64,IFERROR(_xlfn.TEXTBEFORE(AUTO_Public_TSV_FileList!$A$1:$A$1000,".tsv"),"")),0)),"notfound")} -> 10.1002%2Far.a.20114_TABLE3.tsv | P64: FINISHED
A65: Butti, C., Sherwood, C. C., Hakeem, A. Y., Allman, J. M., & Hof, P. R. (2009). Total number and volume of Von Economo neurons in the cerebral cortex of cetaceans. J Comp Neurol, 515(2), 243-259. https://doi.org/10.1002/cne.22055 | D65: Table 1 | E65: =SUBSTITUTE(SUBSTITUTE(_xlfn.TEXTBEFORE(A65,","), "-", ""), " ", "") -> Butti | F65: {=_xlfn.LET( _xlpm.authors,_xlfn.TEXTBEFORE(A65," ("&G65&")"), _xlpm.hasAmp,ISNUMBER(SEARCH("&",_xlpm.authors)), _xlpm.hasEllipsis,ISNUMBER(SEARCH(_xlfn.UNICHAR(8230),_xlpm.authors)), _xlpm.commasBeforeAmp,IF( _xlpm.hasAmp, LEN(_xlfn.TEXTBEFORE(_xlpm.authors,"&"))-LEN(SUBSTITUTE(_xlfn.TEXTBEFORE(_xlpm.authors,"&"),",","")), 0 ), IF( _xlpm.hasEllipsis, "etal", IF( NOT(_xlpm.hasAmp), "", IF( _xlpm.commasBeforeAmp>2, "etal", SUBSTITUTE(TRIM(_xlfn.TEXTBEFORE(_xlfn.TEXTAFTER(_xlpm.authors,"& "),",")),"-","") ) ) ) )} -> etal | G65: =_xlfn.TEXTBEFORE(_xlfn.TEXTAFTER(A65, "("), ")") -> 2009 | H65: =E65 & IF(F65<>"", "_" & F65, "_") & IF(G65<>"", "_" & G65, "_") & IF(B65<>"", "_" & B65, "") -> Butti_etal_2009 | I65: =_xlfn.LET( _xlpm.doi,IF(C65<>"",C65,_xlfn.TEXTAFTER(A65,"https://doi.org/")), SUBSTITUTE( SUBSTITUTE( SUBSTITUTE( SUBSTITUTE( _xlpm.doi, "/","%2F"), ":","%3A"), "<","%3C"), ">","%3E") ) -> 10.1002%2Fcne.22055 | J65: =TRIM(_xlfn.TEXTJOIN("_",FALSE(),H65,(SUBSTITUTE(SUBSTITUTE(D65," ",""), "_", "")))) -> Butti_etal_2009_Table1 | K65: =I65 & "_" & SUBSTITUTE(SUBSTITUTE(SUBSTITUTE(D65,CHAR(160),"")," ",""),"_","") -> 10.1002%2Fcne.22055_Table1 | L65: {=IFERROR(INDEX(AUTO_Public_TSV_FileList!$A$1:$A$1000,MATCH(TRUE(),EXACT(K65,IFERROR(_xlfn.TEXTBEFORE(AUTO_Public_TSV_FileList!$A$1:$A$1000,".tsv"),"")),0)),"notfound")} -> 10.1002%2Fcne.22055_Table1.tsv | P65: FINISHED
A66: Butti, C., Sherwood, C. C., Hakeem, A. Y., Allman, J. M., & Hof, P. R. (2009). Total number and volume of Von Economo neurons in the cerebral cortex of cetaceans. J Comp Neurol, 515(2), 243-259. https://doi.org/10.1002/cne.22055 | D66: Table 5 | E66: =SUBSTITUTE(SUBSTITUTE(_xlfn.TEXTBEFORE(A66,","), "-", ""), " ", "") -> Butti | F66: {=_xlfn.LET( _xlpm.authors,_xlfn.TEXTBEFORE(A66," ("&G66&")"), _xlpm.hasAmp,ISNUMBER(SEARCH("&",_xlpm.authors)), _xlpm.hasEllipsis,ISNUMBER(SEARCH(_xlfn.UNICHAR(8230),_xlpm.authors)), _xlpm.commasBeforeAmp,IF( _xlpm.hasAmp, LEN(_xlfn.TEXTBEFORE(_xlpm.authors,"&"))-LEN(SUBSTITUTE(_xlfn.TEXTBEFORE(_xlpm.authors,"&"),",","")), 0 ), IF( _xlpm.hasEllipsis, "etal", IF( NOT(_xlpm.hasAmp), "", IF( _xlpm.commasBeforeAmp>2, "etal", SUBSTITUTE(TRIM(_xlfn.TEXTBEFORE(_xlfn.TEXTAFTER(_xlpm.authors,"& "),",")),"-","") ) ) ) )} -> etal | G66: =_xlfn.TEXTBEFORE(_xlfn.TEXTAFTER(A66, "("), ")") -> 2009 | H66: =E66 & IF(F66<>"", "_" & F66, "_") & IF(G66<>"", "_" & G66, "_") & IF(B66<>"", "_" & B66, "") -> Butti_etal_2009 | I66: =_xlfn.LET( _xlpm.doi,IF(C66<>"",C66,_xlfn.TEXTAFTER(A66,"https://doi.org/")), SUBSTITUTE( SUBSTITUTE( SUBSTITUTE( SUBSTITUTE( _xlpm.doi, "/","%2F"), ":","%3A"), "<","%3C"), ">","%3E") ) -> 10.1002%2Fcne.22055 | J66: =TRIM(_xlfn.TEXTJOIN("_",FALSE(),H66,(SUBSTITUTE(SUBSTITUTE(D66," ",""), "_", "")))) -> Butti_etal_2009_Table5 | K66: =I66 & "_" & SUBSTITUTE(SUBSTITUTE(SUBSTITUTE(D66,CHAR(160),"")," ",""),"_","") -> 10.1002%2Fcne.22055_Table5 | L66: {=IFERROR(INDEX(AUTO_Public_TSV_FileList!$A$1:$A$1000,MATCH(TRUE(),EXACT(K66,IFERROR(_xlfn.TEXTBEFORE(AUTO_Public_TSV_FileList!$A$1:$A$1000,".tsv"),"")),0)),"notfound")} -> 10.1002%2Fcne.22055_Table5.tsv | P66: FINISHED
A67: Butti, C., Sherwood, C. C., Hakeem, A. Y., Allman, J. M., & Hof, P. R. (2009). Total number and volume of Von Economo neurons in the cerebral cortex of cetaceans. J Comp Neurol, 515(2), 243-259. https://doi.org/10.1002/cne.22055 | D67: Table 6 | E67: =SUBSTITUTE(SUBSTITUTE(_xlfn.TEXTBEFORE(A67,","), "-", ""), " ", "") -> Butti | F67: {=_xlfn.LET( _xlpm.authors,_xlfn.TEXTBEFORE(A67," ("&G67&")"), _xlpm.hasAmp,ISNUMBER(SEARCH("&",_xlpm.authors)), _xlpm.hasEllipsis,ISNUMBER(SEARCH(_xlfn.UNICHAR(8230),_xlpm.authors)), _xlpm.commasBeforeAmp,IF( _xlpm.hasAmp, LEN(_xlfn.TEXTBEFORE(_xlpm.authors,"&"))-LEN(SUBSTITUTE(_xlfn.TEXTBEFORE(_xlpm.authors,"&"),",","")), 0 ), IF( _xlpm.hasEllipsis, "etal", IF( NOT(_xlpm.hasAmp), "", IF( _xlpm.commasBeforeAmp>2, "etal", SUBSTITUTE(TRIM(_xlfn.TEXTBEFORE(_xlfn.TEXTAFTER(_xlpm.authors,"& "),",")),"-","") ) ) ) )} -> etal | G67: =_xlfn.TEXTBEFORE(_xlfn.TEXTAFTER(A67, "("), ")") -> 2009 | H67: =E67 & IF(F67<>"", "_" & F67, "_") & IF(G67<>"", "_" & G67, "_") & IF(B67<>"", "_" & B67, "") -> Butti_etal_2009 | I67: =_xlfn.LET( _xlpm.doi,IF(C67<>"",C67,_xlfn.TEXTAFTER(A67,"https://doi.org/")), SUBSTITUTE( SUBSTITUTE( SUBSTITUTE( SUBSTITUTE( _xlpm.doi, "/","%2F"), ":","%3A"), "<","%3C"), ">","%3E") ) -> 10.1002%2Fcne.22055 | J67: =TRIM(_xlfn.TEXTJOIN("_",FALSE(),H67,(SUBSTITUTE(SUBSTITUTE(D67," ",""), "_", "")))) -> Butti_etal_2009_Table6 | K67: =I67 & "_" & SUBSTITUTE(SUBSTITUTE(SUBSTITUTE(D67,CHAR(160),"")," ",""),"_","") -> 10.1002%2Fcne.22055_Table6 | L67: {=IFERROR(INDEX(AUTO_Public_TSV_FileList!$A$1:$A$1000,MATCH(TRUE(),EXACT(K67,IFERROR(_xlfn.TEXTBEFORE(AUTO_Public_TSV_FileList!$A$1:$A$1000,".tsv"),"")),0)),"notfound")} -> 10.1002%2Fcne.22055_Table6.tsv | P67: FINISHED
A68: Campos, G. B., & Welker, W. I. (1976). Comparisons between brains of a large and a small hystricomorph rodent: capybara, Hydrochoerus and guinea pig, Cavia; neocortical projection regions and measurements of brain subdivisions. Brain Behav Evol, 13(4), 243-266. https://doi.org/10.1159/000123814 | D68: Table 1 | E68: =SUBSTITUTE(SUBSTITUTE(_xlfn.TEXTBEFORE(A68,","), "-", ""), " ", "") -> Campos | F68: {=_xlfn.LET( _xlpm.authors,_xlfn.TEXTBEFORE(A68," ("&G68&")"), _xlpm.hasAmp,ISNUMBER(SEARCH("&",_xlpm.authors)), _xlpm.hasEllipsis,ISNUMBER(SEARCH(_xlfn.UNICHAR(8230),_xlpm.authors)), _xlpm.commasBeforeAmp,IF( _xlpm.hasAmp, LEN(_xlfn.TEXTBEFORE(_xlpm.authors,"&"))-LEN(SUBSTITUTE(_xlfn.TEXTBEFORE(_xlpm.authors,"&"),",","")), 0 ), IF( _xlpm.hasEllipsis, "etal", IF( NOT(_xlpm.hasAmp), "", IF( _xlpm.commasBeforeAmp>2, "etal", SUBSTITUTE(TRIM(_xlfn.TEXTBEFORE(_xlfn.TEXTAFTER(_xlpm.authors,"& "),",")),"-","") ) ) ) )} -> Welker | G68: =_xlfn.TEXTBEFORE(_xlfn.TEXTAFTER(A68, "("), ")") -> 1976 | H68: =E68 & IF(F68<>"", "_" & F68, "_") & IF(G68<>"", "_" & G68, "_") & IF(B68<>"", "_" & B68, "") -> Campos_Welker_1976 | I68: =_xlfn.LET(_xlpm.doi,IF(C68<>"",C68,_xlfn.TEXTAFTER(A68,"https://doi.org/")),SUBSTITUTE(SUBSTITUTE(SUBSTITUTE(SUBSTITUTE(_xlpm.doi,"/","%2F"),":","%3A"),"<","%3C"),">","%3E")) -> 10.1159%2F000123814 | J68: =TRIM(_xlfn.TEXTJOIN("_",FALSE(),H68,(SUBSTITUTE(SUBSTITUTE(D68," ",""), "_", "")))) -> Campos_Welker_1976_Table1 | K68: =I68 & "_" & SUBSTITUTE(SUBSTITUTE(SUBSTITUTE(D68,CHAR(160),"")," ",""),"_","") -> 10.1159%2F000123814_Table1 | L68: {=IFERROR(INDEX(AUTO_Public_TSV_FileList!$A$1:$A$1000,MATCH(TRUE(),EXACT(K68,IFERROR(_xlfn.TEXTBEFORE(AUTO_Public_TSV_FileList!$A$1:$A$1000,".tsv"),"")),0)),"notfound")} -> 10.1159%2F000123814_Table1.tsv | M68: Table 1. Quantitative comparisons of brains of capybara and guinea pig | N68: table | P68: FINISHED | R68: https://doi.org/10.1159/000123814 | T68: mixed-datatype table; n=1 per species; derived multiplication-factor rows | V68: brain subdivisions / cortex / cell counts | W68: Rodents | X68: regional volumes; cortical morphometry; cell density and number | Y68: prosencephalon; neocortex; white matter; thalamus; caudate; globus pallidus; basal forebrain; hippocampus; hypothalamus; cortical surface/fissures/thickness; cell density and number | AA68: histological volumetry; cortical surface measurement; cell-density sampling and counts | AB68: volume + area + thickness + cell density/count | AC68: Welker/Wisconsin | AD68: University of Wisconsin Comparative Mammalian Brain Collection | AE68: primary
A69: Capellini, I., Barton, R. A., McNamara, P., Preston, B. T., & Nunn, C. L. (2008). Phylogenetic analysis of the ecology and evolution of mammalian sleep. Evolution, 62(7), 1764-1776. https://doi.org/10.1111/j.1558-5646.2008.00392.x | D69: sleep-data_Female | E69: =SUBSTITUTE(SUBSTITUTE(_xlfn.TEXTBEFORE(A69,","), "-", ""), " ", "") -> Capellini | F69: {=_xlfn.LET( _xlpm.authors,_xlfn.TEXTBEFORE(A69," ("&G69&")"), _xlpm.hasAmp,ISNUMBER(SEARCH("&",_xlpm.authors)), _xlpm.hasEllipsis,ISNUMBER(SEARCH(_xlfn.UNICHAR(8230),_xlpm.authors)), _xlpm.commasBeforeAmp,IF( _xlpm.hasAmp, LEN(_xlfn.TEXTBEFORE(_xlpm.authors,"&"))-LEN(SUBSTITUTE(_xlfn.TEXTBEFORE(_xlpm.authors,"&"),",","")), 0 ), IF( _xlpm.hasEllipsis, "etal", IF( NOT(_xlpm.hasAmp), "", IF( _xlpm.commasBeforeAmp>2, "etal", SUBSTITUTE(TRIM(_xlfn.TEXTBEFORE(_xlfn.TEXTAFTER(_xlpm.authors,"& "),",")),"-","") ) ) ) )} -> etal | G69: =_xlfn.TEXTBEFORE(_xlfn.TEXTAFTER(A69, "("), ")") -> 2008 | H69: =E69 & IF(F69<>"", "_" & F69, "_") & IF(G69<>"", "_" & G69, "_") & IF(B69<>"", "_" & B69, "") -> Capellini_etal_2008 | I69: =_xlfn.LET( _xlpm.doi,IF(C69<>"",C69,_xlfn.TEXTAFTER(A69,"https://doi.org/")), SUBSTITUTE( SUBSTITUTE( SUBSTITUTE( SUBSTITUTE( _xlpm.doi, "/","%2F"), ":","%3A"), "<","%3C"), ">","%3E") ) -> 10.1111%2Fj.1558-5646.2008.00392.x | J69: =TRIM(_xlfn.TEXTJOIN("_",FALSE(),H69,(SUBSTITUTE(SUBSTITUTE(D69," ",""), "_", "")))) -> Capellini_etal_2008_sleep-dataFemale | K69: =I69 & "_" & SUBSTITUTE(SUBSTITUTE(SUBSTITUTE(D69,CHAR(160),"")," ",""),"_","") -> 10.1111%2Fj.1558-5646.2008.00392.x_sleep-dataFemale | L69: {=IFERROR(INDEX(AUTO_Public_TSV_FileList!$A$1:$A$1000,MATCH(TRUE(),EXACT(K69,IFERROR(_xlfn.TEXTBEFORE(AUTO_Public_TSV_FileList!$A$1:$A$1000,".tsv"),"")),0)),"notfound")} -> 10.1111%2Fj.1558-5646.2008.00392.x_sleep-dataFemale.tsv | N69: table | O69: all data downloaded from database cited in paper with search term Sex = Female | P69: FINISHED | Q69: none - digital-native (sleep-data_Female.csv IS the frozen source) | W69: Mammals | X69: sleep (total sleep time, REM, NREM) | AB69: sleep (h/day, REM %) | AC69: Capellini | AE69: secondary | AG69: one row per primary study x species x sex class, not per species - aggregate at the merge. Citation-dependent with HerculanoHouzel__2015_Table1 for daily sleep (both descend from Zepelin / Campbell & Tobler) - resolve, never average.
A70: Capellini, I., Barton, R. A., McNamara, P., Preston, B. T., & Nunn, C. L. (2008). Phylogenetic analysis of the ecology and evolution of mammalian sleep. Evolution, 62(7), 1764-1776. https://doi.org/10.1111/j.1558-5646.2008.00392.x | D70: sleep-data_Male | E70: =SUBSTITUTE(SUBSTITUTE(_xlfn.TEXTBEFORE(A70,","), "-", ""), " ", "") -> Capellini | F70: {=_xlfn.LET( _xlpm.authors,_xlfn.TEXTBEFORE(A70," ("&G70&")"), _xlpm.hasAmp,ISNUMBER(SEARCH("&",_xlpm.authors)), _xlpm.hasEllipsis,ISNUMBER(SEARCH(_xlfn.UNICHAR(8230),_xlpm.authors)), _xlpm.commasBeforeAmp,IF( _xlpm.hasAmp, LEN(_xlfn.TEXTBEFORE(_xlpm.authors,"&"))-LEN(SUBSTITUTE(_xlfn.TEXTBEFORE(_xlpm.authors,"&"),",","")), 0 ), IF( _xlpm.hasEllipsis, "etal", IF( NOT(_xlpm.hasAmp), "", IF( _xlpm.commasBeforeAmp>2, "etal", SUBSTITUTE(TRIM(_xlfn.TEXTBEFORE(_xlfn.TEXTAFTER(_xlpm.authors,"& "),",")),"-","") ) ) ) )} -> etal | G70: =_xlfn.TEXTBEFORE(_xlfn.TEXTAFTER(A70, "("), ")") -> 2008 | H70: =E70 & IF(F70<>"", "_" & F70, "_") & IF(G70<>"", "_" & G70, "_") & IF(B70<>"", "_" & B70, "") -> Capellini_etal_2008 | I70: =_xlfn.LET( _xlpm.doi,IF(C70<>"",C70,_xlfn.TEXTAFTER(A70,"https://doi.org/")), SUBSTITUTE( SUBSTITUTE( SUBSTITUTE( SUBSTITUTE( _xlpm.doi, "/","%2F"), ":","%3A"), "<","%3C"), ">","%3E") ) -> 10.1111%2Fj.1558-5646.2008.00392.x | J70: =TRIM(_xlfn.TEXTJOIN("_",FALSE(),H70,(SUBSTITUTE(SUBSTITUTE(D70," ",""), "_", "")))) -> Capellini_etal_2008_sleep-dataMale | K70: =I70 & "_" & SUBSTITUTE(SUBSTITUTE(SUBSTITUTE(D70,CHAR(160),"")," ",""),"_","") -> 10.1111%2Fj.1558-5646.2008.00392.x_sleep-dataMale | L70: {=IFERROR(INDEX(AUTO_Public_TSV_FileList!$A$1:$A$1000,MATCH(TRUE(),EXACT(K70,IFERROR(_xlfn.TEXTBEFORE(AUTO_Public_TSV_FileList!$A$1:$A$1000,".tsv"),"")),0)),"notfound")} -> 10.1111%2Fj.1558-5646.2008.00392.x_sleep-dataMale.tsv | N70: table | O70: all data downloaded from database cited in paper with search term Sex = Male | P70: FINISHED | Q70: none - digital-native (sleep-data_Male.csv IS the frozen source) | W70: Mammals | X70: sleep (total sleep time, REM, NREM) | AB70: sleep (h/day, REM %) | AC70: Capellini | AE70: secondary | AG70: one row per primary study x species x sex class, not per species - aggregate at the merge. Citation-dependent with HerculanoHouzel__2015_Table1 for daily sleep (both descend from Zepelin / Campbell & Tobler) - resolve, never average.
A71: Capellini, I., Barton, R. A., McNamara, P., Preston, B. T., & Nunn, C. L. (2008). Phylogenetic analysis of the ecology and evolution of mammalian sleep. Evolution, 62(7), 1764-1776. https://doi.org/10.1111/j.1558-5646.2008.00392.x | D71: sleep-data_Mixed | E71: =SUBSTITUTE(SUBSTITUTE(_xlfn.TEXTBEFORE(A71,","), "-", ""), " ", "") -> Capellini | F71: {=_xlfn.LET( _xlpm.authors,_xlfn.TEXTBEFORE(A71," ("&G71&")"), _xlpm.hasAmp,ISNUMBER(SEARCH("&",_xlpm.authors)), _xlpm.hasEllipsis,ISNUMBER(SEARCH(_xlfn.UNICHAR(8230),_xlpm.authors)), _xlpm.commasBeforeAmp,IF( _xlpm.hasAmp, LEN(_xlfn.TEXTBEFORE(_xlpm.authors,"&"))-LEN(SUBSTITUTE(_xlfn.TEXTBEFORE(_xlpm.authors,"&"),",","")), 0 ), IF( _xlpm.hasEllipsis, "etal", IF( NOT(_xlpm.hasAmp), "", IF( _xlpm.commasBeforeAmp>2, "etal", SUBSTITUTE(TRIM(_xlfn.TEXTBEFORE(_xlfn.TEXTAFTER(_xlpm.authors,"& "),",")),"-","") ) ) ) )} -> etal | G71: =_xlfn.TEXTBEFORE(_xlfn.TEXTAFTER(A71, "("), ")") -> 2008 | H71: =E71 & IF(F71<>"", "_" & F71, "_") & IF(G71<>"", "_" & G71, "_") & IF(B71<>"", "_" & B71, "") -> Capellini_etal_2008 | I71: =_xlfn.LET( _xlpm.doi,IF(C71<>"",C71,_xlfn.TEXTAFTER(A71,"https://doi.org/")), SUBSTITUTE( SUBSTITUTE( SUBSTITUTE( SUBSTITUTE( _xlpm.doi, "/","%2F"), ":","%3A"), "<","%3C"), ">","%3E") ) -> 10.1111%2Fj.1558-5646.2008.00392.x | J71: =TRIM(_xlfn.TEXTJOIN("_",FALSE(),H71,(SUBSTITUTE(SUBSTITUTE(D71," ",""), "_", "")))) -> Capellini_etal_2008_sleep-dataMixed | K71: =I71 & "_" & SUBSTITUTE(SUBSTITUTE(SUBSTITUTE(D71,CHAR(160),"")," ",""),"_","") -> 10.1111%2Fj.1558-5646.2008.00392.x_sleep-dataMixed | L71: {=IFERROR(INDEX(AUTO_Public_TSV_FileList!$A$1:$A$1000,MATCH(TRUE(),EXACT(K71,IFERROR(_xlfn.TEXTBEFORE(AUTO_Public_TSV_FileList!$A$1:$A$1000,".tsv"),"")),0)),"notfound")} -> 10.1111%2Fj.1558-5646.2008.00392.x_sleep-dataMixed.tsv | N71: table | O71: all data downloaded from database cited in paper with search term Sex = Mixed | P71: FINISHED | Q71: none - digital-native (sleep-data_Mixed.csv IS the frozen source) | W71: Mammals | X71: sleep (total sleep time, REM, NREM) | AB71: sleep (h/day, REM %) | AC71: Capellini | AE71: secondary | AG71: one row per primary study x species x sex class, not per species - aggregate at the merge. Citation-dependent with HerculanoHouzel__2015_Table1 for daily sleep (both descend from Zepelin / Campbell & Tobler) - resolve, never average.
A72: Caspar, K. R., Pallasdies, F., Mader, L., Sartorelli, H., & Begall, S. (2022). The evolution and biological correlates of hand preferences in anthropoid primates. Elife, 11, e77875. https://doi.org/10.7554/eLife.77875 | D72: Supplementary file 3 | E72: =SUBSTITUTE(SUBSTITUTE(_xlfn.TEXTBEFORE(A72,","), "-", ""), " ", "") -> Caspar | F72: {=_xlfn.LET( _xlpm.authors,_xlfn.TEXTBEFORE(A72," ("&G72&")"), _xlpm.hasAmp,ISNUMBER(SEARCH("&",_xlpm.authors)), _xlpm.hasEllipsis,ISNUMBER(SEARCH(_xlfn.UNICHAR(8230),_xlpm.authors)), _xlpm.commasBeforeAmp,IF( _xlpm.hasAmp, LEN(_xlfn.TEXTBEFORE(_xlpm.authors,"&"))-LEN(SUBSTITUTE(_xlfn.TEXTBEFORE(_xlpm.authors,"&"),",","")), 0 ), IF( _xlpm.hasEllipsis, "etal", IF( NOT(_xlpm.hasAmp), "", IF( _xlpm.commasBeforeAmp>2, "etal", SUBSTITUTE(TRIM(_xlfn.TEXTBEFORE(_xlfn.TEXTAFTER(_xlpm.authors,"& "),",")),"-","") ) ) ) )} -> etal | G72: =_xlfn.TEXTBEFORE(_xlfn.TEXTAFTER(A72, "("), ")") -> 2022 | H72: =E72 & IF(F72<>"", "_" & F72, "_") & IF(G72<>"", "_" & G72, "_") & IF(B72<>"", "_" & B72, "") -> Caspar_etal_2022 | I72: =_xlfn.LET( _xlpm.doi,IF(C72<>"",C72,_xlfn.TEXTAFTER(A72,"https://doi.org/")), SUBSTITUTE( SUBSTITUTE( SUBSTITUTE( SUBSTITUTE( _xlpm.doi, "/","%2F"), ":","%3A"), "<","%3C"), ">","%3E") ) -> 10.7554%2FeLife.77875 | J72: =TRIM(_xlfn.TEXTJOIN("_",FALSE(),H72,(SUBSTITUTE(SUBSTITUTE(D72," ",""), "_", "")))) -> Caspar_etal_2022_Supplementaryfile3 | K72: =I72 & "_" & SUBSTITUTE(SUBSTITUTE(SUBSTITUTE(D72,CHAR(160),"")," ",""),"_","") -> 10.7554%2FeLife.77875_Supplementaryfile3 | L72: {=IFERROR(INDEX(AUTO_Public_TSV_FileList!$A$1:$A$1000,MATCH(TRUE(),EXACT(K72,IFERROR(_xlfn.TEXTBEFORE(AUTO_Public_TSV_FileList!$A$1:$A$1000,".tsv"),"")),0)),"notfound")} -> 10.7554%2FeLife.77875_Supplementaryfile3.tsv | M72: part 2: ecological table | N72: table | P72: FINISHED | Q72: elife-77875-supp3-v1.xlsx | R72: https://cdn.elifesciences.org/articles/77875/elife-77875-supp3-v1.xlsx | W72: Primates | X72: Habitual Tool Use, Ecology, Female brain size | AB72: behavioural (handedness, tool use, ecology) | AE72: secondary
A73: Caspar, K. R., Pallasdies, F., Mader, L., Sartorelli, H., & Begall, S. (2022). The evolution and biological correlates of hand preferences in anthropoid primates. Elife, 11, e77875. https://doi.org/10.7554/eLife.77875 | D73: Table 1 | E73: =SUBSTITUTE(SUBSTITUTE(_xlfn.TEXTBEFORE(A73,","), "-", ""), " ", "") -> Caspar | F73: {=_xlfn.LET( _xlpm.authors,_xlfn.TEXTBEFORE(A73," ("&G73&")"), _xlpm.hasAmp,ISNUMBER(SEARCH("&",_xlpm.authors)), _xlpm.hasEllipsis,ISNUMBER(SEARCH(_xlfn.UNICHAR(8230),_xlpm.authors)), _xlpm.commasBeforeAmp,IF( _xlpm.hasAmp, LEN(_xlfn.TEXTBEFORE(_xlpm.authors,"&"))-LEN(SUBSTITUTE(_xlfn.TEXTBEFORE(_xlpm.authors,"&"),",","")), 0 ), IF( _xlpm.hasEllipsis, "etal", IF( NOT(_xlpm.hasAmp), "", IF( _xlpm.commasBeforeAmp>2, "etal", SUBSTITUTE(TRIM(_xlfn.TEXTBEFORE(_xlfn.TEXTAFTER(_xlpm.authors,"& "),",")),"-","") ) ) ) )} -> etal | G73: =_xlfn.TEXTBEFORE(_xlfn.TEXTAFTER(A73, "("), ")") -> 2022 | H73: =E73 & IF(F73<>"", "_" & F73, "_") & IF(G73<>"", "_" & G73, "_") & IF(B73<>"", "_" & B73, "") -> Caspar_etal_2022 | I73: =_xlfn.LET( _xlpm.doi,IF(C73<>"",C73,_xlfn.TEXTAFTER(A73,"https://doi.org/")), SUBSTITUTE( SUBSTITUTE( SUBSTITUTE( SUBSTITUTE( _xlpm.doi, "/","%2F"), ":","%3A"), "<","%3C"), ">","%3E") ) -> 10.7554%2FeLife.77875 | J73: =TRIM(_xlfn.TEXTJOIN("_",FALSE(),H73,(SUBSTITUTE(SUBSTITUTE(D73," ",""), "_", "")))) -> Caspar_etal_2022_Table1 | K73: =I73 & "_" & SUBSTITUTE(SUBSTITUTE(SUBSTITUTE(D73,CHAR(160),"")," ",""),"_","") -> 10.7554%2FeLife.77875_Table1 | L73: {=IFERROR(INDEX(AUTO_Public_TSV_FileList!$A$1:$A$1000,MATCH(TRUE(),EXACT(K73,IFERROR(_xlfn.TEXTBEFORE(AUTO_Public_TSV_FileList!$A$1:$A$1000,".tsv"),"")),0)),"notfound")} -> 10.7554%2FeLife.77875_Table1.tsv | M73: part 1: handedness summary table | N73: table | P73: FINISHED | R73: https://elifesciences.org/download/aHR0cHM6Ly9jZG4uZWxpZmVzY2llbmNlcy5vcmcvYXJ0aWNsZXMvNzc4NzUvZWxpZmUtNzc4NzUtdjEucGRmP2Nhbm9uaWNhbFVyaT1odHRwczovL2VsaWZlc2NpZW5jZXMub3JnL2FydGljbGVzLzc3ODc1/elife-77875-v1.pdf?_hash=NStjcL9fTlmy3AQDwSiM0YgMVB3UYjO8nDg0UbwN5gM%3D | W73: Primates | X73: Handedness derived data | AB73: behavioural (handedness) | AE73: secondary | AG73: perhaps useful to get raw data as well?
A74: Caves, E. M., Brandley, N. C., & Johnsen, S. (2018). Visual Acuity and the Evolution of Signals. Trends Ecol Evol, 33(5), 358-372. https://doi.org/10.1016/j.tree.2018.03.001 | D74: Table S1 | E74: =SUBSTITUTE(SUBSTITUTE(_xlfn.TEXTBEFORE(A74,","), "-", ""), " ", "") -> Caves | F74: {=_xlfn.LET( _xlpm.authors,_xlfn.TEXTBEFORE(A74," ("&G74&")"), _xlpm.hasAmp,ISNUMBER(SEARCH("&",_xlpm.authors)), _xlpm.hasEllipsis,ISNUMBER(SEARCH(_xlfn.UNICHAR(8230),_xlpm.authors)), _xlpm.commasBeforeAmp,IF( _xlpm.hasAmp, LEN(_xlfn.TEXTBEFORE(_xlpm.authors,"&"))-LEN(SUBSTITUTE(_xlfn.TEXTBEFORE(_xlpm.authors,"&"),",","")), 0 ), IF( _xlpm.hasEllipsis, "etal", IF( NOT(_xlpm.hasAmp), "", IF( _xlpm.commasBeforeAmp>2, "etal", SUBSTITUTE(TRIM(_xlfn.TEXTBEFORE(_xlfn.TEXTAFTER(_xlpm.authors,"& "),",")),"-","") ) ) ) )} -> etal | G74: =_xlfn.TEXTBEFORE(_xlfn.TEXTAFTER(A74, "("), ")") -> 2018 | H74: =E74 & IF(F74<>"", "_" & F74, "_") & IF(G74<>"", "_" & G74, "_") & IF(B74<>"", "_" & B74, "") -> Caves_etal_2018 | I74: =_xlfn.LET( _xlpm.doi,IF(C74<>"",C74,_xlfn.TEXTAFTER(A74,"https://doi.org/")), SUBSTITUTE( SUBSTITUTE( SUBSTITUTE( SUBSTITUTE( _xlpm.doi, "/","%2F"), ":","%3A"), "<","%3C"), ">","%3E") ) -> 10.1016%2Fj.tree.2018.03.001 | J74: =TRIM(_xlfn.TEXTJOIN("_",FALSE(),H74,(SUBSTITUTE(SUBSTITUTE(D74," ",""), "_", "")))) -> Caves_etal_2018_TableS1 | K74: =I74 & "_" & SUBSTITUTE(SUBSTITUTE(SUBSTITUTE(D74,CHAR(160),"")," ",""),"_","") -> 10.1016%2Fj.tree.2018.03.001_TableS1 | L74: {=IFERROR(INDEX(AUTO_Public_TSV_FileList!$A$1:$A$1000,MATCH(TRUE(),EXACT(K74,IFERROR(_xlfn.TEXTBEFORE(AUTO_Public_TSV_FileList!$A$1:$A$1000,".tsv"),"")),0)),"notfound")} -> 10.1016%2Fj.tree.2018.03.001_TableS1.tsv | P74: FINISHED
A75: Changizi, M. A. (2001). Principles underlying mammalian neocortical scaling. Biol Cybern, 84(3), 207-215. https://doi.org/10.1007/s004220000205 | D75: Figure 3 | E75: =SUBSTITUTE(SUBSTITUTE(_xlfn.TEXTBEFORE(A75,","), "-", ""), " ", "") -> Changizi | F75: {=_xlfn.LET( _xlpm.authors,_xlfn.TEXTBEFORE(A75," ("&G75&")"), _xlpm.hasAmp,ISNUMBER(SEARCH("&",_xlpm.authors)), _xlpm.hasEllipsis,ISNUMBER(SEARCH(_xlfn.UNICHAR(8230),_xlpm.authors)), _xlpm.commasBeforeAmp,IF( _xlpm.hasAmp, LEN(_xlfn.TEXTBEFORE(_xlpm.authors,"&"))-LEN(SUBSTITUTE(_xlfn.TEXTBEFORE(_xlpm.authors,"&"),",","")), 0 ), IF( _xlpm.hasEllipsis, "etal", IF( NOT(_xlpm.hasAmp), "", IF( _xlpm.commasBeforeAmp>2, "etal", SUBSTITUTE(TRIM(_xlfn.TEXTBEFORE(_xlfn.TEXTAFTER(_xlpm.authors,"& "),",")),"-","") ) ) ) )} | G75: =_xlfn.TEXTBEFORE(_xlfn.TEXTAFTER(A75, "("), ")") -> 2001 | H75: =E75 & IF(F75<>"", "_" & F75, "_") & IF(G75<>"", "_" & G75, "_") & IF(B75<>"", "_" & B75, "") -> Changizi__2001 | I75: =_xlfn.LET( _xlpm.doi,IF(C75<>"",C75,_xlfn.TEXTAFTER(A75,"https://doi.org/")), SUBSTITUTE( SUBSTITUTE( SUBSTITUTE( SUBSTITUTE( _xlpm.doi, "/","%2F"), ":","%3A"), "<","%3C"), ">","%3E") ) -> 10.1007%2Fs004220000205 | J75: =TRIM(_xlfn.TEXTJOIN("_",FALSE(),H75,(SUBSTITUTE(SUBSTITUTE(D75," ",""), "_", "")))) -> Changizi__2001_Figure3 | K75: =I75 & "_" & SUBSTITUTE(SUBSTITUTE(SUBSTITUTE(D75,CHAR(160),"")," ",""),"_","") -> 10.1007%2Fs004220000205_Figure3 | L75: {=IFERROR(INDEX(AUTO_Public_TSV_FileList!$A$1:$A$1000,MATCH(TRUE(),EXACT(K75,IFERROR(_xlfn.TEXTBEFORE(AUTO_Public_TSV_FileList!$A$1:$A$1000,".tsv"),"")),0)),"notfound")} -> 10.1007%2Fs004220000205_Figure3.tsv | N75: figure and caption | P75: FINISHED | W75: Mammals | X75: number of cortical areas | AB75: cortical area count / scaling | AE75: secondary | AG75: summary to check more precise areas from ProjectKaskan
A76: Changizi, M. A. (2003). Relationship between number of muscles, behavioral repertoire size, and encephalization in mammals. Journal of Theoretical Biology, 220(2), 157–168. https://doi.org/10.1006/jtbi.2003.3125 | D76: Table 1 | E76: =SUBSTITUTE(SUBSTITUTE(_xlfn.TEXTBEFORE(A76,","), "-", ""), " ", "") -> Changizi | F76: {=_xlfn.LET( _xlpm.authors,_xlfn.TEXTBEFORE(A76," ("&G76&")"), _xlpm.hasAmp,ISNUMBER(SEARCH("&",_xlpm.authors)), _xlpm.hasEllipsis,ISNUMBER(SEARCH(_xlfn.UNICHAR(8230),_xlpm.authors)), _xlpm.commasBeforeAmp,IF( _xlpm.hasAmp, LEN(_xlfn.TEXTBEFORE(_xlpm.authors,"&"))-LEN(SUBSTITUTE(_xlfn.TEXTBEFORE(_xlpm.authors,"&"),",","")), 0 ), IF( _xlpm.hasEllipsis, "etal", IF( NOT(_xlpm.hasAmp), "", IF( _xlpm.commasBeforeAmp>2, "etal", SUBSTITUTE(TRIM(_xlfn.TEXTBEFORE(_xlfn.TEXTAFTER(_xlpm.authors,"& "),",")),"-","") ) ) ) )} | G76: =_xlfn.TEXTBEFORE(_xlfn.TEXTAFTER(A76, "("), ")") -> 2003 | H76: =E76 & IF(F76<>"", "_" & F76, "_") & IF(G76<>"", "_" & G76, "_") & IF(B76<>"", "_" & B76, "") -> Changizi__2003 | I76: =_xlfn.LET( _xlpm.doi,IF(C76<>"",C76,_xlfn.TEXTAFTER(A76,"https://doi.org/")), SUBSTITUTE( SUBSTITUTE( SUBSTITUTE( SUBSTITUTE( _xlpm.doi, "/","%2F"), ":","%3A"), "<","%3C"), ">","%3E") ) -> 10.1006%2Fjtbi.2003.3125 | J76: =TRIM(_xlfn.TEXTJOIN("_",FALSE(),H76,(SUBSTITUTE(SUBSTITUTE(D76," ",""), "_", "")))) -> Changizi__2003_Table1 | K76: =I76 & "_" & SUBSTITUTE(SUBSTITUTE(SUBSTITUTE(D76,CHAR(160),"")," ",""),"_","") -> 10.1006%2Fjtbi.2003.3125_Table1 | L76: {=IFERROR(INDEX(AUTO_Public_TSV_FileList!$A$1:$A$1000,MATCH(TRUE(),EXACT(K76,IFERROR(_xlfn.TEXTBEFORE(AUTO_Public_TSV_FileList!$A$1:$A$1000,".tsv"),"")),0)),"notfound")} -> 10.1006%2Fjtbi.2003.3125_Table1.tsv | M76: Estimates for number of ethobehavior types, encephalization index, and number of muscle types for mammalian orders and species. | N76: table | P76: FINISHED | R76: https://doi.org/10.1006/jtbi.2003.3125 | S76: Source table and interpretation checked against attached PDF | T76: Verify taxon names and whether values are raw, derived, or model summaries before merge | V76: comparative intelligence | W76: Mammals | X76: Behavioral repertoire size; encephalization; muscle types | Y76: Behavioral repertoire size; encephalization; muscle types | AB76: observed counts / derived index | AE76: both | AG76: Ingest this rather than averaging it with Johnson Table 1; use Johnson as provenance/cross-check.
A77: Changizi, M. A., & Shimojo, S. (2005). Parcellation and area-area connectivity as a function of neocortex size. Brain Behavior and Evolution, 66(2), 88-98. https://doi.org/10.1159/000085942 | D77: Table 1 | E77: =SUBSTITUTE(SUBSTITUTE(_xlfn.TEXTBEFORE(A77,","), "-", ""), " ", "") -> Changizi | F77: {=_xlfn.LET( _xlpm.authors,_xlfn.TEXTBEFORE(A77," ("&G77&")"), _xlpm.hasAmp,ISNUMBER(SEARCH("&",_xlpm.authors)), _xlpm.hasEllipsis,ISNUMBER(SEARCH(_xlfn.UNICHAR(8230),_xlpm.authors)), _xlpm.commasBeforeAmp,IF( _xlpm.hasAmp, LEN(_xlfn.TEXTBEFORE(_xlpm.authors,"&"))-LEN(SUBSTITUTE(_xlfn.TEXTBEFORE(_xlpm.authors,"&"),",","")), 0 ), IF( _xlpm.hasEllipsis, "etal", IF( NOT(_xlpm.hasAmp), "", IF( _xlpm.commasBeforeAmp>2, "etal", SUBSTITUTE(TRIM(_xlfn.TEXTBEFORE(_xlfn.TEXTAFTER(_xlpm.authors,"& "),",")),"-","") ) ) ) )} -> Shimojo | G77: =_xlfn.TEXTBEFORE(_xlfn.TEXTAFTER(A77, "("), ")") -> 2005 | H77: =E77 & IF(F77<>"", "_" & F77, "_") & IF(G77<>"", "_" & G77, "_") & IF(B77<>"", "_" & B77, "") -> Changizi_Shimojo_2005 | I77: =_xlfn.LET( _xlpm.doi,IF(C77<>"",C77,_xlfn.TEXTAFTER(A77,"https://doi.org/")), SUBSTITUTE( SUBSTITUTE( SUBSTITUTE( SUBSTITUTE( _xlpm.doi, "/","%2F"), ":","%3A"), "<","%3C"), ">","%3E") ) -> 10.1159%2F000085942 | J77: =TRIM(_xlfn.TEXTJOIN("_",FALSE(),H77,(SUBSTITUTE(SUBSTITUTE(D77," ",""), "_", "")))) -> Changizi_Shimojo_2005_Table1 | K77: =I77 & "_" & SUBSTITUTE(SUBSTITUTE(SUBSTITUTE(D77,CHAR(160),"")," ",""),"_","") -> 10.1159%2F000085942_Table1 | L77: {=IFERROR(INDEX(AUTO_Public_TSV_FileList!$A$1:$A$1000,MATCH(TRUE(),EXACT(K77,IFERROR(_xlfn.TEXTBEFORE(AUTO_Public_TSV_FileList!$A$1:$A$1000,".tsv"),"")),0)),"notfound")} -> 10.1159%2F000085942_Table1.tsv | N77: table | P77: FINISHED | W77: Mammals | X77: average relative size of cortical areas; brain mass; EQ | AB77: cortical parcellation (mean relative area size) | AC77: Changizi | AE77: both | AG77: 19 animals. The 4 rows with no SD (mouse, rat, ferret, cat) were COUNTED from unflattened maps, not measured - avg = 100/(2 x areas shown) reproduces all four exactly; recorded in rel_size_basis. brain_mass_g is kept in grams as printed (project unit is mg - convert x1000 at merge time).
A78: Changizi, M. A., & Shimojo, S. (2005). Parcellation and area-area connectivity as a function of neocortex size. Brain Behavior and Evolution, 66(2), 88-98. https://doi.org/10.1159/000085942 | D78: Table 2 | E78: =SUBSTITUTE(SUBSTITUTE(_xlfn.TEXTBEFORE(A78,","), "-", ""), " ", "") -> Changizi | F78: {=_xlfn.LET( _xlpm.authors,_xlfn.TEXTBEFORE(A78," ("&G78&")"), _xlpm.hasAmp,ISNUMBER(SEARCH("&",_xlpm.authors)), _xlpm.hasEllipsis,ISNUMBER(SEARCH(_xlfn.UNICHAR(8230),_xlpm.authors)), _xlpm.commasBeforeAmp,IF( _xlpm.hasAmp, LEN(_xlfn.TEXTBEFORE(_xlpm.authors,"&"))-LEN(SUBSTITUTE(_xlfn.TEXTBEFORE(_xlpm.authors,"&"),",","")), 0 ), IF( _xlpm.hasEllipsis, "etal", IF( NOT(_xlpm.hasAmp), "", IF( _xlpm.commasBeforeAmp>2, "etal", SUBSTITUTE(TRIM(_xlfn.TEXTBEFORE(_xlfn.TEXTAFTER(_xlpm.authors,"& "),",")),"-","") ) ) ) )} -> Shimojo | G78: =_xlfn.TEXTBEFORE(_xlfn.TEXTAFTER(A78, "("), ")") -> 2005 | H78: =E78 & IF(F78<>"", "_" & F78, "_") & IF(G78<>"", "_" & G78, "_") & IF(B78<>"", "_" & B78, "") -> Changizi_Shimojo_2005 | I78: =_xlfn.LET( _xlpm.doi,IF(C78<>"",C78,_xlfn.TEXTAFTER(A78,"https://doi.org/")), SUBSTITUTE( SUBSTITUTE( SUBSTITUTE( SUBSTITUTE( _xlpm.doi, "/","%2F"), ":","%3A"), "<","%3C"), ">","%3E") ) -> 10.1159%2F000085942 | J78: =TRIM(_xlfn.TEXTJOIN("_",FALSE(),H78,(SUBSTITUTE(SUBSTITUTE(D78," ",""), "_", "")))) -> Changizi_Shimojo_2005_Table2 | K78: =I78 & "_" & SUBSTITUTE(SUBSTITUTE(SUBSTITUTE(D78,CHAR(160),"")," ",""),"_","") -> 10.1159%2F000085942_Table2 | L78: {=IFERROR(INDEX(AUTO_Public_TSV_FileList!$A$1:$A$1000,MATCH(TRUE(),EXACT(K78,IFERROR(_xlfn.TEXTBEFORE(AUTO_Public_TSV_FileList!$A$1:$A$1000,".tsv"),"")),0)),"notfound")} -> 10.1159%2F000085942_Table2.tsv | N78: table | P78: FINISHED | W78: Mammals | X78: relative size of V1, V2, A1, S1 and M1 (% of neocortex) | AB78: cortical area relative size (pct neocortex) | AC78: Changizi | AE78: primary | AG78: 16 animals; blanks are 'not measured', NEVER zero, and are the main hazard in this table - a shifted row misassigns M1. Mouse's row is entirely blank and is kept as printed. V2, A1, S1 and M1 are not yet in _keys/anatomy_reference.csv.
A79: Changizi, M. A., & Shimojo, S. (2005). Parcellation and area-area connectivity as a function of neocortex size. Brain Behavior and Evolution, 66(2), 88-98. https://doi.org/10.1159/000085942 | D79: Table 3 | E79: =SUBSTITUTE(SUBSTITUTE(_xlfn.TEXTBEFORE(A79,","), "-", ""), " ", "") -> Changizi | F79: {=_xlfn.LET( _xlpm.authors,_xlfn.TEXTBEFORE(A79," ("&G79&")"), _xlpm.hasAmp,ISNUMBER(SEARCH("&",_xlpm.authors)), _xlpm.hasEllipsis,ISNUMBER(SEARCH(_xlfn.UNICHAR(8230),_xlpm.authors)), _xlpm.commasBeforeAmp,IF( _xlpm.hasAmp, LEN(_xlfn.TEXTBEFORE(_xlpm.authors,"&"))-LEN(SUBSTITUTE(_xlfn.TEXTBEFORE(_xlpm.authors,"&"),",","")), 0 ), IF( _xlpm.hasEllipsis, "etal", IF( NOT(_xlpm.hasAmp), "", IF( _xlpm.commasBeforeAmp>2, "etal", SUBSTITUTE(TRIM(_xlfn.TEXTBEFORE(_xlfn.TEXTAFTER(_xlpm.authors,"& "),",")),"-","") ) ) ) )} -> Shimojo | G79: =_xlfn.TEXTBEFORE(_xlfn.TEXTAFTER(A79, "("), ")") -> 2005 | H79: =E79 & IF(F79<>"", "_" & F79, "_") & IF(G79<>"", "_" & G79, "_") & IF(B79<>"", "_" & B79, "") -> Changizi_Shimojo_2005 | I79: =_xlfn.LET( _xlpm.doi,IF(C79<>"",C79,_xlfn.TEXTAFTER(A79,"https://doi.org/")), SUBSTITUTE( SUBSTITUTE( SUBSTITUTE( SUBSTITUTE( _xlpm.doi, "/","%2F"), ":","%3A"), "<","%3C"), ">","%3E") ) -> 10.1159%2F000085942 | J79: =TRIM(_xlfn.TEXTJOIN("_",FALSE(),H79,(SUBSTITUTE(SUBSTITUTE(D79," ",""), "_", "")))) -> Changizi_Shimojo_2005_Table3 | K79: =I79 & "_" & SUBSTITUTE(SUBSTITUTE(SUBSTITUTE(D79,CHAR(160),"")," ",""),"_","") -> 10.1159%2F000085942_Table3 | L79: {=IFERROR(INDEX(AUTO_Public_TSV_FileList!$A$1:$A$1000,MATCH(TRUE(),EXACT(K79,IFERROR(_xlfn.TEXTBEFORE(AUTO_Public_TSV_FileList!$A$1:$A$1000,".tsv"),"")),0)),"notfound")} -> 10.1159%2F000085942_Table3.tsv | N79: table | P79: FINISHED | W79: Mammals | X79: number of cortical areas and area-area connections per subnetwork | AB79: cortical connectivity (areas, edges) | AC79: Changizi | AE79: secondary | AG79: 10 sensory / somato-motor subnetworks compiled from other groups' connectivity matrices.
A80: Changizi, M. A., & Shimojo, S. (2005). Parcellation and area-area connectivity as a function of neocortex size. Brain Behavior and Evolution, 66(2), 88-98. https://doi.org/10.1159/000085942 | D80: Table 4 | E80: =SUBSTITUTE(SUBSTITUTE(_xlfn.TEXTBEFORE(A80,","), "-", ""), " ", "") -> Changizi | F80: {=_xlfn.LET( _xlpm.authors,_xlfn.TEXTBEFORE(A80," ("&G80&")"), _xlpm.hasAmp,ISNUMBER(SEARCH("&",_xlpm.authors)), _xlpm.hasEllipsis,ISNUMBER(SEARCH(_xlfn.UNICHAR(8230),_xlpm.authors)), _xlpm.commasBeforeAmp,IF( _xlpm.hasAmp, LEN(_xlfn.TEXTBEFORE(_xlpm.authors,"&"))-LEN(SUBSTITUTE(_xlfn.TEXTBEFORE(_xlpm.authors,"&"),",","")), 0 ), IF( _xlpm.hasEllipsis, "etal", IF( NOT(_xlpm.hasAmp), "", IF( _xlpm.commasBeforeAmp>2, "etal", SUBSTITUTE(TRIM(_xlfn.TEXTBEFORE(_xlfn.TEXTAFTER(_xlpm.authors,"& "),",")),"-","") ) ) ) )} -> Shimojo | G80: =_xlfn.TEXTBEFORE(_xlfn.TEXTAFTER(A80, "("), ")") -> 2005 | H80: =E80 & IF(F80<>"", "_" & F80, "_") & IF(G80<>"", "_" & G80, "_") & IF(B80<>"", "_" & B80, "") -> Changizi_Shimojo_2005 | I80: =_xlfn.LET( _xlpm.doi,IF(C80<>"",C80,_xlfn.TEXTAFTER(A80,"https://doi.org/")), SUBSTITUTE( SUBSTITUTE( SUBSTITUTE( SUBSTITUTE( _xlpm.doi, "/","%2F"), ":","%3A"), "<","%3C"), ">","%3E") ) -> 10.1159%2F000085942 | J80: =TRIM(_xlfn.TEXTJOIN("_",FALSE(),H80,(SUBSTITUTE(SUBSTITUTE(D80," ",""), "_", "")))) -> Changizi_Shimojo_2005_Table4 | K80: =I80 & "_" & SUBSTITUTE(SUBSTITUTE(SUBSTITUTE(D80,CHAR(160),"")," ",""),"_","") -> 10.1159%2F000085942_Table4 | L80: {=IFERROR(INDEX(AUTO_Public_TSV_FileList!$A$1:$A$1000,MATCH(TRUE(),EXACT(K80,IFERROR(_xlfn.TEXTBEFORE(AUTO_Public_TSV_FileList!$A$1:$A$1000,".tsv"),"")),0)),"notfound")} -> 10.1159%2F000085942_Table4.tsv | N80: table | P80: FINISHED | W80: Mammals | X80: area-area connections per cortical area | AB80: cortical connectivity (connections per area) | AC80: Changizi | AE80: secondary | AG80: 38 rows / 11 animals. 3 rows print 'not shown here' -> NA with area_not_shown flagged. Table 4 prints 'TD' twice in the tree-shrew block; the second is almost certainly TI (Lyon et al. 1998) - kept verbatim, flagged. The opossum here is Kahn et al. 2000 (Monodelphis domestica), NOT the Didelphis of Table 1.
A81: Changizi, M. A., & Shimojo, S. (2005). Parcellation and area-area connectivity as a function of neocortex size. Brain Behavior and Evolution, 66(2), 88-98. https://doi.org/10.1159/000085942 | D81: Table 5 | E81: =SUBSTITUTE(SUBSTITUTE(_xlfn.TEXTBEFORE(A81,","), "-", ""), " ", "") -> Changizi | F81: {=_xlfn.LET( _xlpm.authors,_xlfn.TEXTBEFORE(A81," ("&G81&")"), _xlpm.hasAmp,ISNUMBER(SEARCH("&",_xlpm.authors)), _xlpm.hasEllipsis,ISNUMBER(SEARCH(_xlfn.UNICHAR(8230),_xlpm.authors)), _xlpm.commasBeforeAmp,IF( _xlpm.hasAmp, LEN(_xlfn.TEXTBEFORE(_xlpm.authors,"&"))-LEN(SUBSTITUTE(_xlfn.TEXTBEFORE(_xlpm.authors,"&"),",","")), 0 ), IF( _xlpm.hasEllipsis, "etal", IF( NOT(_xlpm.hasAmp), "", IF( _xlpm.commasBeforeAmp>2, "etal", SUBSTITUTE(TRIM(_xlfn.TEXTBEFORE(_xlfn.TEXTAFTER(_xlpm.authors,"& "),",")),"-","") ) ) ) )} -> Shimojo | G81: =_xlfn.TEXTBEFORE(_xlfn.TEXTAFTER(A81, "("), ")") -> 2005 | H81: =E81 & IF(F81<>"", "_" & F81, "_") & IF(G81<>"", "_" & G81, "_") & IF(B81<>"", "_" & B81, "") -> Changizi_Shimojo_2005 | I81: =_xlfn.LET( _xlpm.doi,IF(C81<>"",C81,_xlfn.TEXTAFTER(A81,"https://doi.org/")), SUBSTITUTE( SUBSTITUTE( SUBSTITUTE( SUBSTITUTE( _xlpm.doi, "/","%2F"), ":","%3A"), "<","%3C"), ">","%3E") ) -> 10.1159%2F000085942 | J81: =TRIM(_xlfn.TEXTJOIN("_",FALSE(),H81,(SUBSTITUTE(SUBSTITUTE(D81," ",""), "_", "")))) -> Changizi_Shimojo_2005_Table5 | K81: =I81 & "_" & SUBSTITUTE(SUBSTITUTE(SUBSTITUTE(D81,CHAR(160),"")," ",""),"_","") -> 10.1159%2F000085942_Table5 | L81: {=IFERROR(INDEX(AUTO_Public_TSV_FileList!$A$1:$A$1000,MATCH(TRUE(),EXACT(K81,IFERROR(_xlfn.TEXTBEFORE(AUTO_Public_TSV_FileList!$A$1:$A$1000,".tsv"),"")),0)),"notfound")} -> 10.1159%2F000085942_Table5.tsv | N81: table | P81: FINISHED | W81: Mammals | X81: average number of area connections per area | AB81: cortical connectivity (mean connections per area) | AC81: Changizi | AE81: secondary | AG81: 11 rows, derived from Table 4: 10^mean(log10 x) and the sample SD of log10 x reproduce Table 5's mean AND SD to 2 dp for all 9 recomputable animals. Rat SD = 0 is a true zero (n = 1).
A82: Chaplin, T. A., Yu, H. H., Soares, J. G., Gattass, R., & Rosa, M. G. (2013). A conserved pattern of differential expansion of cortical areas in simian primates. J Neurosci, 33(38), 15120-15125. https://doi.org/10.1523/JNEUROSCI.2909-13.2013 | D82: Results Text | E82: =SUBSTITUTE(SUBSTITUTE(_xlfn.TEXTBEFORE(A82,","), "-", ""), " ", "") -> Chaplin | F82: {=_xlfn.LET( _xlpm.authors,_xlfn.TEXTBEFORE(A82," ("&G82&")"), _xlpm.hasAmp,ISNUMBER(SEARCH("&",_xlpm.authors)), _xlpm.hasEllipsis,ISNUMBER(SEARCH(_xlfn.UNICHAR(8230),_xlpm.authors)), _xlpm.commasBeforeAmp,IF( _xlpm.hasAmp, LEN(_xlfn.TEXTBEFORE(_xlpm.authors,"&"))-LEN(SUBSTITUTE(_xlfn.TEXTBEFORE(_xlpm.authors,"&"),",","")), 0 ), IF( _xlpm.hasEllipsis, "etal", IF( NOT(_xlpm.hasAmp), "", IF( _xlpm.commasBeforeAmp>2, "etal", SUBSTITUTE(TRIM(_xlfn.TEXTBEFORE(_xlfn.TEXTAFTER(_xlpm.authors,"& "),",")),"-","") ) ) ) )} -> etal | G82: =_xlfn.TEXTBEFORE(_xlfn.TEXTAFTER(A82, "("), ")") -> 2013 | H82: =E82 & IF(F82<>"", "_" & F82, "_") & IF(G82<>"", "_" & G82, "_") & IF(B82<>"", "_" & B82, "") -> Chaplin_etal_2013 | I82: =_xlfn.LET( _xlpm.doi,IF(C82<>"",C82,_xlfn.TEXTAFTER(A82,"https://doi.org/")), SUBSTITUTE( SUBSTITUTE( SUBSTITUTE( SUBSTITUTE( _xlpm.doi, "/","%2F"), ":","%3A"), "<","%3C"), ">","%3E") ) -> 10.1523%2FJNEUROSCI.2909-13.2013 | J82: =TRIM(_xlfn.TEXTJOIN("_",FALSE(),H82,(SUBSTITUTE(SUBSTITUTE(D82," ",""), "_", "")))) -> Chaplin_etal_2013_ResultsText | K82: =I82 & "_" & SUBSTITUTE(SUBSTITUTE(SUBSTITUTE(D82,CHAR(160),"")," ",""),"_","") -> 10.1523%2FJNEUROSCI.2909-13.2013_ResultsText | L82: {=IFERROR(INDEX(AUTO_Public_TSV_FileList!$A$1:$A$1000,MATCH(TRUE(),EXACT(K82,IFERROR(_xlfn.TEXTBEFORE(AUTO_Public_TSV_FileList!$A$1:$A$1000,".tsv"),"")),0)),"notfound")} -> 10.1523%2FJNEUROSCI.2909-13.2013_ResultsText.tsv | M82: Results, first paragraph — cortical surface areas of the three monkey models | N82: text | P82: FINISHED | R82: https://doi.org/10.1523/JNEUROSCI.2909-13.2013 | S82: Values, species, sexes and body masses read directly from the PDF Results text on 2026-08-31; confirmed the paper carries Figures 1-4 only and no data tables, and that the supplemental material is a video. Citation and DOI confirmed via CrossRef. | T82: Surface areas of computational cortical models, not direct anatomical measurement, and one individual per species. Whole-cortex and both-hemisphere status must be established at build before wiring into __merging_cortical_areas (compare the Demirci et al. 2023 halving rule). Macaque body mass not reported. Cebus apella value conflicts with Mota et al. 2019 (7653) by ~12 per cent; Macaca mulatta conflicts with Turner et al. 2016 (15,230). | W82: Primates | X82: cortical surface area | Y82: Total cortical surface area (mm2) | AA82: MRI using reference landmark registration | AB82: cortical surface area | AE82: primary | AG82: Three species with printed values, and it unblocks the Chaplin owner decision recorded in _checks/registry_audit_20260831.md: the registered DOI 10.1002/cne.23215 is the marmoset V1 retinotopy paper, this one is the surfaces paper. Establish the hemisphere convention before wiring into __merging_cortical_areas.
A83: Chen, Z., & Wiens, J. J. (2020). The origins of acoustic communication in vertebrates. Nature Communications, 11(1), 369. https://doi.org/10.1038/s41467-020-14356-3 | D83: Supplementary Data 3 | E83: =SUBSTITUTE(SUBSTITUTE(_xlfn.TEXTBEFORE(A83,","), "-", ""), " ", "") -> Chen | F83: {=_xlfn.LET( _xlpm.authors,_xlfn.TEXTBEFORE(A83," ("&G83&")"), _xlpm.hasAmp,ISNUMBER(SEARCH("&",_xlpm.authors)), _xlpm.hasEllipsis,ISNUMBER(SEARCH(_xlfn.UNICHAR(8230),_xlpm.authors)), _xlpm.commasBeforeAmp,IF( _xlpm.hasAmp, LEN(_xlfn.TEXTBEFORE(_xlpm.authors,"&"))-LEN(SUBSTITUTE(_xlfn.TEXTBEFORE(_xlpm.authors,"&"),",","")), 0 ), IF( _xlpm.hasEllipsis, "etal", IF( NOT(_xlpm.hasAmp), "", IF( _xlpm.commasBeforeAmp>2, "etal", SUBSTITUTE(TRIM(_xlfn.TEXTBEFORE(_xlfn.TEXTAFTER(_xlpm.authors,"& "),",")),"-","") ) ) ) )} -> Wiens | G83: =_xlfn.TEXTBEFORE(_xlfn.TEXTAFTER(A83, "("), ")") -> 2020 | H83: =E83 & IF(F83<>"", "_" & F83, "_") & IF(G83<>"", "_" & G83, "_") & IF(B83<>"", "_" & B83, "") -> Chen_Wiens_2020 | I83: =_xlfn.LET( _xlpm.doi,IF(C83<>"",C83,_xlfn.TEXTAFTER(A83,"https://doi.org/")), SUBSTITUTE( SUBSTITUTE( SUBSTITUTE( SUBSTITUTE( _xlpm.doi, "/","%2F"), ":","%3A"), "<","%3C"), ">","%3E") ) -> 10.1038%2Fs41467-020-14356-3 | J83: =TRIM(_xlfn.TEXTJOIN("_",FALSE(),H83,(SUBSTITUTE(SUBSTITUTE(D83," ",""), "_", "")))) -> Chen_Wiens_2020_SupplementaryData3 | K83: =I83 & "_" & SUBSTITUTE(SUBSTITUTE(SUBSTITUTE(D83,CHAR(160),"")," ",""),"_","") -> 10.1038%2Fs41467-020-14356-3_SupplementaryData3 | L83: {=IFERROR(INDEX(AUTO_Public_TSV_FileList!$A$1:$A$1000,MATCH(TRUE(),EXACT(K83,IFERROR(_xlfn.TEXTBEFORE(AUTO_Public_TSV_FileList!$A$1:$A$1000,".tsv"),"")),0)),"notfound")} -> 10.1038%2Fs41467-020-14356-3_SupplementaryData3.tsv | N83: table | P83: FINISHED | Q83: 41467_2020_14356_MOESM6_ESM.xlsx | R83: https://static-content.springer.com/esm/art%3A10.1038%2Fs41467-020-14356-3/MediaObjects/41467_2020_14356_MOESM6_ESM.xlsx | W83: Tetrapod vertebrates | X83: acoustic communication | Y83: dial activity (Supp 4) | AB83: behavioural (acoustic communication) | AE83: secondary
A84: Collins, C. E., Airey, D. C., Young, N. A., Leitch, D. B., & Kaas, J. H. (2010). Neuron densities vary across and within cortical areas in primates. Proc Natl Acad Sci U S A, 107(36), 15927-15932. https://doi.org/10.1073/pnas.1010356107 | D84: Dataset S1 | E84: =SUBSTITUTE(SUBSTITUTE(_xlfn.TEXTBEFORE(A84,","), "-", ""), " ", "") -> Collins | F84: {=_xlfn.LET( _xlpm.authors,_xlfn.TEXTBEFORE(A84," ("&G84&")"), _xlpm.hasAmp,ISNUMBER(SEARCH("&",_xlpm.authors)), _xlpm.hasEllipsis,ISNUMBER(SEARCH(_xlfn.UNICHAR(8230),_xlpm.authors)), _xlpm.commasBeforeAmp,IF( _xlpm.hasAmp, LEN(_xlfn.TEXTBEFORE(_xlpm.authors,"&"))-LEN(SUBSTITUTE(_xlfn.TEXTBEFORE(_xlpm.authors,"&"),",","")), 0 ), IF( _xlpm.hasEllipsis, "etal", IF( NOT(_xlpm.hasAmp), "", IF( _xlpm.commasBeforeAmp>2, "etal", SUBSTITUTE(TRIM(_xlfn.TEXTBEFORE(_xlfn.TEXTAFTER(_xlpm.authors,"& "),",")),"-","") ) ) ) )} -> etal | G84: =_xlfn.TEXTBEFORE(_xlfn.TEXTAFTER(A84, "("), ")") -> 2010 | H84: =E84 & IF(F84<>"", "_" & F84, "_") & IF(G84<>"", "_" & G84, "_") & IF(B84<>"", "_" & B84, "") -> Collins_etal_2010 | I84: =_xlfn.LET( _xlpm.doi,IF(C84<>"",C84,_xlfn.TEXTAFTER(A84,"https://doi.org/")), SUBSTITUTE( SUBSTITUTE( SUBSTITUTE( SUBSTITUTE( _xlpm.doi, "/","%2F"), ":","%3A"), "<","%3C"), ">","%3E") ) -> 10.1073%2Fpnas.1010356107 | J84: =TRIM(_xlfn.TEXTJOIN("_",FALSE(),H84,(SUBSTITUTE(SUBSTITUTE(D84," ",""), "_", "")))) -> Collins_etal_2010_DatasetS1 | K84: =I84 & "_" & SUBSTITUTE(SUBSTITUTE(SUBSTITUTE(D84,CHAR(160),"")," ",""),"_","") -> 10.1073%2Fpnas.1010356107_DatasetS1 | L84: {=IFERROR(INDEX(AUTO_Public_TSV_FileList!$A$1:$A$1000,MATCH(TRUE(),EXACT(K84,IFERROR(_xlfn.TEXTBEFORE(AUTO_Public_TSV_FileList!$A$1:$A$1000,".tsv"),"")),0)),"notfound")} -> 10.1073%2Fpnas.1010356107_DatasetS1.tsv | P84: FINISHED | W84: Primates | X84: cortical area surface area, neuron density | AB84: cortical surface area | AC84: Kaas | AE84: primary
A85: Collins, C. E., Turner, E. C., Sawyer, E. K., Reed, J. L., Young, N. A., Flaherty, D. K., & Kaas, J. H. (2016). Cortical cell and neuron density estimates in one chimpanzee hemisphere. Proc Natl Acad Sci U S A, 113(3), 740-745. https://doi.org/10.1073/pnas.1524208113 | D85: Table 1 | E85: =SUBSTITUTE(SUBSTITUTE(_xlfn.TEXTBEFORE(A85,","), "-", ""), " ", "") -> Collins | F85: {=_xlfn.LET( _xlpm.authors,_xlfn.TEXTBEFORE(A85," ("&G85&")"), _xlpm.hasAmp,ISNUMBER(SEARCH("&",_xlpm.authors)), _xlpm.hasEllipsis,ISNUMBER(SEARCH(_xlfn.UNICHAR(8230),_xlpm.authors)), _xlpm.commasBeforeAmp,IF( _xlpm.hasAmp, LEN(_xlfn.TEXTBEFORE(_xlpm.authors,"&"))-LEN(SUBSTITUTE(_xlfn.TEXTBEFORE(_xlpm.authors,"&"),",","")), 0 ), IF( _xlpm.hasEllipsis, "etal", IF( NOT(_xlpm.hasAmp), "", IF( _xlpm.commasBeforeAmp>2, "etal", SUBSTITUTE(TRIM(_xlfn.TEXTBEFORE(_xlfn.TEXTAFTER(_xlpm.authors,"& "),",")),"-","") ) ) ) )} -> etal | G85: =_xlfn.TEXTBEFORE(_xlfn.TEXTAFTER(A85, "("), ")") -> 2016 | H85: =E85 & IF(F85<>"", "_" & F85, "_") & IF(G85<>"", "_" & G85, "_") & IF(B85<>"", "_" & B85, "") -> Collins_etal_2016 | I85: =_xlfn.LET( _xlpm.doi,IF(C85<>"",C85,_xlfn.TEXTAFTER(A85,"https://doi.org/")), SUBSTITUTE( SUBSTITUTE( SUBSTITUTE( SUBSTITUTE( _xlpm.doi, "/","%2F"), ":","%3A"), "<","%3C"), ">","%3E") ) -> 10.1073%2Fpnas.1524208113 | J85: =TRIM(_xlfn.TEXTJOIN("_",FALSE(),H85,(SUBSTITUTE(SUBSTITUTE(D85," ",""), "_", "")))) -> Collins_etal_2016_Table1 | K85: =I85 & "_" & SUBSTITUTE(SUBSTITUTE(SUBSTITUTE(D85,CHAR(160),"")," ",""),"_","") -> 10.1073%2Fpnas.1524208113_Table1 | L85: {=IFERROR(INDEX(AUTO_Public_TSV_FileList!$A$1:$A$1000,MATCH(TRUE(),EXACT(K85,IFERROR(_xlfn.TEXTBEFORE(AUTO_Public_TSV_FileList!$A$1:$A$1000,".tsv"),"")),0)),"notfound")} -> 10.1073%2Fpnas.1524208113_Table1.tsv | M85: Cortical cell and neuron density in one chimpanzee hemisphere (Table 1) | N85: table | P85: FINISHED | W85: Primates | X85: cortical neuron/cell density | AA85: isotropic fractionator | AB85: neuron/cell density & number | AC85: Kaas | AD85: HH | AE85: primary
A86: de Jager, E., Prigge, L., Amod, N., Oettle, A., & Beaudet, A. (2022). Exploring the relationship between soft and hard tissues: The example of vertebral arteries and transverse foramina. J Anat, 241(2), 447-452. https://doi.org/10.1111/joa.13681 | D86: Table 1 | E86: =SUBSTITUTE(SUBSTITUTE(_xlfn.TEXTBEFORE(A86,","), "-", ""), " ", "") -> deJager | F86: {=_xlfn.LET( _xlpm.authors,_xlfn.TEXTBEFORE(A86," ("&G86&")"), _xlpm.hasAmp,ISNUMBER(SEARCH("&",_xlpm.authors)), _xlpm.hasEllipsis,ISNUMBER(SEARCH(_xlfn.UNICHAR(8230),_xlpm.authors)), _xlpm.commasBeforeAmp,IF( _xlpm.hasAmp, LEN(_xlfn.TEXTBEFORE(_xlpm.authors,"&"))-LEN(SUBSTITUTE(_xlfn.TEXTBEFORE(_xlpm.authors,"&"),",","")), 0 ), IF( _xlpm.hasEllipsis, "etal", IF( NOT(_xlpm.hasAmp), "", IF( _xlpm.commasBeforeAmp>2, "etal", SUBSTITUTE(TRIM(_xlfn.TEXTBEFORE(_xlfn.TEXTAFTER(_xlpm.authors,"& "),",")),"-","") ) ) ) )} -> etal | G86: =_xlfn.TEXTBEFORE(_xlfn.TEXTAFTER(A86, "("), ")") -> 2022 | H86: =E86 & IF(F86<>"", "_" & F86, "_") & IF(G86<>"", "_" & G86, "_") & IF(B86<>"", "_" & B86, "") -> deJager_etal_2022 | I86: =_xlfn.LET( _xlpm.doi,IF(C86<>"",C86,_xlfn.TEXTAFTER(A86,"https://doi.org/")), SUBSTITUTE( SUBSTITUTE( SUBSTITUTE( SUBSTITUTE( _xlpm.doi, "/","%2F"), ":","%3A"), "<","%3C"), ">","%3E") ) -> 10.1111%2Fjoa.13681 | J86: =TRIM(_xlfn.TEXTJOIN("_",FALSE(),H86,(SUBSTITUTE(SUBSTITUTE(D86," ",""), "_", "")))) -> deJager_etal_2022_Table1 | K86: =I86 & "_" & SUBSTITUTE(SUBSTITUTE(SUBSTITUTE(D86,CHAR(160),"")," ",""),"_","") -> 10.1111%2Fjoa.13681_Table1 | L86: {=IFERROR(INDEX(AUTO_Public_TSV_FileList!$A$1:$A$1000,MATCH(TRUE(),EXACT(K86,IFERROR(_xlfn.TEXTBEFORE(AUTO_Public_TSV_FileList!$A$1:$A$1000,".tsv"),"")),0)),"notfound")} -> 10.1111%2Fjoa.13681_Table1.tsv | P86: FINISHED
A87: de Magalhães, J. P., Abidi, Z., Dos Santos, G. A., Avelar, R. A., Barardo, D., Chatsirisupachai, K., Clark, P., De-Souza, E. A., Johnson, E. J., Lopes, I., Novoa, G., Senez, L., Talay, A., Thornton, D., & To, P. K. P. (2024). Human Ageing Genomic Resources: updates on key databases in ageing research. Nucleic Acids Res, 52(D1), D900-D908. https://doi.org/10.1093/nar/gkad927 | D87: anage_data.txt | E87: =SUBSTITUTE(SUBSTITUTE(_xlfn.TEXTBEFORE(A87,","), "-", ""), " ", "") -> deMagalhães | F87: {=_xlfn.LET( _xlpm.authors,_xlfn.TEXTBEFORE(A87," ("&G87&")"), _xlpm.hasAmp,ISNUMBER(SEARCH("&",_xlpm.authors)), _xlpm.hasEllipsis,ISNUMBER(SEARCH(_xlfn.UNICHAR(8230),_xlpm.authors)), _xlpm.commasBeforeAmp,IF( _xlpm.hasAmp, LEN(_xlfn.TEXTBEFORE(_xlpm.authors,"&"))-LEN(SUBSTITUTE(_xlfn.TEXTBEFORE(_xlpm.authors,"&"),",","")), 0 ), IF( _xlpm.hasEllipsis, "etal", IF( NOT(_xlpm.hasAmp), "", IF( _xlpm.commasBeforeAmp>2, "etal", SUBSTITUTE(TRIM(_xlfn.TEXTBEFORE(_xlfn.TEXTAFTER(_xlpm.authors,"& "),",")),"-","") ) ) ) )} -> etal | G87: =_xlfn.TEXTBEFORE(_xlfn.TEXTAFTER(A87, "("), ")") -> 2024 | H87: =E87 & IF(F87<>"", "_" & F87, "_") & IF(G87<>"", "_" & G87, "_") & IF(B87<>"", "_" & B87, "") -> deMagalhães_etal_2024 | I87: =_xlfn.LET(_xlpm.doi,IF(C87<>"",C87,_xlfn.TEXTAFTER(A87,"https://doi.org/")),SUBSTITUTE(SUBSTITUTE(SUBSTITUTE(SUBSTITUTE(_xlpm.doi,"/","%2F"),":","%3A"),"<","%3C"),">","%3E")) -> 10.1093%2Fnar%2Fgkad927 | J87: =TRIM(_xlfn.TEXTJOIN("_",FALSE(),H87,(SUBSTITUTE(SUBSTITUTE(D87," ",""), "_", "")))) -> deMagalhães_etal_2024_anagedata.txt | K87: =I87 & "_" & SUBSTITUTE(SUBSTITUTE(SUBSTITUTE(D87,CHAR(160),"")," ",""),"_","") -> 10.1093%2Fnar%2Fgkad927_anagedata.txt | L87: {=IFERROR(INDEX(AUTO_Public_TSV_FileList!$A$1:$A$1000,MATCH(TRUE(),EXACT(K87,IFERROR(_xlfn.TEXTBEFORE(AUTO_Public_TSV_FileList!$A$1:$A$1000,".tsv"),"")),0)),"notfound")} -> 10.1093%2Fnar%2Fgkad927_anagedata.txt.tsv | M87: AnAge database export (Build 15) -- full species table | N87: database export (tab-delimited txt) | O87: Digital-native source; no snapshot needed (untouched download is the frozen copy). Public TSV, README and definitions.csv all built and uploaded 2026-09-24; flag corrected from BUILT (pending validation) to FINISHED 2026-09-25 once the TSV's presence in __Public/comparative-data was confirmed directly (the AUTO_Public_TSV_FileList cache had not yet been refreshed by _tools/file_list.R, so it still showed no match). | P87: FINISHED | R87: https://genomics.senescence.info/species/index.html | T87: no reference bibliography distributed with export; HAGRID not stable across builds | V87: life history / longevity | W87: all taxa (1,349 of 4,645 rows are Mammalia) | X87: maximum longevity; sexual maturity; gestation/incubation; weaning; litter size; growth rate | Y87: metabolic rate; body temperature; mortality-rate model parameters (sparse) | AA87: database compilation from primary literature (per-record reference codes) | AB87: time (days/yrs); mass (g); count; rate | AE87: secondary | AF87: AnAge's own primary-literature references (per Source_ref / References columns; bibliography not distributed) | AG87: General-purpose life-history covariate table; Mammalia subset most relevant to this project
A88: de Sousa, A. A. (2008). Hominoid brain organization: Histometric and morphometric comparisons of visual brain structures [Ph.D., The George Washington University]. United States -- District of Columbia. http://proquest.umi.com/pqdweb?did=1564016401&Fmt=7&clientId=5241&RQT=309&VName=PQD | C88: UMI:3311323 | D88: Suppl. Table 5.2 | E88: =SUBSTITUTE(SUBSTITUTE(_xlfn.TEXTBEFORE(A88,","), "-", ""), " ", "") -> deSousa | F88: {=_xlfn.LET( _xlpm.authors,_xlfn.TEXTBEFORE(A88," ("&G88&")"), _xlpm.hasAmp,ISNUMBER(SEARCH("&",_xlpm.authors)), _xlpm.hasEllipsis,ISNUMBER(SEARCH(_xlfn.UNICHAR(8230),_xlpm.authors)), _xlpm.commasBeforeAmp,IF( _xlpm.hasAmp, LEN(_xlfn.TEXTBEFORE(_xlpm.authors,"&"))-LEN(SUBSTITUTE(_xlfn.TEXTBEFORE(_xlpm.authors,"&"),",","")), 0 ), IF( _xlpm.hasEllipsis, "etal", IF( NOT(_xlpm.hasAmp), "", IF( _xlpm.commasBeforeAmp>2, "etal", SUBSTITUTE(TRIM(_xlfn.TEXTBEFORE(_xlfn.TEXTAFTER(_xlpm.authors,"& "),",")),"-","") ) ) ) )} | G88: =_xlfn.TEXTBEFORE(_xlfn.TEXTAFTER(A88, "("), ")") -> 2008 | H88: =E88 & IF(F88<>"", "_" & F88, "_") & IF(G88<>"", "_" & G88, "_") & IF(B88<>"", "_" & B88, "") -> deSousa__2008 | I88: =_xlfn.LET(_xlpm.doi,IF(C88<>"",C88,_xlfn.TEXTAFTER(A88,"https://doi.org/")),SUBSTITUTE(SUBSTITUTE(SUBSTITUTE(SUBSTITUTE(_xlpm.doi,"/","%2F"),":","%3A"),"<","%3C"),">","%3E")) -> UMI%3A3311323 | J88: =TRIM(_xlfn.TEXTJOIN("_",FALSE(),H88,(SUBSTITUTE(SUBSTITUTE(D88," ",""), "_", "")))) -> deSousa__2008_Suppl.Table5.2 | K88: =I88 & "_" & SUBSTITUTE(SUBSTITUTE(SUBSTITUTE(D88,CHAR(160),"")," ",""),"_","") -> UMI%3A3311323_Suppl.Table5.2 | L88: {=IFERROR(INDEX(AUTO_Public_TSV_FileList!$A$1:$A$1000,MATCH(TRUE(),EXACT(K88,IFERROR(_xlfn.TEXTBEFORE(AUTO_Public_TSV_FileList!$A$1:$A$1000,".tsv"),"")),0)),"notfound")} -> UMI%3A3311323_Suppl.Table5.2.tsv | M88: Suppl. Table 5.2 Comparison of adjusted values to published data (Semendeferi 1998, 2002)
A89: de Sousa, A. A. (2008). Hominoid brain organization: Histometric and morphometric comparisons of visual brain structures [Ph.D., The George Washington University]. United States -- District of Columbia. http://proquest.umi.com/pqdweb?did=1564016401&Fmt=7&clientId=5241&RQT=309&VName=PQD | C89: UMI:3311323 | D89: Table 4.1 | E89: =SUBSTITUTE(SUBSTITUTE(_xlfn.TEXTBEFORE(A89,","), "-", ""), " ", "") -> deSousa | F89: {=_xlfn.LET( _xlpm.authors,_xlfn.TEXTBEFORE(A89," ("&G89&")"), _xlpm.hasAmp,ISNUMBER(SEARCH("&",_xlpm.authors)), _xlpm.hasEllipsis,ISNUMBER(SEARCH(_xlfn.UNICHAR(8230),_xlpm.authors)), _xlpm.commasBeforeAmp,IF( _xlpm.hasAmp, LEN(_xlfn.TEXTBEFORE(_xlpm.authors,"&"))-LEN(SUBSTITUTE(_xlfn.TEXTBEFORE(_xlpm.authors,"&"),",","")), 0 ), IF( _xlpm.hasEllipsis, "etal", IF( NOT(_xlpm.hasAmp), "", IF( _xlpm.commasBeforeAmp>2, "etal", SUBSTITUTE(TRIM(_xlfn.TEXTBEFORE(_xlfn.TEXTAFTER(_xlpm.authors,"& "),",")),"-","") ) ) ) )} | G89: =_xlfn.TEXTBEFORE(_xlfn.TEXTAFTER(A89, "("), ")") -> 2008 | H89: =E89 & IF(F89<>"", "_" & F89, "_") & IF(G89<>"", "_" & G89, "_") & IF(B89<>"", "_" & B89, "") -> deSousa__2008 | I89: =_xlfn.LET(_xlpm.doi,IF(C89<>"",C89,_xlfn.TEXTAFTER(A89,"https://doi.org/")),SUBSTITUTE(SUBSTITUTE(SUBSTITUTE(SUBSTITUTE(_xlpm.doi,"/","%2F"),":","%3A"),"<","%3C"),">","%3E")) -> UMI%3A3311323 | J89: =TRIM(_xlfn.TEXTJOIN("_",FALSE(),H89,(SUBSTITUTE(SUBSTITUTE(D89," ",""), "_", "")))) -> deSousa__2008_Table4.1 | K89: =I89 & "_" & SUBSTITUTE(SUBSTITUTE(SUBSTITUTE(D89,CHAR(160),"")," ",""),"_","") -> UMI%3A3311323_Table4.1 | L89: {=IFERROR(INDEX(AUTO_Public_TSV_FileList!$A$1:$A$1000,MATCH(TRUE(),EXACT(K89,IFERROR(_xlfn.TEXTBEFORE(AUTO_Public_TSV_FileList!$A$1:$A$1000,".tsv"),"")),0)),"notfound")} -> UMI%3A3311323_Table4.1.tsv | M89: Table 4.1 Samples used in analyses of V1, V2, VP and V5 (9 specimens)
A90: de Sousa, A. A. (2008). Hominoid brain organization: Histometric and morphometric comparisons of visual brain structures [Ph.D., The George Washington University]. United States -- District of Columbia. http://proquest.umi.com/pqdweb?did=1564016401&Fmt=7&clientId=5241&RQT=309&VName=PQD | C90: UMI:3311323 | D90: Table 5.1 | E90: =SUBSTITUTE(SUBSTITUTE(_xlfn.TEXTBEFORE(A90,","), "-", ""), " ", "") -> deSousa | F90: {=_xlfn.LET( _xlpm.authors,_xlfn.TEXTBEFORE(A90," ("&G90&")"), _xlpm.hasAmp,ISNUMBER(SEARCH("&",_xlpm.authors)), _xlpm.hasEllipsis,ISNUMBER(SEARCH(_xlfn.UNICHAR(8230),_xlpm.authors)), _xlpm.commasBeforeAmp,IF( _xlpm.hasAmp, LEN(_xlfn.TEXTBEFORE(_xlpm.authors,"&"))-LEN(SUBSTITUTE(_xlfn.TEXTBEFORE(_xlpm.authors,"&"),",","")), 0 ), IF( _xlpm.hasEllipsis, "etal", IF( NOT(_xlpm.hasAmp), "", IF( _xlpm.commasBeforeAmp>2, "etal", SUBSTITUTE(TRIM(_xlfn.TEXTBEFORE(_xlfn.TEXTAFTER(_xlpm.authors,"& "),",")),"-","") ) ) ) )} | G90: =_xlfn.TEXTBEFORE(_xlfn.TEXTAFTER(A90, "("), ")") -> 2008 | H90: =E90 & IF(F90<>"", "_" & F90, "_") & IF(G90<>"", "_" & G90, "_") & IF(B90<>"", "_" & B90, "") -> deSousa__2008 | I90: =_xlfn.LET(_xlpm.doi,IF(C90<>"",C90,_xlfn.TEXTAFTER(A90,"https://doi.org/")),SUBSTITUTE(SUBSTITUTE(SUBSTITUTE(SUBSTITUTE(_xlpm.doi,"/","%2F"),":","%3A"),"<","%3C"),">","%3E")) -> UMI%3A3311323 | J90: =TRIM(_xlfn.TEXTJOIN("_",FALSE(),H90,(SUBSTITUTE(SUBSTITUTE(D90," ",""), "_", "")))) -> deSousa__2008_Table5.1 | K90: =I90 & "_" & SUBSTITUTE(SUBSTITUTE(SUBSTITUTE(D90,CHAR(160),"")," ",""),"_","") -> UMI%3A3311323_Table5.1 | L90: {=IFERROR(INDEX(AUTO_Public_TSV_FileList!$A$1:$A$1000,MATCH(TRUE(),EXACT(K90,IFERROR(_xlfn.TEXTBEFORE(AUTO_Public_TSV_FileList!$A$1:$A$1000,".tsv"),"")),0)),"notfound")} -> UMI%3A3311323_Table5.1.tsv | M90: Table 5.1 Specimens and volumes
A91: de Sousa, A. A. (2008). Hominoid brain organization: Histometric and morphometric comparisons of visual brain structures [Ph.D., The George Washington University]. United States -- District of Columbia. http://proquest.umi.com/pqdweb?did=1564016401&Fmt=7&clientId=5241&RQT=309&VName=PQD | C91: UMI:3311323 | D91: Table 5.6 | E91: =SUBSTITUTE(SUBSTITUTE(_xlfn.TEXTBEFORE(A91,","), "-", ""), " ", "") -> deSousa | F91: {=_xlfn.LET( _xlpm.authors,_xlfn.TEXTBEFORE(A91," ("&G91&")"), _xlpm.hasAmp,ISNUMBER(SEARCH("&",_xlpm.authors)), _xlpm.hasEllipsis,ISNUMBER(SEARCH(_xlfn.UNICHAR(8230),_xlpm.authors)), _xlpm.commasBeforeAmp,IF( _xlpm.hasAmp, LEN(_xlfn.TEXTBEFORE(_xlpm.authors,"&"))-LEN(SUBSTITUTE(_xlfn.TEXTBEFORE(_xlpm.authors,"&"),",","")), 0 ), IF( _xlpm.hasEllipsis, "etal", IF( NOT(_xlpm.hasAmp), "", IF( _xlpm.commasBeforeAmp>2, "etal", SUBSTITUTE(TRIM(_xlfn.TEXTBEFORE(_xlfn.TEXTAFTER(_xlpm.authors,"& "),",")),"-","") ) ) ) )} | G91: =_xlfn.TEXTBEFORE(_xlfn.TEXTAFTER(A91, "("), ")") -> 2008 | H91: =E91 & IF(F91<>"", "_" & F91, "_") & IF(G91<>"", "_" & G91, "_") & IF(B91<>"", "_" & B91, "") -> deSousa__2008 | I91: =_xlfn.LET(_xlpm.doi,IF(C91<>"",C91,_xlfn.TEXTAFTER(A91,"https://doi.org/")),SUBSTITUTE(SUBSTITUTE(SUBSTITUTE(SUBSTITUTE(_xlpm.doi,"/","%2F"),":","%3A"),"<","%3C"),">","%3E")) -> UMI%3A3311323 | J91: =TRIM(_xlfn.TEXTJOIN("_",FALSE(),H91,(SUBSTITUTE(SUBSTITUTE(D91," ",""), "_", "")))) -> deSousa__2008_Table5.6 | K91: =I91 & "_" & SUBSTITUTE(SUBSTITUTE(SUBSTITUTE(D91,CHAR(160),"")," ",""),"_","") -> UMI%3A3311323_Table5.6 | L91: {=IFERROR(INDEX(AUTO_Public_TSV_FileList!$A$1:$A$1000,MATCH(TRUE(),EXACT(K91,IFERROR(_xlfn.TEXTBEFORE(AUTO_Public_TSV_FileList!$A$1:$A$1000,".tsv"),"")),0)),"notfound")} -> UMI%3A3311323_Table5.6.tsv | M91: Table 5.6 Species mean volumes of cortical areas and brain nuclei
